code/ref/e18-10-neurons/src/sync_fifo.v
module FIFObuffer( Clk, 

                   dataIn, 

                   RD, 

                   WR, 

                   EN, 

                   dataOut, 

                   Rst,

                   EMPTY, 

                   FULL 

                   ); 

input  Clk, 

       RD, 

       WR, 

       EN, 

       Rst;

output  EMPTY, 

        FULL;

input   [31:0]    dataIn;

output reg [31:0] dataOut; // internal registers 

reg [2:0]  Count = 0; 

reg [31:0] FIFO [0:7]; 

reg [2:0]  readCounter = 0, 

           writeCounter = 0; 

assign EMPTY = (Count==0)? 1'b1:1'b0; 

assign FULL = (Count==8)? 1'b1:1'b0; 

always @ (posedge Clk) 

begin 

 if (EN==0); 

 else begin 

  if (Rst) begin 

   readCounter = 0; 

   writeCounter = 0; 

  end 

  else if (RD ==1'b1 && Count!=0) begin 

   dataOut  = FIFO[readCounter]; 

   readCounter = readCounter+1; 

  end 

  else if (WR==1'b1 && Count<8) begin

   FIFO[writeCounter]  = dataIn; 

   writeCounter  = writeCounter+1; 

  end 

  else; 

 end 

 if (writeCounter==8) 

  writeCounter=0; 

 else if (readCounter==8) 

  readCounter=0; 

 else;

 if (readCounter > writeCounter) begin 

  Count=readCounter-writeCounter; 

 end 

 else if (writeCounter > readCounter) 

  Count=writeCounter-readCounter; 

 else;

end 

endmodule

code/ref/e18-10-neurons/src/sync_fifo_tb.v
`timescale 1ns / 1ps

module FIFObuffer_tb;

 // Inputs

 reg Clk;

 reg [31:0] dataIn;

 reg RD;

 reg WR;

 reg EN;

 reg Rst;

 // Outputs

 wire [31:0] dataOut;

 wire EMPTY;

 wire FULL;

 // Instantiate the Unit Under Test (UUT)

 FIFObuffer uut (

                  .Clk(Clk), 

                  .dataIn(dataIn), 

                  .RD(RD), 

                  .WR(WR), 

                  .EN(EN), 

                  .dataOut(dataOut), 

                  .Rst(Rst), 

                  .EMPTY(EMPTY), 

                  .FULL(FULL)

                  );

 initial begin

  // Initialize Inputs

  Clk  = 1'b0;

  dataIn  = 32'h0;

  RD  = 1'b0;

  WR  = 1'b0;

  EN  = 1'b0;

  Rst  = 1'b1;

  // Wait 100 ns for global reset to finish

  #100;        

  // Add stimulus here

  EN  = 1'b1;

  Rst  = 1'b1;

  #20;

  Rst  = 1'b0;

  WR  = 1'b1;

  dataIn  = 32'h0;

  #20;

  dataIn  = 32'h1;

  #20;

  dataIn  = 32'h2;

  #20;

  dataIn  = 32'h3;

  #20;

  dataIn  = 32'h4;

  #20;

  WR = 1'b0;

  RD = 1'b1;  

  #600
  $finish;

 end 

   always #10 Clk = ~Clk;   

// Observe the timing on gtkwave
    initial begin
        $dumpfile("sync_fifo.vcd");
        $dumpvars(0,FIFObuffer_tb);
    end 

endmodule

code/ref/e18-10-neurons/src/sync_fifo.vcd
$date
	Wed Jul  3 14:04:18 2024
$end
$version
	Icarus Verilog
$end
$timescale
	1ps
$end
$scope module FIFObuffer_tb $end
$var wire 32 ! dataOut [31:0] $end
$var wire 1 " FULL $end
$var wire 1 # EMPTY $end
$var reg 1 $ Clk $end
$var reg 1 % EN $end
$var reg 1 & RD $end
$var reg 1 ' Rst $end
$var reg 1 ( WR $end
$var reg 32 ) dataIn [31:0] $end
$scope module uut $end
$var wire 1 $ Clk $end
$var wire 1 % EN $end
$var wire 1 & RD $end
$var wire 1 ' Rst $end
$var wire 1 ( WR $end
$var wire 32 * dataIn [31:0] $end
$var wire 1 " FULL $end
$var wire 1 # EMPTY $end
$var reg 3 + Count [2:0] $end
$var reg 32 , dataOut [31:0] $end
$var reg 3 - readCounter [2:0] $end
$var reg 3 . writeCounter [2:0] $end
$upscope $end
$upscope $end
$enddefinitions $end
$comment Show the parameter values. $end
$dumpall
$end
#0
$dumpvars
b0 .
b0 -
bx ,
b0 +
b0 *
b0 )
0(
1'
0&
0%
0$
1#
0"
bx !
$end
#10000
1$
#20000
0$
#30000
1$
#40000
0$
#50000
1$
#60000
0$
#70000
1$
#80000
0$
#90000
1$
#100000
0$
1%
#110000
1$
#120000
0$
1(
0'
#130000
0#
b1 +
b1 .
1$
#140000
0$
b1 )
b1 *
#150000
b10 +
b10 .
1$
#160000
0$
b10 )
b10 *
#170000
b11 +
b11 .
1$
#180000
0$
b11 )
b11 *
#190000
b100 +
b100 .
1$
#200000
0$
b100 )
b100 *
#210000
b101 +
b101 .
1$
#220000
0$
1&
0(
#230000
b100 +
b1 -
b0 !
b0 ,
1$
#240000
0$
#250000
b11 +
b10 -
b1 !
b1 ,
1$
#260000
0$
#270000
b10 +
b11 -
b10 !
b10 ,
1$
#280000
0$
#290000
b1 +
b100 -
b11 !
b11 ,
1$
#300000
0$
#310000
b101 -
b100 !
b100 ,
1$
#320000
0$
#330000
b110 -
bx !
bx ,
1$
#340000
0$
#350000
b10 +
b111 -
1$
#360000
0$
#370000
b101 +
b0 -
1$
#380000
0$
#390000
b100 +
b1 -
b0 !
b0 ,
1$
#400000
0$
#410000
b11 +
b10 -
b1 !
b1 ,
1$
#420000
0$
#430000
b10 +
b11 -
b10 !
b10 ,
1$
#440000
0$
#450000
b1 +
b100 -
b11 !
b11 ,
1$
#460000
0$
#470000
b101 -
b100 !
b100 ,
1$
#480000
0$
#490000
b110 -
bx !
bx ,
1$
#500000
0$
#510000
b10 +
b111 -
1$
#520000
0$
#530000
b101 +
b0 -
1$
#540000
0$
#550000
b100 +
b1 -
b0 !
b0 ,
1$
#560000
0$
#570000
b11 +
b10 -
b1 !
b1 ,
1$
#580000
0$
#590000
b10 +
b11 -
b10 !
b10 ,
1$
#600000
0$
#610000
b1 +
b100 -
b11 !
b11 ,
1$
#620000
0$
#630000
b101 -
b100 !
b100 ,
1$
#640000
0$
#650000
b110 -
bx !
bx ,
1$
#660000
0$
#670000
b10 +
b111 -
1$
#680000
0$
#690000
b101 +
b0 -
1$
#700000
0$
#710000
b100 +
b1 -
b0 !
b0 ,
1$
#720000
0$
#730000
b11 +
b10 -
b1 !
b1 ,
1$
#740000
0$
#750000
b10 +
b11 -
b10 !
b10 ,
1$
#760000
0$
#770000
b1 +
b100 -
b11 !
b11 ,
1$
#780000
0$
#790000
b101 -
b100 !
b100 ,
1$
#800000
0$
#810000
b110 -
bx !
bx ,
1$
