utils/encording.v
// Decay modes
`define LIF0 3'b000
`define LIF2 3'b001
`define LIF4 3'b010
`define LIF8 3'b011
`define LIF24 3'b100
`define IZHI 3'b101
`define QUAD 3'b110
`define IDLE 3'b111

// Adder model
`define LIF 2'b00
`define IZHI_AD 2'b01
`define QLIF 2'b10

// Adder init mode
`define DEFAULT 3'b000
`define A 3'b001
`define B 3'b010
`define C 3'b011
`define D 3'b100
`define VT 3'b101
`define U 3'b110

utils/32bit_mul.v
module multiplier_32bit(
    input wire clk,
    input wire rst,
    input wire start,
    input wire [31:0] A,
    input wire [31:0] B,
    output reg [63:0] result,
    output reg done
);
    
    reg [31:0] multiplicand, multiplier;
    reg [63:0] product;
    reg [5:0] count;
    reg running;

    always @(posedge rst) begin
        multiplicand <= 0;
        multiplier <= 0;
        product <= 0;
        count <= 0;
        running <= 0;
        done <= 0;
    end

    always @(posedge start) begin
        multiplicand <= A;
        multiplier <= B;
        product <= 0;
        count <= 0;
        running <= 1;
        done <= 0;
    end

    always @(posedge clk) begin
        if (running) begin
            if (count < 32) begin
                if (multiplier[0] == 1'b1) begin
                    product = product + ({32'b0, multiplicand} << count);
                end
                multiplier = multiplier >> 1;
                count = count + 1;
            end else begin
                result <= product;
                done <= 1;
                running <= 0;
            end
        end
    end

endmodule

adder/adder.v
`timescale 1ns/100ps
`include "../utils/32bit_mul.v"
`include "../utils/encording.v"

module potential_adder (
    input wire clk,
    input wire rst,        
    input wire time_step,      
    input wire [31:0] input_weight, 
    input wire [31:0] decayed_potential,
    input wire [1:0] model,
    input wire [2:0] init_mode,
    input wire load,
    
    output reg [31:0] final_potential, 
    output reg done,
    output reg spike
);

    // Common Signals
    reg [31:0] weight_added;
    reg [31:0] u;

    // Internal Signals for Izhikevich Model
    wire [63:0] bv, a_bv_u;
    wire [31:0] bv_u;
    reg [31:0] a, b, c, d, v_threshold;
    
    reg bv_start, abv_start;
    wire bv_done, abv_done;

    multiplier_32bit multIzhiBV (
        .clk(clk),
        .rst(time_step),
        .start(bv_start),
        .A(b),
        .B(decayed_potential),
        .result(bv),
        .done(bv_done)
    );

    multiplier_32bit multIzhiaBVu (
        .clk(clk),
        .rst(time_step),
        .start(abv_start),
        .A(a),
        .B(bv_u),
        .result(a_bv_u),
        .done(abv_done)
    );

    assign bv_u = bv[31:0] - u;

    always @(posedge bv_done) begin
        bv_start <= 0;
        #10 abv_start <= 1;
    end

    always @(posedge load) begin
        if (init_mode == `A) begin
            a <= input_weight;
        end else if (init_mode == `B) begin
            b <= input_weight;
        end else if (init_mode == `C) begin
            c <= input_weight;
        end else if (init_mode == `D) begin
            d <= input_weight;
        end else if (init_mode == `VT) begin
            v_threshold <= input_weight;
        end else if (init_mode == `U) begin
            u <= input_weight;
        end
    end

    always @(posedge time_step) begin
        done <= 0;
        spike <= 0;
        if (init_mode == `DEFAULT) begin
            if (model == `LIF) begin
                weight_added <= input_weight + decayed_potential;
            end else if (model == `IZHI) begin
                weight_added <= input_weight + decayed_potential - u;
                bv_start <= 1;
                abv_start <= 0;
            end else if (model == `QLIF) begin
                weight_added <= input_weight + decayed_potential;
            end
        end
    end

    always @(posedge clk) begin
        if (rst) begin
            final_potential <= 0;
            done <= 0;
            spike <= 0;
            a <= 0;
            b <= 0;
            c <= 0;
            d <= 0;
            v_threshold <= 0;
            u <= 0;
        end else if (init_mode == `DEFAULT) begin
            if(model == `LIF) begin
                spike <= (weight_added > v_threshold);
                final_potential <= (weight_added > v_threshold) ? (weight_added - v_threshold) : weight_added;
                done <= 1;
            end else if (model == `IZHI) begin
                if(abv_done) begin
                    spike <= (weight_added > v_threshold);
                    final_potential <= (weight_added > v_threshold) ? c : weight_added;
                    u <= (weight_added > v_threshold) ? u + d : a_bv_u[31:0];
                    done <= 1;
                end
            end else if (model == `QLIF) begin
                spike <= (weight_added > v_threshold);
                final_potential <= (weight_added > v_threshold) ? (weight_added - v_threshold) : weight_added;
                done <= 1;
            end
        end
    end

endmodule

adder/adder_tb.v
`timescale 1ns/100ps
`include "adder.v"

module potential_adder_tb();
    reg clk;
    reg rst;
    reg time_step;
    reg load;
    reg [31:0] input_weight;
    reg [31:0] decayed_potential;
    reg [1:0] model;
    reg [2:0] init_mode;
    
    wire [31:0] final_potential;
    wire done;
    wire spike;
    
    potential_adder uut (
        .clk(clk),
        .rst(rst),
        .time_step(time_step),
        .input_weight(input_weight),
        .decayed_potential(decayed_potential),
        .model(model),
        .init_mode(init_mode),
        .load(load),
        .final_potential(final_potential),
        .done(done),
        .spike(spike)
    );
    
    // Clock Generation
    always #5 clk = ~clk;
    
    initial begin
        $dumpfile("adder_tb.vcd");
        $dumpvars(0, potential_adder_tb);

        clk = 0;
        rst = 1;
        time_step = 0;
        load = 0;
        input_weight = 32'd0;
        decayed_potential = 32'd0;
        model = 2'b00;
        init_mode = 3'b000;
        
        #20 rst = 0;
        
        // Initialize Parameters
        #10 load = 1; input_weight = 32'd10; init_mode = 3'b001; #10 load = 0; // Set A
        #10 load = 1; input_weight = 32'd20; init_mode = 3'b010; #10 load = 0; // Set B
        #10 load = 1; input_weight = 32'd30; init_mode = 3'b011; #10 load = 0; // Set C
        #10 load = 1; input_weight = 32'd40; init_mode = 3'b100; #10 load = 0; // Set D
        #10 load = 1; input_weight = 32'd50; init_mode = 3'b101; #10 load = 0; // Set VT
        #10 load = 1; input_weight = 32'd5; init_mode = 3'b110; // Set U
        #10 load = 0; init_mode = 3'b000; // Set Default
        
        // Test LIF Model
        #10 model = 2'b00; input_weight = 32'd15; decayed_potential = 32'd25; time_step = 1;
        #10 time_step = 0;
        #100;
        
        // Test Izhikevich Model
        #20 model = 2'b01; input_weight = 32'd5; decayed_potential = 32'd35; time_step = 1;
        #10 time_step = 0;
        #1000;
        
        // Test QLIF Model
        #20 model = 2'b10; input_weight = 32'd20; decayed_potential = 32'd10; time_step = 1;
        #10 time_step = 0;
        #100;
        
        #50 $finish;
    end
    
    initial begin
        $monitor("Time = %0t | Model = %b | Input = %d | Decayed = %d | Final Potential = %d | Spike = %b | Done = %b",
                  $time, model, input_weight, decayed_potential, final_potential, spike, done);
    end
    
endmodule

adder/adder_tb.vcd
$date
	Sun Feb 02 19:04:03 2025
$end
$version
	Icarus Verilog
$end
$timescale
	100ps
$end
$scope module potential_adder_tb $end
$var wire 1 ! spike $end
$var wire 32 " final_potential [31:0] $end
$var wire 1 # done $end
$var reg 1 $ clk $end
$var reg 32 % decayed_potential [31:0] $end
$var reg 3 & init_mode [2:0] $end
$var reg 32 ' input_weight [31:0] $end
$var reg 1 ( load $end
$var reg 2 ) model [1:0] $end
$var reg 1 * rst $end
$var reg 1 + time_step $end
$scope module uut $end
$var wire 1 $ clk $end
$var wire 32 , decayed_potential [31:0] $end
$var wire 3 - init_mode [2:0] $end
$var wire 32 . input_weight [31:0] $end
$var wire 1 ( load $end
$var wire 2 / model [1:0] $end
$var wire 1 * rst $end
$var wire 1 + time_step $end
$var wire 32 0 bv_u [31:0] $end
$var wire 1 1 bv_done $end
$var wire 64 2 bv [63:0] $end
$var wire 1 3 abv_done $end
$var wire 64 4 a_bv_u [63:0] $end
$var reg 32 5 a [31:0] $end
$var reg 1 6 abv_start $end
$var reg 32 7 b [31:0] $end
$var reg 1 8 bv_start $end
$var reg 32 9 c [31:0] $end
$var reg 32 : d [31:0] $end
$var reg 1 # done $end
$var reg 32 ; final_potential [31:0] $end
$var reg 1 ! spike $end
$var reg 32 < u [31:0] $end
$var reg 32 = v_threshold [31:0] $end
$var reg 32 > weight_added [31:0] $end
$scope module multIzhiBV $end
$var wire 32 ? A [31:0] $end
$var wire 32 @ B [31:0] $end
$var wire 1 $ clk $end
$var wire 1 + rst $end
$var wire 1 8 start $end
$var reg 6 A count [5:0] $end
$var reg 1 1 done $end
$var reg 32 B multiplicand [31:0] $end
$var reg 32 C multiplier [31:0] $end
$var reg 64 D product [63:0] $end
$var reg 64 E result [63:0] $end
$var reg 1 F running $end
$upscope $end
$scope module multIzhiaBVu $end
$var wire 32 G A [31:0] $end
$var wire 32 H B [31:0] $end
$var wire 1 $ clk $end
$var wire 1 + rst $end
$var wire 1 6 start $end
$var reg 6 I count [5:0] $end
$var reg 1 3 done $end
$var reg 32 J multiplicand [31:0] $end
$var reg 32 K multiplier [31:0] $end
$var reg 64 L product [63:0] $end
$var reg 64 M result [63:0] $end
$var reg 1 N running $end
$upscope $end
$upscope $end
$upscope $end
$enddefinitions $end
$comment Show the parameter values. $end
$dumpall
$end
#0
$dumpvars
xN
bx M
bx L
bx K
bx J
bx I
bx H
bx G
xF
bx E
bx D
bx C
bx B
bx A
b0 @
bx ?
bx >
bx =
bx <
bx ;
bx :
bx 9
x8
bx 7
x6
bx 5
bx 4
x3
bx 2
x1
bx 0
b0 /
b0 .
b0 -
b0 ,
0+
1*
b0 )
0(
b0 '
b0 &
b0 %
0$
x#
bx "
x!
$end
#50
b0 <
b0 =
b0 :
b0 9
b0 7
b0 ?
b0 5
b0 G
0!
0#
b0 "
b0 ;
1$
#100
0$
#150
1$
#200
0$
0*
#250
1#
bx "
bx ;
x!
1$
#300
b1010 5
b1010 G
0$
b1 &
b1 -
b1010 '
b1010 .
1(
#350
1$
#400
0$
0(
#450
1$
#500
b10100 7
b10100 ?
0$
b10 &
b10 -
b10100 '
b10100 .
1(
#550
1$
#600
0$
0(
#650
1$
#700
b11110 9
0$
b11 &
b11 -
b11110 '
b11110 .
1(
#750
1$
#800
0$
0(
#850
1$
#900
b101000 :
0$
b100 &
b100 -
b101000 '
b101000 .
1(
#950
1$
#1000
0$
0(
#1050
1$
#1100
b110010 =
0$
b101 &
b101 -
b110010 '
b110010 .
1(
#1150
1$
#1200
0$
0(
#1250
1$
#1300
b101 <
0$
b110 &
b110 -
b101 '
b101 .
1(
#1350
1$
#1400
0$
b0 &
b0 -
0(
#1450
1$
#1500
01
0F
b0 A
b0 D
b0 C
b0 B
03
0N
b0 I
b0 L
b0 K
b0 J
b101000 >
0!
0#
0$
1+
b11001 %
b11001 ,
b11001 @
b1111 '
b1111 .
#1550
1#
b101000 "
b101000 ;
1$
#1600
0$
0+
#1650
1$
#1700
0$
#1750
1$
#1800
0$
#1850
1$
#1900
0$
#1950
1$
#2000
0$
#2050
1$
#2100
0$
#2150
1$
#2200
0$
#2250
1$
#2300
0$
#2350
1$
#2400
0$
#2450
1$
#2500
0$
#2550
1$
#2600
0$
#2650
1$
#2700
0$
#2750
1$
#2800
1F
b100011 C
b10100 B
06
18
b100011 >
0#
0$
1+
b100011 %
b100011 ,
b100011 @
b101 '
b101 .
b1 )
b1 /
#2850
b1 A
b10001 C
b10100 D
1$
#2900
0$
0+
#2950
b10 A
b1000 C
b111100 D
1$
#3000
0$
#3050
b11 A
b100 C
1$
#3100
0$
#3150
b100 A
b10 C
1$
#3200
0$
#3250
b101 A
b1 C
1$
#3300
0$
#3350
b110 A
b0 C
b1010111100 D
1$
#3400
0$
#3450
b111 A
1$
#3500
0$
#3550
b1000 A
1$
#3600
0$
#3650
b1001 A
1$
#3700
0$
#3750
b1010 A
1$
#3800
0$
#3850
b1011 A
1$
#3900
0$
#3950
b1100 A
1$
#4000
0$
#4050
b1101 A
1$
#4100
0$
#4150
b1110 A
1$
#4200
0$
#4250
b1111 A
1$
#4300
0$
#4350
b10000 A
1$
#4400
0$
#4450
b10001 A
1$
#4500
0$
#4550
b10010 A
1$
#4600
0$
#4650
b10011 A
1$
#4700
0$
#4750
b10100 A
1$
#4800
0$
#4850
b10101 A
1$
#4900
0$
#4950
b10110 A
1$
#5000
0$
#5050
b10111 A
1$
#5100
0$
#5150
b11000 A
1$
#5200
0$
#5250
b11001 A
1$
#5300
0$
#5350
b11010 A
1$
#5400
0$
#5450
b11011 A
1$
#5500
0$
#5550
b11100 A
1$
#5600
0$
#5650
b11101 A
1$
#5700
0$
#5750
b11110 A
1$
#5800
0$
#5850
b11111 A
1$
#5900
0$
#5950
b100000 A
1$
#6000
0$
#6050
08
b1010110111 0
b1010110111 H
0F
11
b1010111100 2
b1010111100 E
1$
#6100
0$
#6150
1N
b1010110111 K
b1010 J
16
1$
#6200
0$
#6250
b1 I
b101011011 K
b1010 L
1$
#6300
0$
#6350
b10 I
b10101101 K
b11110 L
1$
#6400
0$
#6450
b11 I
b1010110 K
b1000110 L
1$
#6500
0$
#6550
b100 I
b101011 K
1$
#6600
0$
#6650
b101 I
b10101 K
b11100110 L
1$
#6700
0$
#6750
b110 I
b1010 K
b1000100110 L
1$
#6800
0$
#6850
b111 I
b101 K
1$
#6900
0$
#6950
b1000 I
b10 K
b11100100110 L
1$
#7000
0$
#7050
b1001 I
b1 K
1$
#7100
0$
#7150
b1010 I
b0 K
b1101100100110 L
1$
#7200
0$
#7250
b1011 I
1$
#7300
0$
#7350
b1100 I
1$
#7400
0$
#7450
b1101 I
1$
#7500
0$
#7550
b1110 I
1$
#7600
0$
#7650
b1111 I
1$
#7700
0$
#7750
b10000 I
1$
#7800
0$
#7850
b10001 I
1$
#7900
0$
#7950
b10010 I
1$
#8000
0$
#8050
b10011 I
1$
#8100
0$
#8150
b10100 I
1$
#8200
0$
#8250
b10101 I
1$
#8300
0$
#8350
b10110 I
1$
#8400
0$
#8450
b10111 I
1$
#8500
0$
#8550
b11000 I
1$
#8600
0$
#8650
b11001 I
1$
#8700
0$
#8750
b11010 I
1$
#8800
0$
#8850
b11011 I
1$
#8900
0$
#8950
b11100 I
1$
#9000
0$
#9050
b11101 I
1$
#9100
0$
#9150
b11110 I
1$
#9200
0$
#9250
b11111 I
1$
#9300
0$
#9350
b100000 I
1$
#9400
0$
#9450
0N
13
b1101100100110 4
b1101100100110 M
1$
#9500
0$
#9550
1#
b11111111111111111110011110010110 0
b11111111111111111110011110010110 H
b1101100100110 <
b100011 "
b100011 ;
1$
