code/rtl/neuro_int/utils/shifter_32bit.v
`timescale 1ns/100ps

module shifter_32bit (
    input wire clk,
    input wire rst,
    input wire start,
    input wire [31:0] data_in,
    input wire [4:0] shift_amount,  // Supports shifting up to 31 bits
    input wire [1:0] mode,          // 00: Logical Left, 01: Logical Right, 10: Arithmetic Right
    output reg [31:0] data_out,
    output reg done
);

    reg [31:0] shift_reg;
    reg [4:0] count;
    reg running, prev_start;

    always @(posedge clk) begin
        prev_start <= start;
    end

    always @(posedge clk) begin
        if (rst) begin
            shift_reg <= 0;
            count <= 0;
            running <= 0;
            done <= 0;
            data_out <= 0;
        end else if (start && !running && !prev_start) begin
            shift_reg <= data_in;
            count <= shift_amount;
            running <= 1;
            done <= 0;
            data_out <= 0;
        end else if (running) begin
            if (count > 0) begin
                case (mode)
                    2'b00: shift_reg <= shift_reg << 1;  // Logical Left Shift
                    2'b01: shift_reg <= shift_reg >> 1;  // Logical Right Shift
                    2'b10: shift_reg <= shift_reg >>> 1; // Arithmetic Right Shift
                    default: shift_reg <= shift_reg; // No operation
                endcase
                count <= count - 1;
            end else begin
                data_out <= shift_reg;
                done <= 1;
                running <= 0;
            end
        end
    end

endmodule

code/rtl/neuro_int/utils/encording.v
// Decay modes
`define LIF0 3'b000
`define LIF2 3'b001
`define LIF4 3'b010
`define LIF8 3'b011
`define LIF24 3'b100
`define IZHI 3'b101
`define QUAD 3'b110
`define IDLE 3'b111

// Adder model
`define LIF 2'b00
`define IZHI_AD 2'b01
`define QLIF 2'b10

// Adder init mode
`define DEFAULT 3'b000
`define A 3'b001
`define B 3'b010
`define C 3'b011
`define D 3'b100
`define VT 3'b101
`define U 3'b110
`define IDLE 3'b111

// controller working modes
`define ADDR_WEIGHT_SET 8'b11111111
`define WEIGHT_SET 8'b11111110
`define SET_CONTROL_SIGNALS 8'b11111101
`define END_PACKET 8'b00000000

// controller status
`define MODE_SELECT 2'b00
`define MODE_LOAD 2'b01
`define MODE_BUFFER 2'b10

// buffer modes
`define BUFFER_IDLE 2'b00
`define BUFFER_ADDRESS 2'b01
`define BUFFER_VALUE 2'b10

// buffer status
`define ADDRESS_DONE 2'b01
`define VALUE_DONE 2'b11

code/rtl/neuro_int/utils/multiplier_32bit.v
`timescale 1ns/100ps

module multiplier_32bit(
    input wire clk,
    input wire rst,
    input wire start,
    input wire [31:0] A,
    input wire [31:0] B,
    output reg [63:0] result,
    output reg done
);
    
    reg [31:0] multiplicand, multiplier;
    reg [63:0] product;
    reg [5:0] count;
    reg running, prev_start;

    always @(posedge clk) begin
        prev_start <= start;
    end

    always @(posedge clk) begin
        if (rst) begin
            multiplicand <= 0;
            multiplier <= 0;
            product <= 0;
            count <= 0;
            running <= 0;
            done <= 0;
        end else if (start && !running && !prev_start) begin
            multiplicand <= A;
            multiplier <= B;
            product <= 0;
            count <= 0;
            running <= 1;
            done <= 0;
        end else if (running) begin
            if (count < 32) begin
                if (multiplier[0] == 1'b1) begin
                    product <= product + ({32'b0, multiplicand} << count);
                end
                multiplier <= multiplier >> 1;
                count <= count + 1;
            end else begin
                result <= product;
                done <= 1;
                running <= 0;
            end
        end
    end

endmodule

code/rtl/neuro_int/adder/potential_adder.v
`timescale 1ns/100ps

module potential_adder (
    input wire clk,
    input wire rst,        
    input wire time_step,      
    input wire [31:0] input_weight, 
    input wire [31:0] decayed_potential,
    input wire [1:0] model,
    input wire [2:0] init_mode,
    input wire load,
    
    output reg [31:0] final_potential, 
    output reg done,
    output reg spike
);

    // Common Signals
    reg [31:0] weight_added;
    reg [31:0] u;
    reg adder_start, adder_send;

    // Internal Signals for Izhikevich Model
    wire [63:0] bv, a_bv_u;
    wire [31:0] bv_u;
    reg [31:0] a, b, c, d, v_threshold;
    
    reg bv_start, abv_start, clear_mul;
    wire bv_done, abv_done;

    reg prev_load, prev_time_step;

    multiplier_32bit multIzhiBV (
        .clk(clk),
        .rst(rst || clear_mul),
        .start(bv_start),
        .A(b),
        .B(decayed_potential),
        .result(bv),
        .done(bv_done)
    );

    multiplier_32bit multIzhiaBVu (
        .clk(clk),
        .rst(rst || clear_mul),
        .start(abv_start),
        .A(a),
        .B(bv_u),
        .result(a_bv_u),
        .done(abv_done)
    );

    assign bv_u = bv[31:0] - u;

    always @(posedge clk) begin
        if(rst) begin
            bv_start <= 0;
            abv_start <= 0;
        end else if (adder_start && model == `IZHI_AD) begin
            bv_start <= 1;
            abv_start <= 0;
        end else if (bv_done) begin
            bv_start <= 0;
            abv_start <= 1;
        end else if (abv_done) begin
            bv_start <= 0;
            abv_start <= 0;
        end
    end

    always @(posedge clk) begin
        prev_load <= load;
        if (rst) begin
            a <= 0;
            b <= 0;
            c <= 0;
            d <= 0;
            v_threshold <= 0;
            u <= 0;
        end else if (init_mode == `A) begin
            a <= input_weight;
        end else if (init_mode == `B) begin
            b <= input_weight;
        end else if (init_mode == `C) begin
            c <= input_weight;
        end else if (init_mode == `D) begin
            d <= input_weight;
        end else if (init_mode == `VT) begin
            v_threshold <= input_weight;
        end else if (init_mode == `U) begin
            u <= input_weight;
        end else if (init_mode == `DEFAULT) begin
            if (adder_send && model == `IZHI_AD && abv_done) begin
                u <= (weight_added > v_threshold) ? u + d : a_bv_u[31:0];
            end
        end
    end

    always @(posedge clk) begin
        prev_time_step <= time_step;
        if (rst) begin
            adder_start <= 0;
            done <= 0;
            clear_mul <= 0;
        end else if (time_step && !prev_time_step) begin
            adder_start <= 1;
            done <= 0;
        end else if (adder_start) begin
            adder_start <= 0;
            adder_send <= 1;
        end else if (adder_send) begin
            if (model == `LIF) begin
                adder_send <= 0;
                done <= 1;
            end else if (model == `IZHI_AD && abv_done) begin
                adder_send <= 0;
                done <= 1;
                clear_mul <= 1;
            end else if (model == `QLIF) begin
                adder_send <= 0;
                done <= 1;
            end
        end else begin
            clear_mul <= 0;
        end
    end

    always @(posedge clk) begin
        if (rst) begin
            final_potential <= 0;
            spike <= 0;
            weight_added <= 0;
        end else if (init_mode == `DEFAULT) begin
            if (adder_start) begin
                if (model == `LIF) begin
                    weight_added <= input_weight + decayed_potential;
                end else if (model == `IZHI_AD) begin
                    weight_added <= input_weight + decayed_potential - u;
                end else if (model == `QLIF) begin
                    weight_added <= input_weight + decayed_potential;
                end
            end
            if(adder_send) begin
                if(model == `LIF) begin
                    spike <= (weight_added > v_threshold);
                    final_potential <= (weight_added > v_threshold) ? (weight_added - v_threshold) : weight_added;
                    weight_added <= 0;
                end else if (model == `IZHI_AD) begin
                    if (abv_done) begin
                        spike <= (weight_added > v_threshold);
                        final_potential <= (weight_added > v_threshold) ? c : weight_added;
                        weight_added <= 0;
                    end
                end else if (model == `QLIF) begin
                    spike <= (weight_added > v_threshold);
                    final_potential <= (weight_added > v_threshold) ? (weight_added - v_threshold) : weight_added;
                    weight_added <= 0;
                end
            end
        end
    end
endmodule

code/rtl/neuro_int/adder/adder_tb.v
`include "../utils/encording.v"
`include "../utils/multiplier_32bit.v"
`include "../utils/shifter_32bit.v"
`include "potential_adder.v"
`timescale 1ns/100ps

module potential_adder_tb();
    reg clk;
    reg rst;
    reg time_step;
    reg load;
    reg [31:0] input_weight;
    reg [31:0] decayed_potential;
    reg [1:0] model;
    reg [2:0] init_mode;
    
    wire [31:0] final_potential;
    wire done;
    wire spike;
    
    potential_adder uut (
        .clk(clk),
        .rst(rst),
        .time_step(time_step),
        .input_weight(input_weight),
        .decayed_potential(decayed_potential),
        .model(model),
        .init_mode(init_mode),
        .load(load),
        .final_potential(final_potential),
        .done(done),
        .spike(spike)
    );
    
    // Clock Generation
    always #5 clk = ~clk;
    
    initial begin
        $dumpfile("adder_tb.vcd");
        $dumpvars(0, potential_adder_tb);

        clk = 0;
        rst = 1;
        time_step = 0;
        load = 0;
        input_weight = 32'd0;
        decayed_potential = 32'd0;
        model = 2'b00;
        init_mode = 3'b000;
        
        #20 rst = 0;
        
        // Initialize Parameters
        #10 load = 1; input_weight = 32'd10; init_mode = 3'b001; #10 load = 0; // Set A
        #10 load = 1; input_weight = 32'd20; init_mode = 3'b010; #10 load = 0; // Set B
        #10 load = 1; input_weight = 32'd30; init_mode = 3'b011; #10 load = 0; // Set C
        #10 load = 1; input_weight = 32'd40; init_mode = 3'b100; #10 load = 0; // Set D
        #10 load = 1; input_weight = 32'd50; init_mode = 3'b101; #10 load = 0; // Set VT
        #10 load = 1; input_weight = 32'd5; init_mode = 3'b110; // Set U
        #10 load = 0; init_mode = 3'b000; // Set Default
        
        // Test LIF Model
        #10 model = 2'b00; input_weight = 32'd25; decayed_potential = 32'd25; time_step = 1;
        #10 time_step = 0;
        #100;
        
        // Test Izhikevich Model
        #20 model = 2'b01; input_weight = 32'd25; decayed_potential = 32'd35; time_step = 1;
        #10 time_step = 0;
        #1100;
        
        // Test QLIF Model
        #20 model = 2'b10; input_weight = 32'd30; decayed_potential = 32'd10; time_step = 1;
        #10 time_step = 0;
        #100;
        
        #50 $finish;
    end
    
    initial begin
        $monitor("Time = %0t | Model = %b | Input = %d | Decayed = %d | Final Potential = %d | Spike = %b | Done = %b",
                  $time, model, input_weight, decayed_potential, final_potential, spike, done);
    end
    
endmodule

code/rtl/neuro_int/adder/adder_tb.vcd
$date
	Sun Feb 09 19:36:28 2025
$end
$version
	Icarus Verilog
$end
$timescale
	100ps
$end
$scope module potential_adder_tb $end
$var wire 1 ! spike $end
$var wire 32 " final_potential [31:0] $end
$var wire 1 # done $end
$var reg 1 $ clk $end
$var reg 32 % decayed_potential [31:0] $end
$var reg 3 & init_mode [2:0] $end
$var reg 32 ' input_weight [31:0] $end
$var reg 1 ( load $end
$var reg 2 ) model [1:0] $end
$var reg 1 * rst $end
$var reg 1 + time_step $end
$scope module uut $end
$var wire 1 $ clk $end
$var wire 32 , decayed_potential [31:0] $end
$var wire 3 - init_mode [2:0] $end
$var wire 32 . input_weight [31:0] $end
$var wire 1 ( load $end
$var wire 2 / model [1:0] $end
$var wire 1 * rst $end
$var wire 1 + time_step $end
$var wire 32 0 bv_u [31:0] $end
$var wire 1 1 bv_done $end
$var wire 64 2 bv [63:0] $end
$var wire 1 3 abv_done $end
$var wire 64 4 a_bv_u [63:0] $end
$var reg 32 5 a [31:0] $end
$var reg 1 6 abv_start $end
$var reg 1 7 adder_send $end
$var reg 1 8 adder_start $end
$var reg 32 9 b [31:0] $end
$var reg 1 : bv_start $end
$var reg 32 ; c [31:0] $end
$var reg 1 < clear_mul $end
$var reg 32 = d [31:0] $end
$var reg 1 # done $end
$var reg 32 > final_potential [31:0] $end
$var reg 1 ? prev_load $end
$var reg 1 @ prev_time_step $end
$var reg 1 ! spike $end
$var reg 32 A u [31:0] $end
$var reg 32 B v_threshold [31:0] $end
$var reg 32 C weight_added [31:0] $end
$scope module multIzhiBV $end
$var wire 32 D A [31:0] $end
$var wire 32 E B [31:0] $end
$var wire 1 $ clk $end
$var wire 1 F rst $end
$var wire 1 : start $end
$var reg 6 G count [5:0] $end
$var reg 1 1 done $end
$var reg 32 H multiplicand [31:0] $end
$var reg 32 I multiplier [31:0] $end
$var reg 1 J prev_start $end
$var reg 64 K product [63:0] $end
$var reg 64 L result [63:0] $end
$var reg 1 M running $end
$upscope $end
$scope module multIzhiaBVu $end
$var wire 32 N A [31:0] $end
$var wire 32 O B [31:0] $end
$var wire 1 $ clk $end
$var wire 1 P rst $end
$var wire 1 6 start $end
$var reg 6 Q count [5:0] $end
$var reg 1 3 done $end
$var reg 32 R multiplicand [31:0] $end
$var reg 32 S multiplier [31:0] $end
$var reg 1 T prev_start $end
$var reg 64 U product [63:0] $end
$var reg 64 V result [63:0] $end
$var reg 1 W running $end
$upscope $end
$upscope $end
$upscope $end
$enddefinitions $end
$comment Show the parameter values. $end
$dumpall
$end
#0
$dumpvars
xW
bx V
bx U
xT
bx S
bx R
bx Q
1P
bx O
bx N
xM
bx L
bx K
xJ
bx I
bx H
bx G
1F
b0 E
bx D
bx C
bx B
bx A
x@
x?
bx >
bx =
x<
bx ;
x:
bx 9
x8
x7
x6
bx 5
bx 4
x3
bx 2
x1
bx 0
b0 /
b0 .
b0 -
b0 ,
0+
1*
b0 )
0(
b0 '
b0 &
b0 %
0$
x#
bx "
x!
$end
#50
01
0M
b0 G
b0 K
b0 I
b0 H
03
0W
b0 Q
b0 U
b0 S
b0 R
06
0:
b0 A
b0 B
b0 =
b0 ;
b0 9
b0 D
b0 5
b0 N
0?
0<
0#
08
0@
b0 C
0!
b0 "
b0 >
1$
#100
0$
#150
0T
0J
1$
#200
0F
0P
0$
0*
#250
1$
#300
0$
b1 &
b1 -
b1010 '
b1010 .
1(
#350
b1010 5
b1010 N
1?
1$
#400
0$
0(
#450
0?
1$
#500
0$
b10 &
b10 -
b10100 '
b10100 .
1(
#550
b10100 9
b10100 D
1?
1$
#600
0$
0(
#650
0?
1$
#700
0$
b11 &
b11 -
b11110 '
b11110 .
1(
#750
b11110 ;
1?
1$
#800
0$
0(
#850
0?
1$
#900
0$
b100 &
b100 -
b101000 '
b101000 .
1(
#950
b101000 =
1?
1$
#1000
0$
0(
#1050
0?
1$
#1100
0$
b101 &
b101 -
b110010 '
b110010 .
1(
#1150
b110010 B
1?
1$
#1200
0$
0(
#1250
0?
1$
#1300
0$
b110 &
b110 -
b101 '
b101 .
1(
#1350
b101 A
1?
1$
#1400
0$
b0 &
b0 -
0(
#1450
0?
1$
#1500
0$
1+
b11001 %
b11001 ,
b11001 E
b11001 '
b11001 .
#1550
18
1@
1$
#1600
0$
0+
#1650
17
08
0@
b110010 C
1$
#1700
0$
#1750
b0 C
b110010 "
b110010 >
1#
07
1$
#1800
0$
#1850
1$
#1900
0$
#1950
1$
#2000
0$
#2050
1$
#2100
0$
#2150
1$
#2200
0$
#2250
1$
#2300
0$
#2350
1$
#2400
0$
#2450
1$
#2500
0$
#2550
1$
#2600
0$
#2650
1$
#2700
0$
#2750
1$
#2800
0$
1+
b100011 %
b100011 ,
b100011 E
b1 )
b1 /
#2850
0#
18
1@
1$
#2900
0$
0+
#2950
b110111 C
17
08
0@
1:
1$
#3000
0$
#3050
1J
1M
b100011 I
b10100 H
1$
#3100
0$
#3150
b1 G
b10001 I
b10100 K
1$
#3200
0$
#3250
b10 G
b1000 I
b111100 K
1$
#3300
0$
#3350
b11 G
b100 I
1$
#3400
0$
#3450
b100 G
b10 I
1$
#3500
0$
#3550
b101 G
b1 I
1$
#3600
0$
#3650
b110 G
b0 I
b1010111100 K
1$
#3700
0$
#3750
b111 G
1$
#3800
0$
#3850
b1000 G
1$
#3900
0$
#3950
b1001 G
1$
#4000
0$
#4050
b1010 G
1$
#4100
0$
#4150
b1011 G
1$
#4200
0$
#4250
b1100 G
1$
#4300
0$
#4350
b1101 G
1$
#4400
0$
#4450
b1110 G
1$
#4500
0$
#4550
b1111 G
1$
#4600
0$
#4650
b10000 G
1$
#4700
0$
#4750
b10001 G
1$
#4800
0$
#4850
b10010 G
1$
#4900
0$
#4950
b10011 G
1$
#5000
0$
#5050
b10100 G
1$
#5100
0$
#5150
b10101 G
1$
#5200
0$
#5250
b10110 G
1$
#5300
0$
#5350
b10111 G
1$
#5400
0$
#5450
b11000 G
1$
#5500
0$
#5550
b11001 G
1$
#5600
0$
#5650
b11010 G
1$
#5700
0$
#5750
b11011 G
1$
#5800
0$
#5850
b11100 G
1$
#5900
0$
#5950
b11101 G
1$
#6000
0$
#6050
b11110 G
1$
#6100
0$
#6150
b11111 G
1$
#6200
0$
#6250
b100000 G
1$
#6300
0$
#6350
b1010110111 0
b1010110111 O
0M
11
b1010111100 2
b1010111100 L
1$
#6400
0$
#6450
16
0:
1$
#6500
0$
#6550
1W
b1010110111 S
b1010 R
1T
0J
1$
#6600
0$
#6650
b1 Q
b101011011 S
b1010 U
1$
#6700
0$
#6750
b10 Q
b10101101 S
b11110 U
1$
#6800
0$
#6850
b11 Q
b1010110 S
b1000110 U
1$
#6900
0$
#6950
b100 Q
b101011 S
1$
#7000
0$
#7050
b101 Q
b10101 S
b11100110 U
1$
#7100
0$
#7150
b110 Q
b1010 S
b1000100110 U
1$
#7200
0$
#7250
b111 Q
b101 S
1$
#7300
0$
#7350
b1000 Q
b10 S
b11100100110 U
1$
#7400
0$
#7450
b1001 Q
b1 S
1$
#7500
0$
#7550
b1010 Q
b0 S
b1101100100110 U
1$
#7600
0$
#7650
b1011 Q
1$
#7700
0$
#7750
b1100 Q
1$
#7800
0$
#7850
b1101 Q
1$
#7900
0$
#7950
b1110 Q
1$
#8000
0$
#8050
b1111 Q
1$
#8100
0$
#8150
b10000 Q
1$
#8200
0$
#8250
b10001 Q
1$
#8300
0$
#8350
b10010 Q
1$
#8400
0$
#8450
b10011 Q
1$
#8500
0$
#8550
b10100 Q
1$
#8600
0$
#8650
b10101 Q
1$
#8700
0$
#8750
b10110 Q
1$
#8800
0$
#8850
b10111 Q
1$
#8900
0$
#8950
b11000 Q
1$
#9000
0$
#9050
b11001 Q
1$
#9100
0$
#9150
b11010 Q
1$
#9200
0$
#9250
b11011 Q
1$
#9300
0$
#9350
b11100 Q
1$
#9400
0$
#9450
b11101 Q
1$
#9500
0$
#9550
b11110 Q
1$
#9600
0$
#9650
b11111 Q
1$
#9700
0$
#9750
b100000 Q
1$
#9800
0$
#9850
0W
13
b1101100100110 4
b1101100100110 V
1$
#9900
0$
#9950
1P
1F
b0 C
b11110 "
b11110 >
1!
1<
1#
07
b1010001111 0
b1010001111 O
b101101 A
1$
#10000
0$
#10050
0P
0F
01
b0 G
b0 K
b0 H
03
b0 Q
b0 U
b0 R
0<
1$
