code/rtl/neuro_int/utils/encording.v
// Decay modes
`define LIF0 3'b000
`define LIF2 3'b001
`define LIF4 3'b010
`define LIF8 3'b011
`define LIF24 3'b100
`define IZHI 3'b101
`define QUAD 3'b110
`define IDLE 3'b111

// Adder model
`define LIF 2'b00
`define IZHI_AD 2'b01
`define QLIF 2'b10

// Adder init mode
`define DEFAULT 3'b000
`define A 3'b001
`define B 3'b010
`define C 3'b011
`define D 3'b100
`define VT 3'b101
`define U 3'b110
`define IDLE 3'b111

// controller working modes
`define ADDR_WEIGHT_SET 8'b11111111
`define WEIGHT_SET 8'b11111110
`define SET_CONTROL_SIGNALS 8'b11111101
`define END_PACKET 8'b00000000

// controller status
`define MODE_SELECT 2'b00
`define MODE_LOAD 2'b01
`define MODE_BUFFER 2'b10

// buffer modes
`define BUFFER_IDLE 2'b00
`define BUFFER_ADDRESS 2'b01
`define BUFFER_VALUE 2'b10

// buffer status
`define ADDRESS_DONE 2'b01
`define VALUE_DONE 2'b11

code/rtl/neuro_int/utils/shifter_32bit.v
`timescale 1ns/100ps

module shifter_32bit (
    input wire clk,
    input wire rst,
    input wire start,
    input wire [31:0] data_in,
    input wire [4:0] shift_amount,  // Supports shifting up to 31 bits
    input wire [1:0] mode,          // 00: Logical Left, 01: Logical Right, 10: Arithmetic Right
    output reg [31:0] data_out,
    output reg done
);

    reg [31:0] shift_reg;
    reg [4:0] count;
    reg running, prev_start;

    always @(posedge clk) begin
        prev_start <= start;
    end

    always @(posedge clk) begin
        if (rst) begin
            shift_reg <= 0;
            count <= 0;
            running <= 0;
            done <= 0;
            data_out <= 0;
        end else if (start && !running && !prev_start) begin
            shift_reg <= data_in;
            count <= shift_amount;
            running <= 1;
            done <= 0;
            data_out <= 0;
        end else if (running) begin
            if (count > 0) begin
                case (mode)
                    2'b00: shift_reg <= shift_reg << 1;  // Logical Left Shift
                    2'b01: shift_reg <= shift_reg >> 1;  // Logical Right Shift
                    2'b10: shift_reg <= shift_reg >>> 1; // Arithmetic Right Shift
                    default: shift_reg <= shift_reg; // No operation
                endcase
                count <= count - 1;
            end else begin
                data_out <= shift_reg;
                done <= 1;
                running <= 0;
            end
        end
    end

endmodule

code/rtl/neuro_int/utils/multiplier_32bit.v
`timescale 1ns/100ps

module multiplier_32bit(
    input wire clk,
    input wire rst,
    input wire start,
    input wire [31:0] A,
    input wire [31:0] B,
    output reg [63:0] result,
    output reg done
);
    
    reg [31:0] multiplicand, multiplier;
    reg [63:0] product;
    reg [5:0] count;
    reg running, prev_start;

    always @(posedge clk) begin
        prev_start <= start;
    end

    always @(posedge clk) begin
        if (rst) begin
            multiplicand <= 0;
            multiplier <= 0;
            product <= 0;
            count <= 0;
            running <= 0;
            done <= 0;
        end else if (start && !running && !prev_start) begin
            multiplicand <= A;
            multiplier <= B;
            product <= 0;
            count <= 0;
            running <= 1;
            done <= 0;
        end else if (running) begin
            if (count < 32) begin
                if (multiplier[0] == 1'b1) begin
                    product = product + ({32'b0, multiplicand} << count);
                end
                multiplier = multiplier >> 1;
                count = count + 1;
            end else begin
                result <= product;
                done <= 1;
                running <= 0;
            end
        end
    end

endmodule

code/rtl/neuro_int/decay/decay.v
`timescale 1ns/100ps

module potential_decay(
    input wire clk,
    input wire rst,
    input wire load,
    input wire time_step,
    input wire [2:0] mode,
    input wire [31:0] new_potential,
    output reg [31:0] output_potential_decay
);
    
    reg [31:0] membrane_potential;
    wire [31:0] output_lif2;
    wire [31:0] output_lif4;
    wire [31:0] output_lif8;
    wire done_lif2;
    wire done_lif4;
    wire done_lif8;
    wire v_squared_done;
    wire izi1_done;
    wire izi2_done;
    wire [63:0] v_squared;
    wire [31:0] izi_first_term;
    wire [63:0] izi_second_term;
    reg start;
    reg decay_send;
    reg prev_load, prev_time_step;

    multiplier_32bit v_squared_mul(
        .clk(clk),
        .rst(rst),
        .start(start),
        .A(membrane_potential),
        .B(membrane_potential),
        .result(v_squared),
        .done(v_squared_done)
    );

    shifter_32bit izi1(
        .clk(clk),
        .rst(rst),
        .start(v_squared_done),
        .data_in(v_squared[31:0]),
        .shift_amount(5'b00011),
        .mode(2'b01),
        .data_out(izi_first_term),
        .done(izi1_done)
    );

    multiplier_32bit izi2(
        .clk(clk),
        .rst(rst),
        .start(start),
        .A(membrane_potential),
        .B(32'h0005),
        .result(izi_second_term),
        .done(izi2_done)
    );

    shifter_32bit lif2(
        .clk(clk),
        .rst(rst),
        .start(start),
        .data_in(membrane_potential),
        .shift_amount(5'b00001),
        .mode(2'b01),
        .data_out(output_lif2),
        .done(done_lif2)
    );

    shifter_32bit lif4(
        .clk(clk),
        .rst(rst),
        .start(start),
        .data_in(membrane_potential),
        .shift_amount(5'b00010),
        .mode(2'b01),
        .data_out(output_lif4),
        .done(done_lif4)
    );

    shifter_32bit lif8(
        .clk(clk),
        .rst(rst),
        .start(start),
        .data_in(membrane_potential),
        .shift_amount(5'b00011),
        .mode(2'b01),
        .data_out(output_lif8),
        .done(done_lif8)
    );

    always @(posedge clk) begin
        prev_load <= load;
        if (load && !prev_load) begin
            if(mode != `IDLE) begin
                start <= 1;
            end
            membrane_potential <= new_potential;
        end else begin
            start <= 0;
        end
    end

    always @(posedge clk) begin
        prev_time_step <= time_step;
        if (time_step && !prev_time_step) begin
            output_potential_decay <= membrane_potential;
        end
    end

    always @(posedge clk) begin
        if (rst) begin
            membrane_potential <= 0;
            output_potential_decay <= 0;
            decay_send <= 0;
            start <= 0;
        end else if (mode == `LIF0) begin
            // Do nothing
        end else if (mode == `LIF2) begin
            if (done_lif2) begin
                membrane_potential <= output_lif2;
            end
        end else if (mode == `LIF4) begin
            if (done_lif4) begin
                membrane_potential <= output_lif4;
            end
        end else if (mode == `LIF8) begin
            if(done_lif8) begin
                membrane_potential <= output_lif8;
            end
        end else if (mode == `LIF24) begin
            if(done_lif2 & done_lif4) begin
                membrane_potential <= output_lif2 + output_lif4;
            end
        end else if(mode == `IZHI) begin
            if(izi1_done & izi2_done) begin
                membrane_potential <= izi_first_term - izi_second_term[31:0];
            end
        end else if(mode == `QUAD) begin
            if(v_squared_done) begin
                membrane_potential <= v_squared;
            end
        end else if(mode == `IDLE) begin
            // do nothing
        end
    end

endmodule

code/rtl/neuro_int/decay/decay_tb.v
`timescale 1ns/1ps
`include "../utils/encording.v"
`include "../utils/multiplier_32bit.v"
`include "../utils/shifter_32bit.v"
`include "decay.v"

module potential_decay_tb;
    reg clk;
    reg rst;
    reg load;
    reg time_step;
    reg [2:0] mode;
    reg [31:0] new_potential;
    wire [31:0] output_potential_decay;

    // Instantiate the DUT (Device Under Test)
    potential_decay dut (
        .clk(clk),
        .rst(rst),
        .load(load),
        .time_step(time_step),
        .mode(mode),
        .new_potential(new_potential),
        .output_potential_decay(output_potential_decay)
    );

    // Generate clock signal
    always #5 clk = ~clk;

    initial begin
        time_step = 0;
        #100;
        forever begin
            time_step = 1;
            #10 time_step = 0;
            #420;
        end
    end

    always @(posedge time_step) begin
        #10 new_potential <= output_potential_decay;
        #10 load = 1;
        #10 load = 0;
    end

    initial begin
        $dumpfile("decay_tb.vcd");
        $dumpvars(0, potential_decay_tb);

        // Initialize signals
        clk = 0;
        rst = 1;
        load = 0;
        time_step = 0;
        mode = 3'b111;
        new_potential = 32'd0;
        
        // Apply reset
        #10 rst = 0;
        
        // Load initial potential
        #10 new_potential = 32'd1000;
        load = 1;
        #10 load = 0;
        
        #20 mode = `IZHI; 

        // End simulation
        #5000 $finish;
    end

    // Monitor outputs
    initial begin
        $monitor("Time=%0t | Mode=%b | Potential=%d | Output=%d", 
                 $time, mode, new_potential, output_potential_decay);
    end
endmodule

code/rtl/neuro_int/decay/decay_tb.vcd
$date
	Sun Feb 09 17:54:03 2025
$end
$version
	Icarus Verilog
$end
$timescale
	100ps
$end
$scope module potential_decay_tb $end
$var wire 32 ! output_potential_decay [31:0] $end
$var reg 1 " clk $end
$var reg 1 # load $end
$var reg 3 $ mode [2:0] $end
$var reg 32 % new_potential [31:0] $end
$var reg 1 & rst $end
$var reg 1 ' time_step $end
$scope module dut $end
$var wire 1 " clk $end
$var wire 1 # load $end
$var wire 3 ( mode [2:0] $end
$var wire 32 ) new_potential [31:0] $end
$var wire 1 & rst $end
$var wire 1 ' time_step $end
$var wire 1 * v_squared_done $end
$var wire 64 + v_squared [63:0] $end
$var wire 32 , output_lif8 [31:0] $end
$var wire 32 - output_lif4 [31:0] $end
$var wire 32 . output_lif2 [31:0] $end
$var wire 64 / izi_second_term [63:0] $end
$var wire 32 0 izi_first_term [31:0] $end
$var wire 1 1 izi2_done $end
$var wire 1 2 izi1_done $end
$var wire 1 3 done_lif8 $end
$var wire 1 4 done_lif4 $end
$var wire 1 5 done_lif2 $end
$var reg 1 6 decay_send $end
$var reg 32 7 membrane_potential [31:0] $end
$var reg 32 8 output_potential_decay [31:0] $end
$var reg 1 9 prev_load $end
$var reg 1 : prev_time_step $end
$var reg 1 ; start $end
$scope module izi1 $end
$var wire 1 " clk $end
$var wire 32 < data_in [31:0] $end
$var wire 2 = mode [1:0] $end
$var wire 1 & rst $end
$var wire 5 > shift_amount [4:0] $end
$var wire 1 * start $end
$var reg 5 ? count [4:0] $end
$var reg 32 @ data_out [31:0] $end
$var reg 1 2 done $end
$var reg 1 A prev_start $end
$var reg 1 B running $end
$var reg 32 C shift_reg [31:0] $end
$upscope $end
$scope module izi2 $end
$var wire 32 D A [31:0] $end
$var wire 32 E B [31:0] $end
$var wire 1 " clk $end
$var wire 1 & rst $end
$var wire 1 ; start $end
$var reg 6 F count [5:0] $end
$var reg 1 1 done $end
$var reg 32 G multiplicand [31:0] $end
$var reg 32 H multiplier [31:0] $end
$var reg 1 I prev_start $end
$var reg 64 J product [63:0] $end
$var reg 64 K result [63:0] $end
$var reg 1 L running $end
$upscope $end
$scope module lif2 $end
$var wire 1 " clk $end
$var wire 32 M data_in [31:0] $end
$var wire 2 N mode [1:0] $end
$var wire 1 & rst $end
$var wire 5 O shift_amount [4:0] $end
$var wire 1 ; start $end
$var reg 5 P count [4:0] $end
$var reg 32 Q data_out [31:0] $end
$var reg 1 5 done $end
$var reg 1 R prev_start $end
$var reg 1 S running $end
$var reg 32 T shift_reg [31:0] $end
$upscope $end
$scope module lif4 $end
$var wire 1 " clk $end
$var wire 32 U data_in [31:0] $end
$var wire 2 V mode [1:0] $end
$var wire 1 & rst $end
$var wire 5 W shift_amount [4:0] $end
$var wire 1 ; start $end
$var reg 5 X count [4:0] $end
$var reg 32 Y data_out [31:0] $end
$var reg 1 4 done $end
$var reg 1 Z prev_start $end
$var reg 1 [ running $end
$var reg 32 \ shift_reg [31:0] $end
$upscope $end
$scope module lif8 $end
$var wire 1 " clk $end
$var wire 32 ] data_in [31:0] $end
$var wire 2 ^ mode [1:0] $end
$var wire 1 & rst $end
$var wire 5 _ shift_amount [4:0] $end
$var wire 1 ; start $end
$var reg 5 ` count [4:0] $end
$var reg 32 a data_out [31:0] $end
$var reg 1 3 done $end
$var reg 1 b prev_start $end
$var reg 1 c running $end
$var reg 32 d shift_reg [31:0] $end
$upscope $end
$scope module v_squared_mul $end
$var wire 32 e A [31:0] $end
$var wire 32 f B [31:0] $end
$var wire 1 " clk $end
$var wire 1 & rst $end
$var wire 1 ; start $end
$var reg 6 g count [5:0] $end
$var reg 1 * done $end
$var reg 32 h multiplicand [31:0] $end
$var reg 32 i multiplier [31:0] $end
$var reg 1 j prev_start $end
$var reg 64 k product [63:0] $end
$var reg 64 l result [63:0] $end
$var reg 1 m running $end
$upscope $end
$upscope $end
$upscope $end
$enddefinitions $end
$comment Show the parameter values. $end
$dumpall
$end
#0
$dumpvars
xm
bx l
bx k
xj
bx i
bx h
bx g
bx f
bx e
bx d
xc
xb
bx a
bx `
b11 _
b1 ^
bx ]
bx \
x[
xZ
bx Y
bx X
b10 W
b1 V
bx U
bx T
xS
xR
bx Q
bx P
b1 O
b1 N
bx M
xL
bx K
bx J
xI
bx H
bx G
bx F
b101 E
bx D
bx C
xB
xA
bx @
bx ?
b11 >
b1 =
bx <
x;
x:
x9
bx 8
bx 7
x6
x5
x4
x3
x2
x1
bx 0
bx /
bx .
bx -
bx ,
bx +
x*
b0 )
b111 (
0'
1&
b0 %
b111 $
0#
0"
bx !
$end
#50
0*
0m
b0 g
b0 k
b0 i
b0 h
b0 0
b0 @
02
0B
b0 ?
b0 C
01
0L
b0 F
b0 J
b0 H
b0 G
b0 .
b0 Q
05
0S
b0 P
b0 T
b0 -
b0 Y
04
0[
b0 X
b0 \
b0 ,
b0 a
03
0c
b0 `
b0 d
09
0:
0;
06
b0 !
b0 8
b0 7
b0 D
b0 M
b0 U
b0 ]
b0 e
b0 f
1"
#100
0"
0&
#150
0b
0Z
0R
0I
0A
0j
1"
#200
0"
1#
b1111101000 %
b1111101000 )
#250
b1111101000 7
b1111101000 D
b1111101000 M
b1111101000 U
b1111101000 ]
b1111101000 e
b1111101000 f
19
1"
#300
0"
0#
#350
09
1"
#400
0"
#450
1"
#500
0"
b101 $
b101 (
#550
1"
#600
0"
#650
1"
#700
0"
#750
1"
#800
0"
#850
1"
#900
0"
#950
1"
#1000
0"
1'
#1050
b1111101000 !
b1111101000 8
1:
1"
#1100
0"
0'
#1150
0:
1"
#1200
0"
1#
#1250
1;
19
1"
#1300
0"
0#
#1350
0;
09
1c
b11 `
b1111101000 d
1b
1[
b10 X
b1111101000 \
1Z
1S
b1 P
b1111101000 T
1R
1L
b101 H
b1111101000 G
1I
1m
b1111101000 i
b1111101000 h
1j
1"
#1400
0"
#1450
0j
0I
0R
b0 P
b111110100 T
0Z
b1 X
b111110100 \
0b
b10 `
b111110100 d
b1 g
b111110100 i
b1 F
b10 H
b1111101000 J
1"
#1500
0"
#1550
b1 `
b11111010 d
b0 X
b11111010 \
0S
15
b111110100 .
b111110100 Q
b10 F
b1 H
b10 g
b11111010 i
1"
#1600
0"
#1650
0[
14
b11111010 -
b11111010 Y
b0 `
b1111101 d
b11 g
b1111101 i
b11 F
b0 H
b1001110001000 J
1"
#1700
0"
#1750
0c
13
b1111101 ,
b1111101 a
b100 F
b100 g
b111110 i
b1111101000000 k
1"
#1800
0"
#1850
b101 g
b11111 i
b101 F
1"
#1900
0"
#1950
b110 F
b110 g
b1111 i
b1001110001000000 k
1"
#2000
0"
#2050
b111 g
b111 i
b11001011001000000 k
b111 F
1"
#2100
0"
#2150
b1000 F
b1000 g
b11 i
b111000101001000000 k
1"
#2200
0"
#2250
b1001 g
b1 i
b1110111001001000000 k
b1001 F
1"
#2300
0"
#2350
b1010 F
b1010 g
b0 i
b11110100001001000000 k
1"
#2400
0"
#2450
b1011 g
b1011 F
1"
#2500
0"
#2550
b1100 F
b1100 g
1"
#2600
0"
#2650
b1101 g
b1101 F
1"
#2700
0"
#2750
b1110 F
b1110 g
1"
#2800
0"
#2850
b1111 g
b1111 F
1"
#2900
0"
#2950
b10000 F
b10000 g
1"
#3000
0"
#3050
b10001 g
b10001 F
1"
#3100
0"
#3150
b10010 F
b10010 g
1"
#3200
0"
#3250
b10011 g
b10011 F
1"
#3300
0"
#3350
b10100 F
b10100 g
1"
#3400
0"
#3450
b10101 g
b10101 F
1"
#3500
0"
#3550
b10110 F
b10110 g
1"
#3600
0"
#3650
b10111 g
b10111 F
1"
#3700
0"
#3750
b11000 F
b11000 g
1"
#3800
0"
#3850
b11001 g
b11001 F
1"
#3900
0"
#3950
b11010 F
b11010 g
1"
#4000
0"
#4050
b11011 g
b11011 F
1"
#4100
0"
#4150
b11100 F
b11100 g
1"
#4200
0"
#4250
b11101 g
b11101 F
1"
#4300
0"
#4350
b11110 F
b11110 g
1"
#4400
0"
#4450
b11111 g
b11111 F
1"
#4500
0"
#4550
b100000 F
b100000 g
1"
#4600
0"
#4650
b11110100001001000000 <
0m
1*
b11110100001001000000 +
b11110100001001000000 l
0L
11
b1001110001000 /
b1001110001000 K
1"
#4700
0"
#4750
1B
b11 ?
b11110100001001000000 C
1A
1"
#4800
0"
#4850
b10 ?
b1111010000100100000 C
1"
#4900
0"
#4950
b1 ?
b111101000010010000 C
1"
#5000
0"
#5050
b0 ?
b11110100001001000 C
1"
#5100
0"
#5150
0B
12
b11110100001001000 0
b11110100001001000 @
1"
#5200
0"
#5250
b11101010011000000 7
b11101010011000000 D
b11101010011000000 M
b11101010011000000 U
b11101010011000000 ]
b11101010011000000 e
b11101010011000000 f
1"
#5300
0"
1'
#5350
b11101010011000000 !
b11101010011000000 8
1:
1"
#5400
b11101010011000000 %
b11101010011000000 )
0"
0'
#5450
0:
1"
#5500
0"
1#
#5550
1;
19
1"
#5600
0"
0#
#5650
1j
0*
1m
b0 g
b0 k
b11101010011000000 i
b11101010011000000 h
1I
01
1L
b0 F
b0 J
b101 H
b11101010011000000 G
1R
b0 .
b0 Q
05
1S
b1 P
b11101010011000000 T
1Z
b0 -
b0 Y
04
1[
b10 X
b11101010011000000 \
1b
b0 ,
b0 a
03
1c
b11 `
b11101010011000000 d
0;
09
1"
#5700
0"
#5750
b10 `
b1110101001100000 d
0b
b1 X
b1110101001100000 \
0Z
b0 P
b1110101001100000 T
0R
0I
0A
0j
b1 F
b10 H
b11101010011000000 J
b1 g
b1110101001100000 i
1"
#5800
0"
#5850
0S
15
b1110101001100000 .
b1110101001100000 Q
b0 X
b111010100110000 \
b1 `
b111010100110000 d
b10 g
b111010100110000 i
b10 F
b1 H
1"
#5900
0"
#5950
b0 `
b11101010011000 d
0[
14
b111010100110000 -
b111010100110000 Y
b11 F
b0 H
b10010010011111000000 J
b11 g
b11101010011000 i
1"
#6000
0"
#6050
0c
13
b11101010011000 ,
b11101010011000 a
b100 g
b1110101001100 i
b100 F
1"
#6100
0"
#6150
b101 F
b101 g
b111010100110 i
1"
#6200
0"
#6250
b110 g
b11101010011 i
b110 F
1"
#6300
0"
#6350
b111 F
b111 g
b1110101001 i
b11101010011000000000000 k
1"
#6400
0"
#6450
b1000 g
b111010100 i
b1010111111001000000000000 k
b1000 F
1"
#6500
0"
#6550
b1001 F
b1001 g
b11101010 i
1"
#6600
0"
#6650
b1010 g
b1110101 i
b1010 F
1"
#6700
0"
#6750
b1011 F
b1011 g
b111010 i
b1000101100101001000000000000 k
1"
#6800
0"
#6850
b1100 g
b11101 i
b1100 F
1"
#6900
0"
#6950
b1101 F
b1101 g
b1110 i
b100101111111101001000000000000 k
1"
#7000
0"
#7050
b1110 g
b111 i
b1110 F
1"
#7100
0"
#7150
b1111 F
b1111 g
b11 i
b10011011001011101001000000000000 k
1"
#7200
0"
#7250
b10000 g
b1 i
b110000101100011101001000000000000 k
b10000 F
1"
#7300
0"
#7350
b10001 F
b10001 g
b0 i
b1101011010010011101001000000000000 k
1"
#7400
0"
#7450
b10010 g
b10010 F
1"
#7500
0"
#7550
b10011 F
b10011 g
1"
#7600
0"
#7650
b10100 g
b10100 F
1"
#7700
0"
#7750
b10101 F
b10101 g
1"
#7800
0"
#7850
b10110 g
b10110 F
1"
#7900
0"
#7950
b10111 F
b10111 g
1"
#8000
0"
#8050
b11000 g
b11000 F
1"
#8100
0"
#8150
b11001 F
b11001 g
1"
#8200
0"
#8250
b11010 g
b11010 F
1"
#8300
0"
#8350
b11011 F
b11011 g
1"
#8400
0"
#8450
b11100 g
b11100 F
1"
#8500
0"
#8550
b11101 F
b11101 g
1"
#8600
0"
#8650
b11110 g
b11110 F
1"
#8700
0"
#8750
b11111 F
b11111 g
1"
#8800
0"
#8850
b100000 g
b100000 F
1"
#8900
0"
#8950
b1011010010011101001000000000000 <
0L
11
b10010010011111000000 /
b10010010011111000000 K
0m
1*
b1101011010010011101001000000000000 +
b1101011010010011101001000000000000 l
1"
#9000
0"
#9050
1A
b0 0
b0 @
02
1B
b11 ?
b1011010010011101001000000000000 C
b11111111111110001100000010001000 7
b11111111111110001100000010001000 D
b11111111111110001100000010001000 M
b11111111111110001100000010001000 U
b11111111111110001100000010001000 ]
b11111111111110001100000010001000 e
b11111111111110001100000010001000 f
1"
#9100
0"
#9150
b10 ?
b101101001001110100100000000000 C
1"
#9200
0"
#9250
b1 ?
b10110100100111010010000000000 C
1"
#9300
0"
#9350
b0 ?
b1011010010011101001000000000 C
1"
#9400
0"
#9450
0B
12
b1011010010011101001000000000 0
b1011010010011101001000000000 @
1"
#9500
0"
#9550
b1011010000001010101001000000 7
b1011010000001010101001000000 D
b1011010000001010101001000000 M
b1011010000001010101001000000 U
b1011010000001010101001000000 ]
b1011010000001010101001000000 e
b1011010000001010101001000000 f
1"
#9600
0"
1'
#9650
b1011010000001010101001000000 !
b1011010000001010101001000000 8
1:
1"
#9700
b1011010000001010101001000000 %
b1011010000001010101001000000 )
0"
0'
#9750
0:
1"
#9800
0"
1#
#9850
1;
19
1"
#9900
0"
0#
#9950
0;
09
b0 ,
b0 a
03
1c
b11 `
b1011010000001010101001000000 d
1b
b0 -
b0 Y
04
1[
b10 X
b1011010000001010101001000000 \
1Z
b0 .
b0 Q
05
1S
b1 P
b1011010000001010101001000000 T
1R
01
1L
b0 F
b0 J
b101 H
b1011010000001010101001000000 G
1I
0*
1m
b0 g
b0 k
b1011010000001010101001000000 i
b1011010000001010101001000000 h
1j
1"
#10000
0"
#10050
0j
0A
0I
0R
b0 P
b101101000000101010100100000 T
0Z
b1 X
b101101000000101010100100000 \
0b
b10 `
b101101000000101010100100000 d
b1 g
b101101000000101010100100000 i
b1 F
b10 H
b1011010000001010101001000000 J
1"
#10100
0"
#10150
b1 `
b10110100000010101010010000 d
b0 X
b10110100000010101010010000 \
0S
15
b101101000000101010100100000 .
b101101000000101010100100000 Q
b10 F
b1 H
b10 g
b10110100000010101010010000 i
1"
#10200
0"
#10250
0[
14
b10110100000010101010010000 -
b10110100000010101010010000 Y
b0 `
b1011010000001010101001000 d
b11 g
b1011010000001010101001000 i
b11 F
b0 H
b111000010000110101001101000000 J
1"
#10300
0"
#10350
0c
13
b1011010000001010101001000 ,
b1011010000001010101001000 a
b100 F
b100 g
b101101000000101010100100 i
1"
#10400
0"
#10450
b101 g
b10110100000010101010010 i
b101 F
1"
#10500
0"
#10550
b110 F
b110 g
b1011010000001010101001 i
1"
#10600
0"
#10650
b111 g
b101101000000101010100 i
b1011010000001010101001000000000000 k
b111 F
1"
#10700
0"
#10750
b1000 F
b1000 g
b10110100000010101010 i
1"
#10800
0"
#10850
b1001 g
b1011010000001010101 i
b1001 F
1"
#10900
0"
#10950
b1010 F
b1010 g
b101101000000101010 i
b1100101010001011111110001000000000000 k
1"
#11000
0"
#11050
b1011 g
b10110100000010101 i
b1011 F
1"
#11100
0"
#11150
b1100 F
b1100 g
b1011010000001010 i
b111001101010110110100010001000000000000 k
1"
#11200
0"
#11250
b1101 g
b101101000000101 i
b1101 F
1"
#11300
0"
#11350
b1110 F
b1110 g
b10110100000010 i
b11101101101101100000110010001000000000000 k
1"
#11400
0"
#11450
b1111 g
b1011010000001 i
b1111 F
1"
#11500
0"
#11550
b10000 F
b10000 g
b101101000000 i
b1110111101111000001001110010001000000000000 k
1"
#11600
0"
#11650
b10001 g
b10110100000 i
b10001 F
1"
#11700
0"
#11750
b10010 F
b10010 g
b1011010000 i
1"
#11800
0"
#11850
b10011 g
b101101000 i
b10011 F
1"
#11900
0"
#11950
b10100 F
b10100 g
b10110100 i
1"
#12000
0"
#12050
b10101 g
b1011010 i
b10101 F
1"
#12100
0"
#12150
b10110 F
b10110 g
b101101 i
1"
#12200
0"
#12250
b10111 g
b10110 i
b10110101111010011001010001001110010001000000000000 k
b10111 F
1"
#12300
0"
#12350
b11000 F
b11000 g
b1011 i
1"
#12400
0"
#12450
b11001 g
b101 i
b1110000110000101000010010001001110010001000000000000 k
b11001 F
1"
#12500
0"
#12550
b11010 F
b11010 g
b10 i
b100100100110011010010100010001001110010001000000000000 k
1"
#12600
0"
#12650
b11011 g
b1 i
b11011 F
1"
#12700
0"
#12750
b11100 F
b11100 g
b0 i
b1111110100111101111011100010001001110010001000000000000 k
1"
#12800
0"
#12850
b11101 g
b11101 F
1"
#12900
0"
#12950
b11110 F
b11110 g
1"
#13000
0"
#13050
b11111 g
b11111 F
1"
#13100
0"
#13150
b100000 F
b100000 g
1"
#13200
0"
#13250
b10001001110010001000000000000 <
0m
1*
b1111110100111101111011100010001001110010001000000000000 +
b1111110100111101111011100010001001110010001000000000000 l
0L
11
b111000010000110101001101000000 /
b111000010000110101001101000000 K
1"
#13300
0"
#13350
b11010011000001100111111011000000 7
b11010011000001100111111011000000 D
b11010011000001100111111011000000 M
b11010011000001100111111011000000 U
b11010011000001100111111011000000 ]
b11010011000001100111111011000000 e
b11010011000001100111111011000000 f
b0 0
b0 @
02
1B
b11 ?
b10001001110010001000000000000 C
1A
1"
#13400
0"
#13450
b10 ?
b1000100111001000100000000000 C
1"
#13500
0"
#13550
b1 ?
b100010011100100010000000000 C
1"
#13600
0"
#13650
b0 ?
b10001001110010001000000000 C
1"
#13700
0"
#13750
0B
12
b10001001110010001000000000 0
b10001001110010001000000000 @
1"
#13800
0"
#13850
b11001001111000111100111011000000 7
b11001001111000111100111011000000 D
b11001001111000111100111011000000 M
b11001001111000111100111011000000 U
b11001001111000111100111011000000 ]
b11001001111000111100111011000000 e
b11001001111000111100111011000000 f
1"
#13900
0"
1'
#13950
b11001001111000111100111011000000 !
b11001001111000111100111011000000 8
1:
1"
#14000
b11001001111000111100111011000000 %
b11001001111000111100111011000000 )
0"
0'
#14050
0:
1"
#14100
0"
1#
#14150
1;
19
1"
#14200
0"
0#
#14250
1j
0*
1m
b0 g
b0 k
b11001001111000111100111011000000 i
b11001001111000111100111011000000 h
1I
01
1L
b0 F
b0 J
b101 H
b11001001111000111100111011000000 G
1R
b0 .
b0 Q
05
1S
b1 P
b11001001111000111100111011000000 T
1Z
b0 -
b0 Y
04
1[
b10 X
b11001001111000111100111011000000 \
1b
b0 ,
b0 a
03
1c
b11 `
b11001001111000111100111011000000 d
0;
09
1"
#14300
0"
#14350
b10 `
b1100100111100011110011101100000 d
0b
b1 X
b1100100111100011110011101100000 \
0Z
b0 P
b1100100111100011110011101100000 T
0R
0I
0A
0j
b1 F
b10 H
b11001001111000111100111011000000 J
b1 g
b1100100111100011110011101100000 i
1"
#14400
0"
#14450
0S
15
b1100100111100011110011101100000 .
b1100100111100011110011101100000 Q
b0 X
b110010011110001111001110110000 \
b1 `
b110010011110001111001110110000 d
b10 g
b110010011110001111001110110000 i
b10 F
b1 H
1"
#14500
0"
#14550
b0 `
b11001001111000111100111011000 d
0[
14
b110010011110001111001110110000 -
b110010011110001111001110110000 Y
b11 F
b0 H
b1111110001011100110000100111000000 J
b11 g
b11001001111000111100111011000 i
1"
#14600
0"
#14650
0c
13
b11001001111000111100111011000 ,
b11001001111000111100111011000 a
b100 g
b1100100111100011110011101100 i
b100 F
1"
#14700
0"
#14750
b101 F
b101 g
b110010011110001111001110110 i
1"
#14800
0"
#14850
b110 g
b11001001111000111100111011 i
b110 F
1"
#14900
0"
#14950
b111 F
b111 g
b1100100111100011110011101 i
b11001001111000111100111011000000000000 k
1"
#15000
0"
#15050
b1000 g
b110010011110001111001110 i
b1001011101101010110110110001000000000000 k
b1000 F
1"
#15100
0"
#15150
b1001 F
b1001 g
b11001001111000111100111 i
1"
#15200
0"
#15250
b1010 g
b1100100111100011110011 i
b100010101100110010011110001001000000000000 k
b1010 F
1"
#15300
0"
#15350
b1011 F
b1011 g
b110010011110001111001 i
b1010101001011000001101100111001000000000000 k
1"
#15400
0"
#15450
b1100 g
b11001001111000111100 i
b10111010000111100000001010011001000000000000 k
b1100 F
1"
#15500
0"
#15550
b1101 F
b1101 g
b1100100111100011110 i
1"
#15600
0"
#15650
b1110 g
b110010011110001111 i
b1110 F
1"
#15700
0"
#15750
b1111 F
b1111 g
b11001001111000111 i
b1111100001101011010011110110011001000000000000 k
1"
#15800
0"
#15850
b10000 g
b1100100111100011 i
b101000110000110010111011001110011001000000000000 k
b10000 F
1"
#15900
0"
#15950
b10001 F
b10001 g
b110010011110001 i
b1011011001111000010001001111110011001000000000000 k
1"
#16000
0"
#16050
b10010 g
b11001001111000 i
b11000000001011100000100111011110011001000000000000 k
b10010 F
1"
#16100
0"
#16150
b10011 F
b10011 g
b1100100111100 i
1"
#16200
0"
#16250
b10100 g
b110010011110 i
b10100 F
1"
#16300
0"
#16350
b10101 F
b10101 g
b11001001111 i
1"
#16400
0"
#16450
b10110 g
b1100100111 i
b11100001111010011000111111111011110011001000000000000 k
b10110 F
1"
#16500
0"
#16550
b10111 F
b10111 g
b110010011 i
b1001110101101100010010110101111011110011001000000000000 k
1"
#16600
0"
#16650
b11000 g
b11001001 i
b10110011101010000000110100001111011110011001000000000000 k
b11000 F
1"
#16700
0"
#16750
b11001 F
b11001 g
b1100100 i
b101111101100010111101101111001111011110011001000000000000 k
1"
#16800
0"
#16850
b11010 g
b110010 i
b11010 F
1"
#16900
0"
#16950
b11011 F
b11011 g
b11001 i
1"
#17000
0"
#17050
b11100 g
b1100 i
b11111001100101010100101000111001111011110011001000000000000 k
b11100 F
1"
#17100
0"
#17150
b11101 F
b11101 g
b110 i
1"
#17200
0"
#17250
b11110 g
b11 i
b11110 F
1"
#17300
0"
#17350
b11111 F
b11111 g
b1 i
b11101001000101100111100000000111001111011110011001000000000000 k
1"
#17400
0"
#17450
b100000 g
b0 i
b1001111100110111100001010110000111001111011110011001000000000000 k
b100000 F
1"
#17500
0"
#17550
b11001111011110011001000000000000 <
0L
11
b1111110001011100110000100111000000 /
b1111110001011100110000100111000000 K
0m
1*
b1001111100110111100001010110000111001111011110011001000000000000 +
b1001111100110111100001010110000111001111011110011001000000000000 l
1"
#17600
0"
