utils/encording.v
// Decay modes
`define LIF0 3'b000
`define LIF2 3'b001
`define LIF4 3'b010
`define LIF8 3'b011
`define LIF24 3'b100
`define IZHI 3'b101
`define QUAD 3'b110
`define IDLE 3'b111

// Adder model
`define LIF 2'b00
`define IZHI_AD 2'b01
`define QLIF 2'b10

// Adder init mode
`define DEFAULT 3'b000
`define A 3'b001
`define B 3'b010
`define C 3'b011
`define D 3'b100
`define VT 3'b101
`define U 3'b110

code/neuro_int/neuron/controller.v
`timescale 1ns/100ps

module Controller_N(
    input wire load_data,
    input wire [7:0] data,
    input wire clk, rst,
    output reg load,
    output reg [31:0] value,
    output reg [9:0] address,
    output reg [2:0] decay_mode,
    output reg [2:0] init_mode_adder,
    output reg [1:0] adder_model,
    output reg init_mode_acc
);

    reg [7:0] controller_mode;
    reg [1:0] controller_status;
    reg [7:0] buffer [2:0];
    reg [1:0] buffer_status;
    reg [1:0] buffer_mode;
    reg data_ready;

    always @(posedge load_data) begin
        data_ready <= 1;
    end

    always @(posedge clk) begin
        if (rst) begin
            load <= 0;
            address <= 0;
            value <= 0;
            decay_mode <= 0;
            adder_model <= 0;
            init_mode_adder <= 0;
            init_mode_acc <= 0;
            controller_mode <= 0;
            controller_status <= `MODE_SELECT;
            buffer[0] <= 0;
            buffer[1] <= 0;
            buffer[2] <= 0;
            buffer_status <= 0;
            buffer_mode <= `BUFFER_IDLE;
            data_ready <= 0;
        end else if (data_ready) begin
            if (controller_status == `MODE_SELECT) begin
                if(data == `END_PACKET) begin
                    load <= 1;
                    #10 load <= 0;
                end else begin
                    load <= 0;
                    controller_mode <= data;
                    controller_status <= `MODE_LOAD;
                end
            end else if (controller_status == `MODE_LOAD) begin
                buffer[buffer_status] <= data;
                buffer_status <= buffer_status + 1;
                if (buffer_status == `ADDRESS_DONE) begin
                    decay_mode <= buffer[0][2:0];
                    init_mode_adder <= buffer[0][5:3];
                    adder_model <= buffer[0][7:6];
                    init_mode_acc <= data[0];
                    buffer_status <= 0;
                    if (controller_mode == `SET_CONTROL_SIGNALS) begin
                        controller_status <= `MODE_SELECT;
                    end else begin
                        controller_status = `MODE_BUFFER;
                        if(controller_mode == `ADDR_WEIGHT_SET) begin
                            buffer_mode <= `BUFFER_ADDRESS;
                        end else if(controller_mode == `WEIGHT_SET) begin
                            buffer_mode <= `BUFFER_VALUE;
                        end
                    end                    
                end
            end else if (controller_status == `MODE_BUFFER) begin
                buffer[buffer_status] <= data;
                buffer_status <= buffer_status + 1;
                if (buffer_mode == `BUFFER_ADDRESS) begin
                    if (buffer_status == `ADDRESS_DONE) begin
                        address <= {data[1:0], buffer[0][7:0]};
                        buffer_mode <= `BUFFER_VALUE;
                        buffer_status <= 0;
                    end
                end else if (buffer_mode == `BUFFER_VALUE) begin
                    if(buffer_status == `VALUE_DONE) begin
                        value <= {data, buffer[2], buffer[1], buffer[0]};
                        buffer_mode <= `BUFFER_IDLE;
                        controller_status <= `MODE_SELECT;
                        buffer_status <= 0;
                    end
                end
            end
            data_ready <= 0;
        end
    end

endmodule

code/neuro_int/neuron/controller_tb.v
`include "../utils/encording.v"
`include "controller.v"
`timescale 1ns/100ps

module controller_tb();
    reg clk, rst;
    reg [7:0] data;
    reg load_data;
    wire load;
    wire [31:0] value;
    wire [9:0] address;
    wire [2:0] decay_mode;
    wire [2:0] init_mode_adder;
    wire [1:0] adder_model;
    wire init_mode_acc;

    Controller_N controller(
        .data(data),
        .clk(clk),
        .rst(rst),
        .load_data(load_data),
        .load(load),
        .value(value),
        .address(address),
        .decay_mode(decay_mode),
        .init_mode_adder(init_mode_adder),
        .adder_model(adder_model),
        .init_mode_acc(init_mode_acc)
    );

    always #5 clk = ~clk;

    initial begin
        $dumpfile("controller_tb.vcd");
        $dumpvars(0, controller_tb);

        clk = 0;
        rst = 1;
        data = 0;
        #10 rst = 0;

        #30 data = 8'b11111111;
        load_data <= 1; #10 load_data <= 0;
        #30 data = 8'b00111000;
        load_data <= 1; #10 load_data <= 0;
        #30 data = 8'b00000001;
        load_data <= 1; #10 load_data <= 0;
        #30 data = 8'b10101111;
        load_data <= 1; #10 load_data <= 0;
        #30 data = 8'b00000010;
        load_data <= 1; #10 load_data <= 0;
        #30 data = 8'b00000011;
        load_data <= 1; #10 load_data <= 0;
        #30 data = 8'b00000100;
        load_data <= 1; #10 load_data <= 0;
        #30 data = 8'b00000101;
        load_data <= 1; #10 load_data <= 0;
        #30 data = 8'b00000110;
        load_data <= 1; #10 load_data <= 0;
        #30 data = 8'b00000000;
        load_data <= 1; #10 load_data <= 0;

        #50;

        #30 data = 8'b11111110;
        load_data <= 1; #10 load_data <= 0;
        #30 data = 8'b00111111;
        load_data <= 1; #10 load_data <= 0;
        #30 data = 8'b00000000;
        load_data <= 1; #10 load_data <= 0;
        #30 data = 8'b10101111;
        load_data <= 1; #10 load_data <= 0;
        #30 data = 8'b00000010;
        load_data <= 1; #10 load_data <= 0;
        #30 data = 8'b00000011;
        load_data <= 1; #10 load_data <= 0;
        #30 data = 8'b00000100;
        load_data <= 1; #10 load_data <= 0;
        #30 data = 8'b00000000;
        load_data <= 1; #10 load_data <= 0;

        #100
        $finish;
    end

endmodule

code/neuro_int/neuron/controller_tb.vcd
$date
	Thu Feb 06 18:48:10 2025
$end
$version
	Icarus Verilog
$end
$timescale
	100ps
$end
$scope module controller_tb $end
$var wire 32 ! value [31:0] $end
$var wire 1 " load $end
$var wire 3 # init_mode_adder [2:0] $end
$var wire 1 $ init_mode_acc $end
$var wire 3 % decay_mode [2:0] $end
$var wire 10 & address [9:0] $end
$var wire 2 ' adder_model [1:0] $end
$var reg 1 ( clk $end
$var reg 8 ) data [7:0] $end
$var reg 1 * load_data $end
$var reg 1 + rst $end
$scope module controller $end
$var wire 1 ( clk $end
$var wire 8 , data [7:0] $end
$var wire 1 * load_data $end
$var wire 1 + rst $end
$var reg 2 - adder_model [1:0] $end
$var reg 10 . address [9:0] $end
$var reg 2 / buffer_mode [1:0] $end
$var reg 2 0 buffer_status [1:0] $end
$var reg 8 1 controller_mode [7:0] $end
$var reg 2 2 controller_status [1:0] $end
$var reg 1 3 data_ready $end
$var reg 3 4 decay_mode [2:0] $end
$var reg 1 $ init_mode_acc $end
$var reg 3 5 init_mode_adder [2:0] $end
$var reg 1 " load $end
$var reg 32 6 value [31:0] $end
$upscope $end
$upscope $end
$enddefinitions $end
$comment Show the parameter values. $end
$dumpall
$end
#0
$dumpvars
bx 6
bx 5
bx 4
x3
bx 2
bx 1
bx 0
bx /
bx .
bx -
b0 ,
1+
x*
b0 )
0(
bx '
bx &
bx %
x$
bx #
x"
bx !
$end
#50
03
b0 /
b0 0
b0 2
b0 1
0$
b0 #
b0 5
b0 '
b0 -
b0 %
b0 4
b0 !
b0 6
b0 &
b0 .
0"
1(
#100
0(
0+
#150
1(
#200
0(
#250
1(
#300
0(
#350
1(
#400
13
1*
0(
b11111111 )
b11111111 ,
#450
03
b1 2
b11111111 1
1(
#500
0*
0(
#550
1(
#600
0(
#650
1(
#700
0(
#750
1(
#800
13
1*
0(
b111000 )
b111000 ,
#850
03
b1 0
1(
#900
0*
0(
#950
1(
#1000
0(
#1050
1(
#1100
0(
#1150
1(
#1200
13
1*
0(
b1 )
b1 ,
#1250
03
b1 /
1$
b111 #
b111 5
b0 0
b10 2
1(
#1300
0*
0(
#1350
1(
#1400
0(
#1450
1(
#1500
0(
#1550
1(
#1600
13
1*
0(
b10101111 )
b10101111 ,
#1650
03
b1 0
1(
#1700
0*
0(
#1750
1(
#1800
0(
#1850
1(
#1900
0(
#1950
1(
#2000
13
1*
0(
b10 )
b10 ,
#2050
03
b10 /
b1010101111 &
b1010101111 .
b0 0
1(
#2100
0*
0(
#2150
1(
#2200
0(
#2250
1(
#2300
0(
#2350
1(
#2400
13
1*
0(
b11 )
b11 ,
#2450
03
b1 0
1(
#2500
0*
0(
#2550
1(
#2600
0(
#2650
1(
#2700
0(
#2750
1(
#2800
13
1*
0(
b100 )
b100 ,
#2850
03
b10 0
1(
#2900
0*
0(
#2950
1(
#3000
0(
#3050
1(
#3100
0(
#3150
1(
#3200
13
1*
0(
b101 )
b101 ,
#3250
03
b11 0
1(
#3300
0*
0(
#3350
1(
#3400
0(
#3450
1(
#3500
0(
#3550
1(
#3600
13
1*
0(
b110 )
b110 ,
#3650
03
b0 2
b0 /
b110000001010000010000000011 !
b110000001010000010000000011 6
b0 0
1(
#3700
0*
0(
#3750
1(
#3800
0(
#3850
1(
#3900
0(
#3950
1(
#4000
13
1*
0(
b0 )
b0 ,
#4050
1"
1(
#4100
0*
0(
#4150
03
1"
1(
#4200
0(
#4250
0"
1(
#4300
0(
#4350
1(
#4400
0(
#4450
1(
#4500
0(
#4550
1(
#4600
0(
#4650
1(
#4700
0(
#4750
1(
#4800
0(
#4850
1(
#4900
13
1*
0(
b11111110 )
b11111110 ,
#4950
03
b1 2
b11111110 1
1(
#5000
0*
0(
#5050
1(
#5100
0(
#5150
1(
#5200
0(
#5250
1(
#5300
13
1*
0(
b111111 )
b111111 ,
#5350
03
b1 0
1(
#5400
0*
0(
#5450
1(
#5500
0(
#5550
1(
#5600
0(
#5650
1(
#5700
13
1*
0(
b0 )
b0 ,
#5750
03
b10 /
0$
b111 %
b111 4
b0 0
b10 2
1(
#5800
0*
0(
#5850
1(
#5900
0(
#5950
1(
#6000
0(
#6050
1(
#6100
13
1*
0(
b10101111 )
b10101111 ,
#6150
03
b1 0
1(
#6200
0*
0(
#6250
1(
#6300
0(
#6350
1(
#6400
0(
#6450
1(
#6500
13
1*
0(
b10 )
b10 ,
#6550
03
b10 0
1(
#6600
0*
0(
#6650
1(
#6700
0(
#6750
1(
#6800
0(
#6850
1(
#6900
13
1*
0(
b11 )
b11 ,
#6950
03
b11 0
1(
#7000
0*
0(
#7050
1(
#7100
0(
#7150
1(
#7200
0(
#7250
1(
#7300
13
1*
0(
b100 )
b100 ,
#7350
03
b0 2
b0 /
b100000000110000001010101111 !
b100000000110000001010101111 6
b0 0
1(
#7400
0*
0(
#7450
1(
#7500
0(
#7550
1(
#7600
0(
#7650
1(
#7700
13
1*
0(
b0 )
b0 ,
#7750
1"
1(
#7800
0*
0(
#7850
03
1"
1(
#7900
0(
#7950
0"
1(
#8000
0(
#8050
1(
#8100
0(
#8150
1(
#8200
0(
#8250
1(
#8300
0(
#8350
1(
#8400
0(
#8450
1(
#8500
0(
#8550
1(
#8600
13
1*
0(
b11111110 )
b11111110 ,
#8650
03
b1 2
1(
#8700
0*
0(
#8750
1(
#8800
0(
#8850
1(
#8900
0(
#8950
1(
#9000
13
1*
0(
b1000 )
b1000 ,
#9050
03
b1 0
1(
#9100
0*
0(
#9150
1(
#9200
0(
#9250
1(
#9300
0(
#9350
1(
#9400
13
1*
0(
b0 )
b0 ,
#9450
03
b10 /
b1 #
b1 5
b0 %
b0 4
b0 0
b10 2
1(
#9500
0*
0(
#9550
1(
#9600
0(
#9650
1(
#9700
0(
#9750
1(
#9800
13
1*
0(
b10101111 )
b10101111 ,
#9850
03
b1 0
1(
#9900
0*
0(
#9950
1(
#10000
0(
#10050
1(
#10100
0(
#10150
1(
#10200
13
1*
0(
b10 )
b10 ,
#10250
03
b10 0
1(
#10300
0*
0(
#10350
1(
#10400
0(
#10450
1(
#10500
0(
#10550
1(
#10600
13
1*
0(
b11 )
b11 ,
#10650
03
b11 0
1(
#10700
0*
0(
#10750
1(
#10800
0(
#10850
1(
#10900
0(
#10950
1(
#11000
13
1*
0(
b100100 )
b100100 ,
#11050
03
b0 2
b0 /
b100100000000110000001010101111 !
b100100000000110000001010101111 6
b0 0
1(
#11100
0*
0(
#11150
1(
#11200
0(
#11250
1(
#11300
0(
#11350
1(
#11400
13
1*
0(
b0 )
b0 ,
#11450
1"
1(
#11500
0*
0(
#11550
03
1"
1(
#11600
0(
#11650
0"
1(
#11700
0(
#11750
1(
#11800
0(
#11850
1(
#11900
0(
#11950
1(
#12000
0(
#12050
1(
#12100
0(
#12150
1(
#12200
0(
#12250
1(
#12300
13
1*
0(
b11111110 )
b11111110 ,
#12350
03
b1 2
1(
#12400
0*
0(
#12450
1(
#12500
0(
#12550
1(
#12600
0(
#12650
1(
#12700
13
1*
0(
b10000 )
b10000 ,
#12750
03
b1 0
1(
#12800
0*
0(
#12850
1(
#12900
0(
#12950
1(
#13000
0(
#13050
1(
#13100
13
1*
0(
b0 )
b0 ,
#13150
03
b10 /
b10 #
b10 5
b0 0
b10 2
1(
#13200
0*
0(
#13250
1(
#13300
0(
#13350
1(
#13400
0(
#13450
1(
#13500
13
1*
0(
b10101111 )
b10101111 ,
#13550
03
b1 0
1(
#13600
0*
0(
#13650
1(
#13700
0(
#13750
1(
#13800
0(
#13850
1(
#13900
13
1*
0(
b10 )
b10 ,
#13950
03
b10 0
1(
#14000
0*
0(
#14050
1(
#14100
0(
#14150
1(
#14200
0(
#14250
1(
#14300
13
1*
0(
b11 )
b11 ,
#14350
03
b11 0
1(
#14400
0*
0(
#14450
1(
#14500
0(
#14550
1(
#14600
0(
#14650
1(
#14700
13
1*
0(
b100100 )
b100100 ,
#14750
03
b0 2
b0 /
b0 0
1(
#14800
0*
0(
#14850
1(
#14900
0(
#14950
1(
#15000
0(
#15050
1(
#15100
13
1*
0(
b0 )
b0 ,
#15150
1"
1(
#15200
0*
0(
#15250
03
1"
1(
#15300
0(
#15350
0"
1(
#15400
0(
#15450
1(
#15500
0(
#15550
1(
#15600
0(
#15650
1(
#15700
0(
#15750
1(
#15800
0(
#15850
1(
#15900
0(
#15950
1(
#16000
13
1*
0(
b11111110 )
b11111110 ,
#16050
03
b1 2
1(
#16100
0*
0(
#16150
1(
#16200
0(
#16250
1(
#16300
0(
#16350
1(
#16400
13
1*
0(
b11000 )
b11000 ,
#16450
03
b1 0
1(
#16500
0*
0(
#16550
1(
#16600
0(
#16650
1(
#16700
0(
#16750
1(
#16800
13
1*
0(
b0 )
b0 ,
#16850
03
b10 /
b11 #
b11 5
b0 0
b10 2
1(
#16900
0*
0(
#16950
1(
#17000
0(
#17050
1(
#17100
0(
#17150
1(
#17200
13
1*
0(
b10101111 )
b10101111 ,
#17250
03
b1 0
1(
#17300
0*
0(
#17350
1(
#17400
0(
#17450
1(
#17500
0(
#17550
1(
#17600
13
1*
0(
b10 )
b10 ,
#17650
03
b10 0
1(
#17700
0*
0(
#17750
1(
#17800
0(
#17850
1(
#17900
0(
#17950
1(
#18000
13
1*
0(
b11 )
b11 ,
#18050
03
b11 0
1(
#18100
0*
0(
#18150
1(
#18200
0(
#18250
1(
#18300
0(
#18350
1(
#18400
13
1*
0(
b100100 )
b100100 ,
#18450
03
b0 2
b0 /
b0 0
1(
#18500
0*
0(
#18550
1(
#18600
0(
#18650
1(
#18700
0(
#18750
1(
#18800
13
1*
0(
b0 )
b0 ,
#18850
1"
1(
#18900
0*
0(
#18950
03
1"
1(
#19000
0(
#19050
0"
1(
#19100
0(
#19150
1(
#19200
0(
#19250
1(
#19300
0(
#19350
1(
#19400
0(
#19450
1(
#19500
0(
#19550
1(
#19600
0(
#19650
1(
#19700
13
1*
0(
b11111110 )
b11111110 ,
#19750
03
b1 2
1(
#19800
0*
0(
#19850
1(
#19900
0(
#19950
1(
#20000
0(
#20050
1(
#20100
13
1*
0(
b100000 )
b100000 ,
#20150
03
b1 0
1(
#20200
0*
0(
#20250
1(
#20300
0(
#20350
1(
#20400
0(
#20450
1(
#20500
13
1*
0(
b0 )
b0 ,
#20550
03
b10 /
b100 #
b100 5
b0 0
b10 2
1(
#20600
0*
0(
#20650
1(
#20700
0(
#20750
1(
#20800
0(
#20850
1(
#20900
13
1*
0(
b10101111 )
b10101111 ,
#20950
03
b1 0
1(
#21000
0*
0(
#21050
1(
#21100
0(
#21150
1(
#21200
0(
#21250
1(
#21300
13
1*
0(
b10 )
b10 ,
#21350
03
b10 0
1(
#21400
0*
0(
#21450
1(
#21500
0(
#21550
1(
#21600
0(
#21650
1(
#21700
13
1*
0(
b11 )
b11 ,
#21750
03
b11 0
1(
#21800
0*
0(
#21850
1(
#21900
0(
#21950
1(
#22000
0(
#22050
1(
#22100
13
1*
0(
b100100 )
b100100 ,
#22150
03
b0 2
b0 /
b0 0
1(
#22200
0*
0(
#22250
1(
#22300
0(
#22350
1(
#22400
0(
#22450
1(
#22500
13
1*
0(
b0 )
b0 ,
#22550
1"
1(
#22600
0*
0(
#22650
03
1"
1(
#22700
0(
#22750
0"
1(
#22800
0(
#22850
1(
#22900
0(
#22950
1(
#23000
0(
#23050
1(
#23100
0(
#23150
1(
#23200
0(
#23250
1(
#23300
0(
#23350
1(
#23400
13
1*
0(
b11111110 )
b11111110 ,
#23450
03
b1 2
1(
#23500
0*
0(
#23550
1(
#23600
0(
#23650
1(
#23700
0(
#23750
1(
#23800
13
1*
0(
b101000 )
b101000 ,
#23850
03
b1 0
1(
#23900
0*
0(
#23950
1(
#24000
0(
#24050
1(
#24100
0(
#24150
1(
#24200
13
1*
0(
b0 )
b0 ,
#24250
03
b10 /
b101 #
b101 5
b0 0
b10 2
1(
#24300
0*
0(
#24350
1(
#24400
0(
#24450
1(
#24500
0(
#24550
1(
#24600
13
1*
0(
b10101111 )
b10101111 ,
#24650
03
b1 0
1(
#24700
0*
0(
#24750
1(
#24800
0(
#24850
1(
#24900
0(
#24950
1(
#25000
13
1*
0(
b10 )
b10 ,
#25050
03
b10 0
1(
#25100
0*
0(
#25150
1(
#25200
0(
#25250
1(
#25300
0(
#25350
1(
#25400
13
1*
0(
b11 )
b11 ,
#25450
03
b11 0
1(
#25500
0*
0(
#25550
1(
#25600
0(
#25650
1(
#25700
0(
#25750
1(
#25800
13
1*
0(
b100100 )
b100100 ,
#25850
03
b0 2
b0 /
b0 0
1(
#25900
0*
0(
#25950
1(
#26000
0(
#26050
1(
#26100
0(
#26150
1(
#26200
13
1*
0(
b0 )
b0 ,
#26250
1"
1(
#26300
0*
0(
#26350
03
1"
1(
#26400
0(
#26450
0"
1(
#26500
0(
#26550
1(
#26600
0(
#26650
1(
#26700
0(
#26750
1(
#26800
0(
#26850
1(
#26900
0(
#26950
1(
#27000
0(
#27050
1(
#27100
13
1*
0(
b11111110 )
b11111110 ,
#27150
03
b1 2
1(
#27200
0*
0(
#27250
1(
#27300
0(
#27350
1(
#27400
0(
#27450
1(
#27500
13
1*
0(
b110000 )
b110000 ,
#27550
03
b1 0
1(
#27600
0*
0(
#27650
1(
#27700
0(
#27750
1(
#27800
0(
#27850
1(
#27900
13
1*
0(
b0 )
b0 ,
#27950
03
b10 /
b110 #
b110 5
b0 0
b10 2
1(
#28000
0*
0(
#28050
1(
#28100
0(
#28150
1(
#28200
0(
#28250
1(
#28300
13
1*
0(
b10101111 )
b10101111 ,
#28350
03
b1 0
1(
#28400
0*
0(
#28450
1(
#28500
0(
#28550
1(
#28600
0(
#28650
1(
#28700
13
1*
0(
b10 )
b10 ,
#28750
03
b10 0
1(
#28800
0*
0(
#28850
1(
#28900
0(
#28950
1(
#29000
0(
#29050
1(
#29100
13
1*
0(
b11 )
b11 ,
#29150
03
b11 0
1(
#29200
0*
0(
#29250
1(
#29300
0(
#29350
1(
#29400
0(
#29450
1(
#29500
13
1*
0(
b100100 )
b100100 ,
#29550
03
b0 2
b0 /
b0 0
1(
#29600
0*
0(
#29650
1(
#29700
0(
#29750
1(
#29800
0(
#29850
1(
#29900
13
1*
0(
b0 )
b0 ,
#29950
1"
1(
#30000
0*
0(
#30050
03
1"
1(
#30100
0(
#30150
0"
1(
#30200
0(
#30250
1(
#30300
0(
#30350
1(
#30400
0(
#30450
1(
#30500
0(
#30550
1(
#30600
0(
#30650
1(
#30700
0(
#30750
1(
#30800
13
1*
0(
b11111101 )
b11111101 ,
#30850
03
b1 2
b11111101 1
1(
#30900
0*
0(
#30950
1(
#31000
0(
#31050
1(
#31100
0(
#31150
1(
#31200
13
1*
0(
b1 )
b1 ,
#31250
03
b1 0
1(
#31300
0*
0(
#31350
1(
#31400
0(
#31450
1(
#31500
0(
#31550
1(
#31600
13
1*
0(
b0 )
b0 ,
#31650
03
b0 2
b0 #
b0 5
b1 %
b1 4
b0 0
1(
#31700
0*
0(
#31750
1(
#31800
0(
#31850
1(
#31900
0(
#31950
1(
#32000
13
1*
0(
#32050
1"
1(
#32100
0*
0(
#32150
03
1"
1(
#32200
0(
#32250
0"
1(
