utils/encording.v
// Decay modes
`define LIF0 3'b000
`define LIF2 3'b001
`define LIF4 3'b010
`define LIF8 3'b011
`define LIF24 3'b100
`define IZHI 3'b101
`define QUAD 3'b110
`define IDLE 3'b111

// Adder model
`define LIF 2'b00
`define IZHI_AD 2'b01
`define QLIF 2'b10

// Adder init mode
`define DEFAULT 3'b000
`define A 3'b001
`define B 3'b010
`define C 3'b011
`define D 3'b100
`define VT 3'b101
`define U 3'b110

code/neuro_int/neuron/controller.v
`timescale 1ns/100ps

module Controller_N(
    input wire load_data,
    input wire [7:0] data,
    input wire clk, rst,
    output reg load,
    output reg [31:0] value,
    output reg [9:0] address,
    output reg [2:0] decay_mode,
    output reg [2:0] init_mode_adder,
    output reg [1:0] adder_model,
    output reg init_mode_acc
);

    reg [7:0] controller_mode;
    reg [1:0] controller_status;
    reg [7:0] buffer [3:0];
    reg [1:0] buffer_status;
    reg [1:0] buffer_mode;
    reg data_ready;

    always @(posedge load_data) begin
        data_ready <= 1;
    end

    always @(posedge clk) begin
        if (rst) begin
            load <= 0;
            address <= 0;
            value <= 0;
            decay_mode <= 0;
            adder_model <= 0;
            init_mode_adder <= 0;
            init_mode_acc <= 0;
            controller_mode <= 0;
            controller_status <= `MODE_SELECT;
            buffer[0] <= 0;
            buffer[1] <= 0;
            buffer[2] <= 0;
            buffer[3] <= 0;
            buffer_status <= 0;
            buffer_mode <= `BUFFER_IDLE;
            data_ready <= 0;
        end else if (data_ready) begin
            if (controller_status == `MODE_SELECT) begin
                if(data == `END_PACKET) begin
                    load <= 1;
                end else begin
                    load <= 0;
                    controller_mode <= data;
                    controller_status <= `MODE_LOAD;
                end
            end else if (controller_status == `MODE_LOAD) begin
                buffer[buffer_status] <= data;
                buffer_status <= buffer_status + 1;
                if (buffer_status == `ADDRESS_DONE) begin
                    decay_mode <= buffer[0][2:0];
                    init_mode_adder <= buffer[0][5:3];
                    adder_model <= buffer[0][7:6];
                    init_mode_acc <= data[0];
                    buffer_status <= 0;
                    if (controller_mode == `SET_CONTROL_SIGNALS) begin
                        controller_status <= `MODE_SELECT;
                    end else begin
                        controller_status = `MODE_BUFFER;
                        if(controller_mode == `ADDR_WEIGHT_SET) begin
                            buffer_mode <= `BUFFER_ADDRESS;
                        end else if(controller_mode == `WEIGHT_SET) begin
                            buffer_mode <= `BUFFER_VALUE;
                        end
                    end                    
                end
            end else if (controller_status == `MODE_BUFFER) begin
                buffer[buffer_status] <= data;
                buffer_status <= buffer_status + 1;
                if (buffer_mode == `BUFFER_ADDRESS) begin
                    if (buffer_status == `ADDRESS_DONE) begin
                        address <= {data[1:0], buffer[0][7:0]};
                        buffer_mode <= `BUFFER_VALUE;
                        buffer_status <= 0;
                    end
                end else if (buffer_mode == `BUFFER_VALUE) begin
                    if(buffer_status == `VALUE_DONE) begin
                        value <= {data, buffer[2], buffer[1], buffer[0]};
                        buffer_mode <= `BUFFER_IDLE;
                        controller_status <= `MODE_SELECT;
                        buffer_status <= 0;
                    end
                end
            end
            data_ready <= 0;
        end
    end

endmodule

code/neuro_int/neuron/controller_tb.v
`include "../utils/encording.v"
`include "controller.v"
`timescale 1ns/100ps

module controller_tb();
    reg clk, rst;
    reg [7:0] data;
    reg load_data;
    wire load;
    wire [31:0] value;
    wire [9:0] address;
    wire [2:0] decay_mode;
    wire [2:0] init_mode_adder;
    wire [1:0] adder_model;
    wire init_mode_acc;

    Controller_N controller(
        .data(data),
        .clk(clk),
        .rst(rst),
        .load_data(load_data),
        .load(load),
        .value(value),
        .address(address),
        .decay_mode(decay_mode),
        .init_mode_adder(init_mode_adder),
        .adder_model(adder_model),
        .init_mode_acc(init_mode_acc)
    );

    always #5 clk = ~clk;

    initial begin
        $dumpfile("controller_tb.vcd");
        $dumpvars(0, controller_tb);

        clk = 0;
        rst = 1;
        data = 0;
        #10 rst = 0;

        #30 data = 8'b11111111;
        load_data <= 1; #10 load_data <= 0;
        #30 data = 8'b00111000;
        load_data <= 1; #10 load_data <= 0;
        #30 data = 8'b00000001;
        load_data <= 1; #10 load_data <= 0;
        #30 data = 8'b10101111;
        load_data <= 1; #10 load_data <= 0;
        #30 data = 8'b00000010;
        load_data <= 1; #10 load_data <= 0;
        #30 data = 8'b00000011;
        load_data <= 1; #10 load_data <= 0;
        #30 data = 8'b00000100;
        load_data <= 1; #10 load_data <= 0;
        #30 data = 8'b00000101;
        load_data <= 1; #10 load_data <= 0;
        #30 data = 8'b00000110;
        load_data <= 1; #10 load_data <= 0;
        #30 data = 8'b00000000;
        load_data <= 1; #10 load_data <= 0;

        #50;

        #30 data = 8'b11111110;
        load_data <= 1; #10 load_data <= 0;
        #30 data = 8'b00111111;
        load_data <= 1; #10 load_data <= 0;
        #30 data = 8'b00000000;
        load_data <= 1; #10 load_data <= 0;
        #30 data = 8'b10101111;
        load_data <= 1; #10 load_data <= 0;
        #30 data = 8'b00000010;
        load_data <= 1; #10 load_data <= 0;
        #30 data = 8'b00000011;
        load_data <= 1; #10 load_data <= 0;
        #30 data = 8'b00000100;
        load_data <= 1; #10 load_data <= 0;
        #30 data = 8'b00000000;
        load_data <= 1; #10 load_data <= 0;

        #100
        $finish;
    end

endmodule

code/neuro_int/neuron/controller_tb.vcd
$date
	Thu Feb 06 09:45:36 2025
$end
$version
	Icarus Verilog
$end
$timescale
	100ps
$end
$scope module controller_tb $end
$var wire 32 ! value [31:0] $end
$var wire 1 " load $end
$var wire 3 # init_mode_adder [2:0] $end
$var wire 1 $ init_mode_acc $end
$var wire 3 % decay_mode [2:0] $end
$var wire 10 & address [9:0] $end
$var wire 2 ' adder_model [1:0] $end
$var reg 1 ( clk $end
$var reg 8 ) data [7:0] $end
$var reg 1 * load_data $end
$var reg 1 + rst $end
$scope module controller $end
$var wire 1 ( clk $end
$var wire 8 , data [7:0] $end
$var wire 1 * load_data $end
$var wire 1 + rst $end
$var reg 2 - adder_model [1:0] $end
$var reg 10 . address [9:0] $end
$var reg 2 / buffer_mode [1:0] $end
$var reg 2 0 buffer_status [1:0] $end
$var reg 8 1 controller_mode [7:0] $end
$var reg 2 2 controller_status [1:0] $end
$var reg 1 3 data_ready $end
$var reg 3 4 decay_mode [2:0] $end
$var reg 1 $ init_mode_acc $end
$var reg 3 5 init_mode_adder [2:0] $end
$var reg 1 " load $end
$var reg 32 6 value [31:0] $end
$upscope $end
$upscope $end
$enddefinitions $end
$comment Show the parameter values. $end
$dumpall
$end
#0
$dumpvars
bx 6
bx 5
bx 4
x3
bx 2
bx 1
bx 0
bx /
bx .
bx -
b0 ,
1+
x*
b0 )
0(
bx '
bx &
bx %
x$
bx #
x"
bx !
$end
#50
03
b0 /
b0 0
b0 2
b0 1
0$
b0 #
b0 5
b0 '
b0 -
b0 %
b0 4
b0 !
b0 6
b0 &
b0 .
0"
1(
#100
0(
0+
#150
1(
#200
0(
#250
1(
#300
0(
#350
1(
#400
13
1*
0(
b11111111 )
b11111111 ,
#450
03
b1 2
b11111111 1
1(
#500
0*
0(
#550
1(
#600
0(
#650
1(
#700
0(
#750
1(
#800
13
1*
0(
b111000 )
b111000 ,
#850
03
b1 0
1(
#900
0*
0(
#950
1(
#1000
0(
#1050
1(
#1100
0(
#1150
1(
#1200
13
1*
0(
b1 )
b1 ,
#1250
03
b1 /
1$
b111 #
b111 5
b0 0
b10 2
1(
#1300
0*
0(
#1350
1(
#1400
0(
#1450
1(
#1500
0(
#1550
1(
#1600
13
1*
0(
b10101111 )
b10101111 ,
#1650
03
b1 0
1(
#1700
0*
0(
#1750
1(
#1800
0(
#1850
1(
#1900
0(
#1950
1(
#2000
13
1*
0(
b10 )
b10 ,
#2050
03
b10 /
b1010101111 &
b1010101111 .
b0 0
1(
#2100
0*
0(
#2150
1(
#2200
0(
#2250
1(
#2300
0(
#2350
1(
#2400
13
1*
0(
b11 )
b11 ,
#2450
03
b1 0
1(
#2500
0*
0(
#2550
1(
#2600
0(
#2650
1(
#2700
0(
#2750
1(
#2800
13
1*
0(
b100 )
b100 ,
#2850
03
b10 0
1(
#2900
0*
0(
#2950
1(
#3000
0(
#3050
1(
#3100
0(
#3150
1(
#3200
13
1*
0(
b101 )
b101 ,
#3250
03
b11 0
1(
#3300
0*
0(
#3350
1(
#3400
0(
#3450
1(
#3500
0(
#3550
1(
#3600
13
1*
0(
b110 )
b110 ,
#3650
03
b0 2
b0 /
b110000001010000010000000011 !
b110000001010000010000000011 6
b0 0
1(
#3700
0*
0(
#3750
1(
#3800
0(
#3850
1(
#3900
0(
#3950
1(
#4000
13
1*
0(
b0 )
b0 ,
#4050
03
1"
1(
#4100
0*
0(
#4150
1(
#4200
0(
#4250
1(
#4300
0(
#4350
1(
#4400
0(
#4450
1(
#4500
0(
#4550
1(
#4600
0(
#4650
1(
#4700
0(
#4750
1(
#4800
0(
#4850
1(
#4900
13
1*
0(
b11111110 )
b11111110 ,
#4950
03
b1 2
b11111110 1
0"
1(
#5000
0*
0(
#5050
1(
#5100
0(
#5150
1(
#5200
0(
#5250
1(
#5300
13
1*
0(
b111111 )
b111111 ,
#5350
03
b1 0
1(
#5400
0*
0(
#5450
1(
#5500
0(
#5550
1(
#5600
0(
#5650
1(
#5700
13
1*
0(
b0 )
b0 ,
#5750
03
b10 /
0$
b111 %
b111 4
b0 0
b10 2
1(
#5800
0*
0(
#5850
1(
#5900
0(
#5950
1(
#6000
0(
#6050
1(
#6100
13
1*
0(
b10101111 )
b10101111 ,
#6150
03
b1 0
1(
#6200
0*
0(
#6250
1(
#6300
0(
#6350
1(
#6400
0(
#6450
1(
#6500
13
1*
0(
b10 )
b10 ,
#6550
03
b10 0
1(
#6600
0*
0(
#6650
1(
#6700
0(
#6750
1(
#6800
0(
#6850
1(
#6900
13
1*
0(
b11 )
b11 ,
#6950
03
b11 0
1(
#7000
0*
0(
#7050
1(
#7100
0(
#7150
1(
#7200
0(
#7250
1(
#7300
13
1*
0(
b100 )
b100 ,
#7350
03
b0 2
b0 /
b100000000110000001010101111 !
b100000000110000001010101111 6
b0 0
1(
#7400
0*
0(
#7450
1(
#7500
0(
#7550
1(
#7600
0(
#7650
1(
#7700
13
1*
0(
b0 )
b0 ,
#7750
03
1"
1(
#7800
0*
0(
