utils/encording.v
// Decay modes
`define LIF0 3'b000
`define LIF2 3'b001
`define LIF4 3'b010
`define LIF8 3'b011
`define LIF24 3'b100
`define IZHI 3'b101
`define QUAD 3'b110
`define IDLE 3'b111

// Adder model
`define LIF 2'b00
`define IZHI_AD 2'b01
`define QLIF 2'b10

// Adder init mode
`define DEFAULT 3'b000
`define A 3'b001
`define B 3'b010
`define C 3'b011
`define D 3'b100
`define VT 3'b101
`define U 3'b110

utils/32bit_mul.v
module multiplier_32bit(
    input wire clk,
    input wire rst,
    input wire start,
    input wire [31:0] A,
    input wire [31:0] B,
    output reg [63:0] result,
    output reg done
);
    
    reg [31:0] multiplicand, multiplier;
    reg [63:0] product;
    reg [5:0] count;
    reg running;

    always @(posedge rst) begin
        multiplicand <= 0;
        multiplier <= 0;
        product <= 0;
        count <= 0;
        running <= 0;
        done <= 0;
    end

    always @(posedge start) begin
        multiplicand <= A;
        multiplier <= B;
        product <= 0;
        count <= 0;
        running <= 1;
        done <= 0;
    end

    always @(posedge clk) begin
        if (running) begin
            if (count < 32) begin
                if (multiplier[0] == 1'b1) begin
                    product = product + ({32'b0, multiplicand} << count);
                end
                multiplier = multiplier >> 1;
                count = count + 1;
            end else begin
                result <= product;
                done <= 1;
                running <= 0;
            end
        end
    end

endmodule

code/neuro_int/adder/adder.v
`timescale 1ns/100ps

module potential_adder (
    input wire clk,
    input wire rst,        
    input wire time_step,      
    input wire [31:0] input_weight, 
    input wire [31:0] decayed_potential,
    input wire [1:0] model,
    input wire [2:0] init_mode,
    input wire load,
    
    output reg [31:0] final_potential, 
    output reg done,
    output reg spike
);

    // Common Signals
    reg [31:0] weight_added;
    reg [31:0] u;
    reg adder_start, adder_send;

    // Internal Signals for Izhikevich Model
    wire [63:0] bv, a_bv_u;
    wire [31:0] bv_u;
    reg [31:0] a, b, c, d, v_threshold;
    
    reg bv_start, abv_start, clear_mul;
    wire bv_done, abv_done;

    multiplier_32bit multIzhiBV (
        .clk(clk),
        .rst(clear_mul),
        .start(bv_start),
        .A(b),
        .B(decayed_potential),
        .result(bv),
        .done(bv_done)
    );

    multiplier_32bit multIzhiaBVu (
        .clk(clk),
        .rst(clear_mul),
        .start(abv_start),
        .A(a),
        .B(bv_u),
        .result(a_bv_u),
        .done(abv_done)
    );

    assign bv_u = bv[31:0] - u;

    always @(posedge bv_done) begin
        bv_start <= 0;
        #10 abv_start <= 1;
    end

    always @(posedge load) begin
        if (init_mode == `A) begin
            a <= input_weight;
        end else if (init_mode == `B) begin
            b <= input_weight;
        end else if (init_mode == `C) begin
            c <= input_weight;
        end else if (init_mode == `D) begin
            d <= input_weight;
        end else if (init_mode == `VT) begin
            v_threshold <= input_weight;
        end else if (init_mode == `U) begin
            u <= input_weight;
        end
    end

    always @(posedge time_step) begin
        done <= 0;
        spike <= 0;
        clear_mul <= 1;
        #10 adder_start <= 1;
        clear_mul <= 0;
    end

    always @(posedge clk) begin
        if (rst) begin
            final_potential <= 0;
            done <= 0;
            spike <= 0;
            a <= 0;
            b <= 0;
            c <= 0;
            d <= 0;
            v_threshold <= 0;
            u <= 0;
            weight_added <= 0;
        end else if (init_mode == `DEFAULT) begin
            if (adder_start) begin
                if (model == `LIF) begin
                    weight_added <= input_weight + decayed_potential;
                end else if (model == `IZHI_AD) begin
                    weight_added <= input_weight + decayed_potential - u;
                    bv_start <= 1;
                    abv_start <= 0;
                end else if (model == `QLIF) begin
                    weight_added <= input_weight + decayed_potential;
                end
                adder_start <= 0;
                adder_send <= 1;
            end
            if(adder_send) begin
                if(model == `LIF) begin
                    spike <= (weight_added > v_threshold);
                    final_potential <= (weight_added > v_threshold) ? (weight_added - v_threshold) : weight_added;
                    done <= 1;
                    adder_send <= 0;
                end else if (model == `IZHI) begin
                    if(abv_done) begin
                        clear_mul <= 1;
                        spike <= (weight_added > v_threshold);
                        final_potential <= (weight_added > v_threshold) ? c : weight_added;
                        u <= (weight_added > v_threshold) ? u + d : a_bv_u[31:0];
                        done <= 1;
                        #10 clear_mul <= 0;
                        adder_send <= 0;
                    end
                end else if (model == `QLIF) begin
                    spike <= (weight_added > v_threshold);
                    final_potential <= (weight_added > v_threshold) ? (weight_added - v_threshold) : weight_added;
                    done <= 1;
                    adder_send <= 0;
                end
            end
        end
    end

endmodule

utils/32bit_shifter.v
module shifter_32bit (
    input wire clk,
    input wire rst,
    input wire start,
    input wire [31:0] data_in,
    input wire [4:0] shift_amount,  // Supports shifting up to 31 bits
    input wire [1:0] mode,          // 00: Logical Left, 01: Logical Right, 10: Arithmetic Right
    output reg [31:0] data_out,
    output reg done
);

    reg [31:0] shift_reg;
    reg [4:0] count;
    reg running;

    always @(posedge rst) begin
        shift_reg <= 0;
        count <= 0;
        running <= 0;
        done <= 0;
        data_out <= 0;
    end

    always @(posedge start) begin
        shift_reg <= data_in;
        count <= shift_amount;
        running <= 1;
        done <= 0;
        data_out <= 0;
    end

    always @(posedge clk) begin
        if (running) begin
            if (count > 0) begin
                case (mode)
                    2'b00: shift_reg <= shift_reg << 1;  // Logical Left Shift
                    2'b01: shift_reg <= shift_reg >> 1;  // Logical Right Shift
                    2'b10: shift_reg <= shift_reg >>> 1; // Arithmetic Right Shift
                    default: shift_reg <= shift_reg; // No operation
                endcase
                count <= count - 1;
            end else begin
                data_out <= shift_reg;
                done <= 1;
                running <= 0;
            end
        end
    end

endmodule

code/neuro_int/decay/decay.v
`timescale 1ns/100ps

module potential_decay(
    input wire clk,
    input wire rst,
    input wire load,
    input wire time_step,
    input wire [2:0] mode,
    input wire [31:0] new_potential,
    output reg [31:0] output_potential_decay
);
    
    reg [31:0] membrane_potential;
    wire [31:0] output_lif2;
    wire [31:0] output_lif4;
    wire [31:0] output_lif8;
    wire done_lif2;
    wire done_lif4;
    wire done_lif8;
    wire v_squared_done;
    wire izi1_done;
    wire izi2_done;
    wire [63:0] v_squared;
    wire [31:0] izi_first_term;
    wire [63:0] izi_second_term;
    reg start;
    reg decay_send;

    multiplier_32bit v_squared_mul(
        .clk(clk),
        .rst(time_step),
        .start(start),
        .A(membrane_potential),
        .B(membrane_potential),
        .result(v_squared),
        .done(v_squared_done)
    );

    shifter_32bit izi1(
        .clk(clk),
        .rst(time_step),
        .start(v_squared_done),
        .data_in(v_squared[31:0]),
        .shift_amount(5'b00011),
        .mode(2'b01),
        .data_out(izi_first_term),
        .done(izi1_done)
    );

    multiplier_32bit izi2(
        .clk(clk),
        .rst(time_step),
        .start(start),
        .A(membrane_potential),
        .B(32'h0005),
        .result(izi_second_term),
        .done(izi2_done)
    );

    shifter_32bit lif2(
        .clk(clk),
        .rst(time_step),
        .start(start),
        .data_in(membrane_potential),
        .shift_amount(5'b00001),
        .mode(2'b01),
        .data_out(output_lif2),
        .done(done_lif2)
    );

    shifter_32bit lif4(
        .clk(clk),
        .rst(time_step),
        .start(start),
        .data_in(membrane_potential),
        .shift_amount(5'b00010),
        .mode(2'b01),
        .data_out(output_lif4),
        .done(done_lif4)
    );

    shifter_32bit lif8(
        .clk(clk),
        .rst(time_step),
        .start(start),
        .data_in(membrane_potential),
        .shift_amount(5'b00011),
        .mode(2'b01),
        .data_out(output_lif8),
        .done(done_lif8)
    );

    always @(posedge load) begin
        membrane_potential <= new_potential;
        if(mode != `IDLE) begin
            #10 start <= 1;
            #10 start <= 0;
        end
    end

    always @(posedge time_step) begin
        decay_send <= 1;
    end

    always @(posedge clk) begin
        if (rst) begin
            membrane_potential <= 0;
            output_potential_decay <= 0;
            decay_send <= 0;
            start <= 0;
        end else if (mode == `LIF0) begin
            // Do nothing
        end else if (mode == `LIF2) begin
            if (done_lif2) begin
                membrane_potential <= output_lif2;
            end
        end else if (mode == `LIF4) begin
            if (done_lif4) begin
                membrane_potential <= output_lif4;
            end
        end else if (mode == `LIF8) begin
            if(done_lif8) begin
                membrane_potential <= output_lif8;
            end
        end else if (mode == `LIF24) begin
            if(done_lif2 & done_lif4) begin
                membrane_potential <= output_lif2 + output_lif4;
            end
        end else if(mode == `IZHI) begin
            if(izi1_done & izi2_done) begin
                membrane_potential <= izi_first_term - izi_second_term[31:0];
            end
        end else if(mode == `QUAD) begin
            if(v_squared_done) begin
                membrane_potential <= v_squared;
            end
        end else if(mode == `IDLE) begin
            // do nothing
        end

        if(decay_send) begin
            output_potential_decay <= membrane_potential;
            decay_send <= 0;
        end
    end

endmodule

code/rtl/neuro_int/accumulator/accumulator.v
`timescale 1ns/100ps

module Accumulator (
    input  clk,        // System clock
    input  rst,        // Reset signal
    input  time_step,  // Time step pulse (sync signal)
    input  load,       // Load signal for setting weights
    input  mode,       // Mode
    input  [9:0]  src_addr,  // 10-bit Source address
    input  [31:0] weight_in, // Input weight for loading
    output reg [31:0] accumulated_out // Output accumulated weight (32-bit)
);

    // Fixed-size registers for weight addresses and values
    reg [9:0]  weight_addr [0:15];  // 16 entries of 10-bit addresses
    reg [31:0] weight_value [0:15]; // 16 entries of 32-bit weights
    reg [31:0] accumulated_reg;     // 32-bit accumulation register
    reg [4:0]  write_ptr;           // 5-bit pointer for writing weights
    reg acc_send;                   // Accumulator send signal

    integer i; // Declare loop variable

    always @(posedge time_step) begin
        acc_send <= 1; // Send accumulated weight
    end

    // Reset and Weight Initialization
    always @(posedge clk) begin
        if(rst) begin
            for (i = 0; i < 16; i = i + 1) begin
                weight_addr[i]  <= 10'b0;
                weight_value[i] <= 32'b0;
            end
            accumulated_reg <= 32'b0;
            write_ptr       <= 5'b0;
            accumulated_out <= 32'b0;
            acc_send        <= 0;
        end
        if(!mode) begin
            for (i = 0; i < 16; i = i + 1) begin
                if (weight_addr[i] == src_addr) begin
                    accumulated_reg <= accumulated_reg + weight_value[i];
                end
            end
            if(acc_send) begin
                accumulated_out <= accumulated_reg; // Store accumulated weight
                accumulated_reg <= 32'b0;           // Reset accumulator for next time step
                acc_send <= 0;                       // Reset send signal
            end
        end
    end

    always @(posedge load) begin
        if (load) begin
            if (write_ptr < 16) begin
                weight_addr[write_ptr]  <= src_addr;
                weight_value[write_ptr] <= weight_in;
                write_ptr <= write_ptr + 1;
            end
        end
    end

endmodule

code/neuro_int/neuron/neuron.v
`timescale 1ns/100ps

module Neuron (
    input wire clk, rst, time_step, load,
    input wire [9:0] address,
    input wire [31:0] value,
    input wire [2:0] decay_mode,
    input wire [1:0] adder_model,
    input wire [2:0] init_mode_adder,
    input wire init_mode_acc,
    output wire spike
);

    wire [31:0] new_potential, final_potential;
    wire [31:0] output_potential_decay;
    wire [31:0] accumulated_out;
    wire [31:0] input_weight; 
    wire [31:0] decayed_potential;
    wire weight_load, adder_load, adder_done, decay_load;
    wire [9:0] src_addr;
    wire [31:0] weight_in;


    Accumulator acc (
        .clk(clk),
        .rst(rst),
        .time_step(time_step),
        .load(weight_load),
        .mode(init_mode_acc),
        .src_addr(src_addr),
        .weight_in(weight_in),
        .accumulated_out(accumulated_out)
    );

    potential_decay decay (
        .clk(clk),
        .rst(rst),
        .load(decay_load),
        .time_step(time_step),
        .mode(decay_mode),
        .new_potential(new_potential),
        .output_potential_decay(output_potential_decay)
    );

    potential_adder adder (
        .clk(clk),
        .rst(rst),
        .time_step(time_step),
        .load(adder_load),
        .input_weight(input_weight),
        .decayed_potential(decayed_potential),
        .model(adder_model),
        .init_mode(init_mode_adder),
        .final_potential(final_potential),
        .done(adder_done),
        .spike(spike)
    );

    assign weight_load = (init_mode_acc == 1'b1) ? load : 0;
    assign src_addr = address;
    assign weight_in = (init_mode_acc == 1'b1) ? value : 0;

    assign decay_load = (decay_mode == `IDLE) ? load : adder_done;
    assign new_potential = (decay_mode == `IDLE) ? value : final_potential;

    assign adder_load = (init_mode_adder == `DEFAULT) ? 0 : (init_mode_adder == `IDLE) ? 0 : load;
    assign input_weight = (init_mode_adder == `DEFAULT) ? accumulated_out : (init_mode_adder == `IDLE) ? 0 : value;
    assign decayed_potential = output_potential_decay;

endmodule

code/neuro_int/neuron/neuron_tb.v
`include "../utils/encording.v"
`include "../utils/32bit_mul.v"
`include "../utils/32bit_shifter.v"
`include "../decay/decay.v"
`include "../adder/adder.v"
`include "../accumulator/accumulator.v"
`include "neuron.v"
`timescale 1ns/100ps

module Neuron_tb ();

    reg clk, rst, time_step, load;
    reg [9:0] address;
    reg [31:0] value;
    reg [2:0] decay_mode;
    reg [1:0] adder_model;
    reg [2:0] init_mode_adder;
    reg init_mode_acc;
    output wire spike;
    
    Neuron neuron(
        .clk(clk),
        .rst(rst),
        .time_step(time_step),
        .load(load),
        .value(value),
        .address(address),
        .decay_mode(decay_mode),
        .adder_model(adder_model),
        .init_mode_adder(init_mode_adder),
        .init_mode_acc(init_mode_acc),
        .spike(spike)
    );

    always #5 clk = ~clk;

    initial begin
        $dumpfile("neuron_tb.vcd");
        $dumpvars(0, Neuron_tb);

        clk = 0;
        rst = 0;
        time_step = 0;
        load = 0;
        address = 0;
        value = 0;
        decay_mode = `LIF0;
        adder_model = 0;
        init_mode_adder = `IDLE;
        init_mode_acc = 0;

        // reset
        #10 rst = 1;
        #10 rst = 0;

        // init mode adder
        #10 init_mode_acc = 1;

        // load weight
        #10
        address = 1;
        value = 32'h0000d125;
        load = 1;
        #10 load = 0;

        // load weight
        #10
        address = 2;
        value = 32'h00000fff;
        load = 1;
        #10 load = 0;

        // load weight
        #10
        address = 3;
        value = 32'h0000f501;
        load = 1;
        #10 load = 0;

        // reset address and change mode to normal
        #10 
        address = 0;
        value = 0;
        init_mode_acc = 0;

        // decay mode init
        #10 decay_mode = `IDLE;

        // init potential
        #10 value = 32'h0000bcb5;
        load = 1;
        #10 load = 0;

        // decay mode reset
        #10 decay_mode = `LIF0;
        value = 0;

        // adder mode init
        #10 adder_model = 0;
        // init A
        #10;
        init_mode_adder = `A;
        value = 32'h00000021;
        load = 1;
        #10 load = 0;
        // init B
        #10;
        init_mode_adder = `B;
        value = 32'h00000011;
        load = 1;
        #10 load = 0;
        // init C
        #10;
        init_mode_adder = `C;
        value = 32'h00000001;
        load = 1;
        #10 load = 0;
        // init D
        #10;
        init_mode_adder = `D;
        value = 32'h00000001;
        load = 1;
        #10 load = 0;
        // init VT
        #10;
        init_mode_adder = `VT;
        value = 32'h0002ffff;
        load = 1;
        #10 load = 0;
        // init U
        #10;
        init_mode_adder = `U;
        value = 32'h00000002;
        load = 1;
        #10 load = 0;

        // reset mode adder
        #10 adder_model = 0;
        init_mode_adder = `IDLE;
        value = 0;

        // set modes for working
        #10 decay_mode = `LIF24;
        adder_model = `LIF;
        init_mode_adder = `DEFAULT;

        // give inputs
        #10 address = 1;
        #10 address = 2;
        #10 address = 3;
        #10 address = 0;
        
        // Time step
        #15 time_step = 1;
        #10 time_step = 0;
        
        #50;

        // give inputs
        #10 address = 1;
        #10 address = 3;
        #10 address = 0;
        
        // Time step
        #15 time_step = 1;
        #10 time_step = 0;

        #50;

        // give inputs
        #10 address = 1;
        #10 address = 2;
        #10 address = 0;
        
        // Time step
        #15 time_step = 1;
        #10 time_step = 0;

        #50;

        // give inputs
        #10 address = 2;
        #10 address = 3;
        #10 address = 0;
        
        // Time step
        #15 time_step = 1;
        #10 time_step = 0;

        #50;

        // give inputs
        #10 address = 1;
        #10 address = 2;
        #10 address = 3;
        #10 address = 0;
        
        // Time step
        #15 time_step = 1;
        #10 time_step = 0;

        #50;

        #100;
        $finish;
    end

endmodule

code/neuro_int/neuron/neuron_tb.vcd
$date
	Wed Feb 05 10:01:53 2025
$end
$version
	Icarus Verilog
$end
$timescale
	100ps
$end
$scope module Neuron_tb $end
$var wire 1 ! spike $end
$var reg 2 " adder_model [1:0] $end
$var reg 10 # address [9:0] $end
$var reg 1 $ clk $end
$var reg 3 % decay_mode [2:0] $end
$var reg 1 & init_mode_acc $end
$var reg 3 ' init_mode_adder [2:0] $end
$var reg 1 ( load $end
$var reg 1 ) rst $end
$var reg 1 * time_step $end
$var reg 32 + value [31:0] $end
$scope module neuron $end
$var wire 2 , adder_model [1:0] $end
$var wire 10 - address [9:0] $end
$var wire 1 $ clk $end
$var wire 3 . decay_mode [2:0] $end
$var wire 32 / decayed_potential [31:0] $end
$var wire 1 & init_mode_acc $end
$var wire 3 0 init_mode_adder [2:0] $end
$var wire 1 ( load $end
$var wire 1 ) rst $end
$var wire 10 1 src_addr [9:0] $end
$var wire 1 * time_step $end
$var wire 32 2 value [31:0] $end
$var wire 1 3 weight_load $end
$var wire 32 4 weight_in [31:0] $end
$var wire 1 ! spike $end
$var wire 32 5 output_potential_decay [31:0] $end
$var wire 32 6 new_potential [31:0] $end
$var wire 32 7 input_weight [31:0] $end
$var wire 32 8 final_potential [31:0] $end
$var wire 1 9 decay_load $end
$var wire 1 : adder_load $end
$var wire 1 ; adder_done $end
$var wire 32 < accumulated_out [31:0] $end
$scope module acc $end
$var wire 1 $ clk $end
$var wire 1 3 load $end
$var wire 1 & mode $end
$var wire 1 ) rst $end
$var wire 10 = src_addr [9:0] $end
$var wire 1 * time_step $end
$var wire 32 > weight_in [31:0] $end
$var reg 1 ? acc_send $end
$var reg 32 @ accumulated_out [31:0] $end
$var reg 32 A accumulated_reg [31:0] $end
$var reg 5 B write_ptr [4:0] $end
$var integer 32 C i [31:0] $end
$upscope $end
$scope module adder $end
$var wire 1 $ clk $end
$var wire 32 D decayed_potential [31:0] $end
$var wire 3 E init_mode [2:0] $end
$var wire 32 F input_weight [31:0] $end
$var wire 1 : load $end
$var wire 2 G model [1:0] $end
$var wire 1 ) rst $end
$var wire 1 * time_step $end
$var wire 32 H bv_u [31:0] $end
$var wire 1 I bv_done $end
$var wire 64 J bv [63:0] $end
$var wire 1 K abv_done $end
$var wire 64 L a_bv_u [63:0] $end
$var reg 32 M a [31:0] $end
$var reg 1 N abv_start $end
$var reg 1 O adder_send $end
$var reg 1 P adder_start $end
$var reg 32 Q b [31:0] $end
$var reg 1 R bv_start $end
$var reg 32 S c [31:0] $end
$var reg 1 T clear_mul $end
$var reg 32 U d [31:0] $end
$var reg 1 ; done $end
$var reg 32 V final_potential [31:0] $end
$var reg 1 ! spike $end
$var reg 32 W u [31:0] $end
$var reg 32 X v_threshold [31:0] $end
$var reg 32 Y weight_added [31:0] $end
$scope module multIzhiBV $end
$var wire 32 Z A [31:0] $end
$var wire 32 [ B [31:0] $end
$var wire 1 $ clk $end
$var wire 1 T rst $end
$var wire 1 R start $end
$var reg 6 \ count [5:0] $end
$var reg 1 I done $end
$var reg 32 ] multiplicand [31:0] $end
$var reg 32 ^ multiplier [31:0] $end
$var reg 64 _ product [63:0] $end
$var reg 64 ` result [63:0] $end
$var reg 1 a running $end
$upscope $end
$scope module multIzhiaBVu $end
$var wire 32 b A [31:0] $end
$var wire 32 c B [31:0] $end
$var wire 1 $ clk $end
$var wire 1 T rst $end
$var wire 1 N start $end
$var reg 6 d count [5:0] $end
$var reg 1 K done $end
$var reg 32 e multiplicand [31:0] $end
$var reg 32 f multiplier [31:0] $end
$var reg 64 g product [63:0] $end
$var reg 64 h result [63:0] $end
$var reg 1 i running $end
$upscope $end
$upscope $end
$scope module decay $end
$var wire 1 $ clk $end
$var wire 1 9 load $end
$var wire 3 j mode [2:0] $end
$var wire 32 k new_potential [31:0] $end
$var wire 1 ) rst $end
$var wire 1 * time_step $end
$var wire 1 l v_squared_done $end
$var wire 64 m v_squared [63:0] $end
$var wire 32 n output_lif8 [31:0] $end
$var wire 32 o output_lif4 [31:0] $end
$var wire 32 p output_lif2 [31:0] $end
$var wire 64 q izi_second_term [63:0] $end
$var wire 32 r izi_first_term [31:0] $end
$var wire 1 s izi2_done $end
$var wire 1 t izi1_done $end
$var wire 1 u done_lif8 $end
$var wire 1 v done_lif4 $end
$var wire 1 w done_lif2 $end
$var reg 1 x decay_send $end
$var reg 32 y membrane_potential [31:0] $end
$var reg 32 z output_potential_decay [31:0] $end
$var reg 1 { start $end
$scope module izi1 $end
$var wire 1 $ clk $end
$var wire 32 | data_in [31:0] $end
$var wire 2 } mode [1:0] $end
$var wire 1 * rst $end
$var wire 5 ~ shift_amount [4:0] $end
$var wire 1 l start $end
$var reg 5 !" count [4:0] $end
$var reg 32 "" data_out [31:0] $end
$var reg 1 t done $end
$var reg 1 #" running $end
$var reg 32 $" shift_reg [31:0] $end
$upscope $end
$scope module izi2 $end
$var wire 32 %" A [31:0] $end
$var wire 32 &" B [31:0] $end
$var wire 1 $ clk $end
$var wire 1 * rst $end
$var wire 1 { start $end
$var reg 6 '" count [5:0] $end
$var reg 1 s done $end
$var reg 32 (" multiplicand [31:0] $end
$var reg 32 )" multiplier [31:0] $end
$var reg 64 *" product [63:0] $end
$var reg 64 +" result [63:0] $end
$var reg 1 ," running $end
$upscope $end
$scope module lif2 $end
$var wire 1 $ clk $end
$var wire 32 -" data_in [31:0] $end
$var wire 2 ." mode [1:0] $end
$var wire 1 * rst $end
$var wire 5 /" shift_amount [4:0] $end
$var wire 1 { start $end
$var reg 5 0" count [4:0] $end
$var reg 32 1" data_out [31:0] $end
$var reg 1 w done $end
$var reg 1 2" running $end
$var reg 32 3" shift_reg [31:0] $end
$upscope $end
$scope module lif4 $end
$var wire 1 $ clk $end
$var wire 32 4" data_in [31:0] $end
$var wire 2 5" mode [1:0] $end
$var wire 1 * rst $end
$var wire 5 6" shift_amount [4:0] $end
$var wire 1 { start $end
$var reg 5 7" count [4:0] $end
$var reg 32 8" data_out [31:0] $end
$var reg 1 v done $end
$var reg 1 9" running $end
$var reg 32 :" shift_reg [31:0] $end
$upscope $end
$scope module lif8 $end
$var wire 1 $ clk $end
$var wire 32 ;" data_in [31:0] $end
$var wire 2 <" mode [1:0] $end
$var wire 1 * rst $end
$var wire 5 =" shift_amount [4:0] $end
$var wire 1 { start $end
$var reg 5 >" count [4:0] $end
$var reg 32 ?" data_out [31:0] $end
$var reg 1 u done $end
$var reg 1 @" running $end
$var reg 32 A" shift_reg [31:0] $end
$upscope $end
$scope module v_squared_mul $end
$var wire 32 B" A [31:0] $end
$var wire 32 C" B [31:0] $end
$var wire 1 $ clk $end
$var wire 1 * rst $end
$var wire 1 { start $end
$var reg 6 D" count [5:0] $end
$var reg 1 l done $end
$var reg 32 E" multiplicand [31:0] $end
$var reg 32 F" multiplier [31:0] $end
$var reg 64 G" product [63:0] $end
$var reg 64 H" result [63:0] $end
$var reg 1 I" running $end
$upscope $end
$upscope $end
$upscope $end
$upscope $end
$enddefinitions $end
$comment Show the parameter values. $end
$dumpall
$end
#0
$dumpvars
xI"
bx H"
bx G"
bx F"
bx E"
bx D"
bx C"
bx B"
bx A"
x@"
bx ?"
bx >"
b11 ="
b1 <"
bx ;"
bx :"
x9"
bx 8"
bx 7"
b10 6"
b1 5"
bx 4"
bx 3"
x2"
bx 1"
bx 0"
b1 /"
b1 ."
bx -"
x,"
bx +"
bx *"
bx )"
bx ("
bx '"
b101 &"
bx %"
bx $"
x#"
bx ""
bx !"
b11 ~
b1 }
bx |
x{
bx z
bx y
xx
xw
xv
xu
xt
xs
bx r
bx q
bx p
bx o
bx n
bx m
xl
bx k
b0 j
xi
bx h
bx g
bx f
bx e
bx d
bx c
bx b
xa
bx `
bx _
bx ^
bx ]
bx \
bx [
bx Z
bx Y
bx X
bx W
bx V
bx U
xT
bx S
xR
bx Q
xP
xO
xN
bx M
bx L
xK
bx J
xI
bx H
b0 G
b0 F
b111 E
bx D
bx C
bx B
bx A
bx @
x?
b0 >
b0 =
bx <
x;
0:
x9
bx 8
b0 7
bx 6
bx 5
b0 4
03
b0 2
b0 1
b111 0
bx /
b0 .
b0 -
b0 ,
b0 +
0*
0)
0(
b111 '
0&
b0 %
0$
b0 #
b0 "
x!
$end
#50
b10000 C
1$
#100
0$
1)
#150
09
b0 6
b0 k
b0 Y
b0 W
b0 X
b0 U
b0 S
b0 Q
b0 Z
b0 M
b0 b
0!
0;
b0 8
b0 V
0{
0x
b0 /
b0 D
b0 [
b0 5
b0 z
b0 y
b0 %"
b0 -"
b0 4"
b0 ;"
b0 B"
b0 C"
0?
b0 <
b0 @
b0 B
b0 A
b10000 C
1$
#200
0$
0)
#250
b10000 C
1$
#300
0$
1&
#350
1$
#400
b1 B
13
b1101000100100101 4
b1101000100100101 >
0$
1(
b1101000100100101 +
b1101000100100101 2
b1 1
b1 =
b1 #
b1 -
#450
1$
#500
03
0$
0(
#550
1$
#600
b10 B
13
b111111111111 4
b111111111111 >
0$
1(
b111111111111 +
b111111111111 2
b10 1
b10 =
b10 #
b10 -
#650
1$
#700
03
0$
0(
#750
1$
#800
b11 B
13
b1111010100000001 4
b1111010100000001 >
0$
1(
b1111010100000001 +
b1111010100000001 2
b11 1
b11 =
b11 #
b11 -
#850
1$
#900
03
0$
0(
#950
1$
#1000
b0 4
b0 >
0$
0&
b0 +
b0 2
b0 1
b0 =
b0 #
b0 -
#1050
b10000 C
1$
#1100
0$
b111 %
b111 .
b111 j
#1150
b10000 C
1$
#1200
b1011110010110101 y
b1011110010110101 %"
b1011110010110101 -"
b1011110010110101 4"
b1011110010110101 ;"
b1011110010110101 B"
b1011110010110101 C"
19
b1011110010110101 6
b1011110010110101 k
0$
1(
b1011110010110101 +
b1011110010110101 2
#1250
b10000 C
1$
#1300
09
0$
0(
#1350
b10000 C
1$
#1400
b0 6
b0 k
0$
b0 +
b0 2
b0 %
b0 .
b0 j
#1450
b10000 C
1$
#1500
0$
#1550
b10000 C
1$
#1600
b100001 M
b100001 b
1:
b100001 7
b100001 F
0$
1(
b100001 +
b100001 2
b1 '
b1 0
b1 E
#1650
b10000 C
1$
#1700
0:
0$
0(
#1750
b10000 C
1$
#1800
b10001 Q
b10001 Z
1:
b10001 7
b10001 F
0$
1(
b10001 +
b10001 2
b10 '
b10 0
b10 E
#1850
b10000 C
1$
#1900
0:
0$
0(
#1950
b10000 C
1$
#2000
b1 S
1:
b1 7
b1 F
0$
1(
b1 +
b1 2
b11 '
b11 0
b11 E
#2050
b10000 C
1$
#2100
0:
0$
0(
#2150
b10000 C
1$
#2200
b1 U
1:
0$
1(
b100 '
b100 0
b100 E
#2250
b10000 C
1$
#2300
0:
0$
0(
#2350
b10000 C
1$
#2400
b101111111111111111 X
1:
b101111111111111111 7
b101111111111111111 F
0$
1(
b101111111111111111 +
b101111111111111111 2
b101 '
b101 0
b101 E
#2450
b10000 C
1$
#2500
0:
0$
0(
#2550
b10000 C
1$
#2600
b10 W
1:
b10 7
b10 F
0$
1(
b10 +
b10 2
b110 '
b110 0
b110 E
#2650
b10000 C
1$
#2700
0:
0$
0(
#2750
b10000 C
1$
#2800
b0 7
b0 F
0$
b0 +
b0 2
b111 '
b111 0
b111 E
#2850
b10000 C
1$
#2900
0$
b0 '
b0 0
b0 E
b100 %
b100 .
b100 j
#2950
b10000 C
1$
#3000
0$
b1 1
b1 =
b1 #
b1 -
#3050
b1101000100100101 A
b10000 C
1$
#3100
0$
b10 1
b10 =
b10 #
b10 -
#3150
b1110000100100100 A
b10000 C
1$
#3200
0$
b11 1
b11 =
b11 #
b11 -
#3250
b11101011000100101 A
b10000 C
1$
#3300
0$
b0 1
b0 =
b0 #
b0 -
#3350
b10000 C
1$
#3400
0$
#3450
0I
0a
b0 \
b0 _
b0 ^
b0 ]
0K
0i
b0 d
b0 g
b0 f
b0 e
1?
0l
0I"
b0 D"
b0 G"
b0 F"
b0 E"
b0 r
b0 ""
0t
0#"
b0 !"
b0 $"
0s
0,"
b0 '"
b0 *"
b0 )"
b0 ("
b0 p
b0 1"
0w
02"
b0 0"
b0 3"
b0 o
b0 8"
0v
09"
b0 7"
b0 :"
b0 n
b0 ?"
0u
0@"
b0 >"
b0 A"
1x
1T
b10000 C
1$
1*
#3500
0$
#3550
b11101011000100101 7
b11101011000100101 F
0x
b1011110010110101 /
b1011110010110101 D
b1011110010110101 [
b1011110010110101 5
b1011110010110101 z
0?
b0 A
b11101011000100101 <
b11101011000100101 @
0T
1P
b10000 C
1$
0*
#3600
0$
#3650
1O
0P
b101001001011011010 Y
b10000 C
1$
#3700
0$
#3750
b101001001011011010 y
b101001001011011010 %"
b101001001011011010 -"
b101001001011011010 4"
b101001001011011010 ;"
b101001001011011010 B"
b101001001011011010 C"
19
b101001001011011010 6
b101001001011011010 k
b0 Y
0O
1;
b101001001011011010 8
b101001001011011010 V
b10000 C
1$
#3800
0$
#3850
1I"
b101001001011011010 F"
b101001001011011010 E"
1,"
b101 )"
b101001001011011010 ("
12"
b1 0"
b101001001011011010 3"
19"
b10 7"
b101001001011011010 :"
1@"
b11 >"
b101001001011011010 A"
1{
b10000 C
1$
#3900
0$
#3950
b10 >"
b10100100101101101 A"
b1 7"
b10100100101101101 :"
b0 0"
b10100100101101101 3"
0{
b1 '"
b10 )"
b101001001011011010 *"
b1 D"
b10100100101101101 F"
b10000 C
1$
#4000
0$
#4050
02"
1w
b10100100101101101 p
b10100100101101101 1"
b0 7"
b1010010010110110 :"
b1 >"
b1010010010110110 A"
b10000 C
b10 D"
b1010010010110110 F"
b1010010010110110100 G"
b10 '"
b1 )"
1$
#4100
0$
#4150
b0 >"
b101001001011011 A"
09"
1v
b1010010010110110 o
b1010010010110110 8"
b1101000100100101 A
b11 '"
b0 )"
b11001101111001000010 *"
b11 D"
b101001001011011 F"
b10000 C
1$
b1 1
b1 =
b1 #
b1 -
#4200
0$
#4250
b11100011000100110 A
0@"
1u
b101001001011011 n
b101001001011011 ?"
b11110111000100011 y
b11110111000100011 %"
b11110111000100011 -"
b11110111000100011 4"
b11110111000100011 ;"
b11110111000100011 B"
b11110111000100011 C"
b10000 C
b100 D"
b10100100101101 F"
b110011011110010000100 G"
b100 '"
1$
b11 1
b11 =
b11 #
b11 -
#4300
0$
#4350
b101 '"
b101 D"
b1010010010110 F"
b10000101110101000100100 G"
b10000 C
1$
b0 1
b0 =
b0 #
b0 -
#4400
0$
