utils/32bit_mul.v
module multiplier_32bit(
    input wire clk,
    input wire rst,
    input wire start,
    input wire [31:0] A,
    input wire [31:0] B,
    output reg [63:0] result,
    output reg done
);
    
    reg [31:0] multiplicand, multiplier;
    reg [63:0] product;
    reg [5:0] count;
    reg running;

    always @(posedge rst) begin
        multiplicand <= 0;
        multiplier <= 0;
        product <= 0;
        count <= 0;
        running <= 0;
        done <= 0;
    end

    always @(posedge start) begin
        multiplicand <= A;
        multiplier <= B;
        product <= 0;
        count <= 0;
        running <= 1;
        done <= 0;
    end

    always @(posedge clk) begin
        if (running) begin
            if (count < 32) begin
                if (multiplier[0] == 1'b1) begin
                    product = product + ({32'b0, multiplicand} << count);
                end
                multiplier = multiplier >> 1;
                count = count + 1;
            end else begin
                result <= product;
                done <= 1;
                running <= 0;
            end
        end
    end

endmodule

code/neuro_int/adder/adder.v
`timescale 1ns/100ps

module potential_adder (
    input wire clk,
    input wire rst,        
    input wire time_step,      
    input wire [31:0] input_weight, 
    input wire [31:0] decayed_potential,
    input wire [1:0] model,
    input wire [2:0] init_mode,
    input wire load,
    
    output reg [31:0] final_potential, 
    output reg done,
    output reg spike
);

    // Common Signals
    reg [31:0] weight_added;
    reg [31:0] u;
    reg adder_start, adder_send;

    // Internal Signals for Izhikevich Model
    wire [63:0] bv, a_bv_u;
    wire [31:0] bv_u;
    reg [31:0] a, b, c, d, v_threshold;
    
    reg bv_start, abv_start, clear_mul;
    wire bv_done, abv_done;

    multiplier_32bit multIzhiBV (
        .clk(clk),
        .rst(clear_mul),
        .start(bv_start),
        .A(b),
        .B(decayed_potential),
        .result(bv),
        .done(bv_done)
    );

    multiplier_32bit multIzhiaBVu (
        .clk(clk),
        .rst(clear_mul),
        .start(abv_start),
        .A(a),
        .B(bv_u),
        .result(a_bv_u),
        .done(abv_done)
    );

    assign bv_u = bv[31:0] - u;

    always @(posedge bv_done) begin
        bv_start <= 0;
        #10 abv_start <= 1;
    end

    always @(posedge load) begin
        if (init_mode == `A) begin
            a <= input_weight;
        end else if (init_mode == `B) begin
            b <= input_weight;
        end else if (init_mode == `C) begin
            c <= input_weight;
        end else if (init_mode == `D) begin
            d <= input_weight;
        end else if (init_mode == `VT) begin
            v_threshold <= input_weight;
        end else if (init_mode == `U) begin
            u <= input_weight;
        end
    end

    always @(posedge time_step) begin
        done <= 0;
        spike <= 0;
        clear_mul <= 1;
        #10 adder_start <= 1;
        clear_mul <= 0;
    end

    always @(posedge clk) begin
        if (rst) begin
            final_potential <= 0;
            done <= 0;
            spike <= 0;
            a <= 0;
            b <= 0;
            c <= 0;
            d <= 0;
            v_threshold <= 0;
            u <= 0;
            weight_added <= 0;
        end else if (init_mode == `DEFAULT) begin
            if (adder_start) begin
                if (model == `LIF) begin
                    weight_added <= input_weight + decayed_potential;
                end else if (model == `IZHI_AD) begin
                    weight_added <= input_weight + decayed_potential - u;
                    bv_start <= 1;
                    abv_start <= 0;
                end else if (model == `QLIF) begin
                    weight_added <= input_weight + decayed_potential;
                end
                adder_start <= 0;
                adder_send <= 1;
            end
            if(adder_send) begin
                if(model == `LIF) begin
                    spike <= (weight_added > v_threshold);
                    final_potential <= (weight_added > v_threshold) ? (weight_added - v_threshold) : weight_added;
                    done <= 1;
                    adder_send <= 0;
                end else if (model == `IZHI) begin
                    if(abv_done) begin
                        clear_mul <= 1;
                        spike <= (weight_added > v_threshold);
                        final_potential <= (weight_added > v_threshold) ? c : weight_added;
                        u <= (weight_added > v_threshold) ? u + d : a_bv_u[31:0];
                        done <= 1;
                        #10 clear_mul <= 0;
                        adder_send <= 0;
                    end
                end else if (model == `QLIF) begin
                    spike <= (weight_added > v_threshold);
                    final_potential <= (weight_added > v_threshold) ? (weight_added - v_threshold) : weight_added;
                    done <= 1;
                    adder_send <= 0;
                end
            end
        end
    end

endmodule

adder/adder_tb.v
`timescale 1ns/100ps
`include "adder.v"

module potential_adder_tb();
    reg clk;
    reg rst;
    reg time_step;
    reg load;
    reg [31:0] input_weight;
    reg [31:0] decayed_potential;
    reg [1:0] model;
    reg [2:0] init_mode;
    
    wire [31:0] final_potential;
    wire done;
    wire spike;
    
    potential_adder uut (
        .clk(clk),
        .rst(rst),
        .time_step(time_step),
        .input_weight(input_weight),
        .decayed_potential(decayed_potential),
        .model(model),
        .init_mode(init_mode),
        .load(load),
        .final_potential(final_potential),
        .done(done),
        .spike(spike)
    );
    
    // Clock Generation
    always #5 clk = ~clk;
    
    initial begin
        $dumpfile("adder_tb.vcd");
        $dumpvars(0, potential_adder_tb);

        clk = 0;
        rst = 1;
        time_step = 0;
        load = 0;
        input_weight = 32'd0;
        decayed_potential = 32'd0;
        model = 2'b00;
        init_mode = 3'b000;
        
        #20 rst = 0;
        
        // Initialize Parameters
        #10 load = 1; input_weight = 32'd10; init_mode = 3'b001; #10 load = 0; // Set A
        #10 load = 1; input_weight = 32'd20; init_mode = 3'b010; #10 load = 0; // Set B
        #10 load = 1; input_weight = 32'd30; init_mode = 3'b011; #10 load = 0; // Set C
        #10 load = 1; input_weight = 32'd40; init_mode = 3'b100; #10 load = 0; // Set D
        #10 load = 1; input_weight = 32'd50; init_mode = 3'b101; #10 load = 0; // Set VT
        #10 load = 1; input_weight = 32'd5; init_mode = 3'b110; // Set U
        #10 load = 0; init_mode = 3'b000; // Set Default
        
        // Test LIF Model
        #10 model = 2'b00; input_weight = 32'd25; decayed_potential = 32'd25; time_step = 1;
        #10 time_step = 0;
        #100;
        
        // Test Izhikevich Model
        #20 model = 2'b01; input_weight = 32'd25; decayed_potential = 32'd35; time_step = 1;
        #10 time_step = 0;
        #1000;
        
        // Test QLIF Model
        #20 model = 2'b10; input_weight = 32'd30; decayed_potential = 32'd10; time_step = 1;
        #10 time_step = 0;
        #100;
        
        #50 $finish;
    end
    
    initial begin
        $monitor("Time = %0t | Model = %b | Input = %d | Decayed = %d | Final Potential = %d | Spike = %b | Done = %b",
                  $time, model, input_weight, decayed_potential, final_potential, spike, done);
    end
    
endmodule

code/neuro_int/adder/adder_tb.vcd
$date
	Mon Feb 03 16:44:34 2025
$end
$version
	Icarus Verilog
$end
$timescale
	100ps
$end
$scope module potential_adder_tb $end
$var wire 1 ! spike $end
$var wire 32 " final_potential [31:0] $end
$var wire 1 # done $end
$var reg 1 $ clk $end
$var reg 32 % decayed_potential [31:0] $end
$var reg 3 & init_mode [2:0] $end
$var reg 32 ' input_weight [31:0] $end
$var reg 1 ( load $end
$var reg 2 ) model [1:0] $end
$var reg 1 * rst $end
$var reg 1 + time_step $end
$scope module uut $end
$var wire 1 $ clk $end
$var wire 32 , decayed_potential [31:0] $end
$var wire 3 - init_mode [2:0] $end
$var wire 32 . input_weight [31:0] $end
$var wire 1 ( load $end
$var wire 2 / model [1:0] $end
$var wire 1 * rst $end
$var wire 1 + time_step $end
$var wire 32 0 bv_u [31:0] $end
$var wire 1 1 bv_done $end
$var wire 64 2 bv [63:0] $end
$var wire 1 3 abv_done $end
$var wire 64 4 a_bv_u [63:0] $end
$var reg 32 5 a [31:0] $end
$var reg 1 6 abv_start $end
$var reg 1 7 adder_send $end
$var reg 1 8 adder_start $end
$var reg 32 9 b [31:0] $end
$var reg 1 : bv_start $end
$var reg 32 ; c [31:0] $end
$var reg 1 < clear_mul $end
$var reg 32 = d [31:0] $end
$var reg 1 # done $end
$var reg 32 > final_potential [31:0] $end
$var reg 1 ! spike $end
$var reg 32 ? u [31:0] $end
$var reg 32 @ v_threshold [31:0] $end
$var reg 32 A weight_added [31:0] $end
$scope module multIzhiBV $end
$var wire 32 B A [31:0] $end
$var wire 32 C B [31:0] $end
$var wire 1 $ clk $end
$var wire 1 < rst $end
$var wire 1 : start $end
$var reg 6 D count [5:0] $end
$var reg 1 1 done $end
$var reg 32 E multiplicand [31:0] $end
$var reg 32 F multiplier [31:0] $end
$var reg 64 G product [63:0] $end
$var reg 64 H result [63:0] $end
$var reg 1 I running $end
$upscope $end
$scope module multIzhiaBVu $end
$var wire 32 J A [31:0] $end
$var wire 32 K B [31:0] $end
$var wire 1 $ clk $end
$var wire 1 < rst $end
$var wire 1 6 start $end
$var reg 6 L count [5:0] $end
$var reg 1 3 done $end
$var reg 32 M multiplicand [31:0] $end
$var reg 32 N multiplier [31:0] $end
$var reg 64 O product [63:0] $end
$var reg 64 P result [63:0] $end
$var reg 1 Q running $end
$upscope $end
$upscope $end
$upscope $end
$enddefinitions $end
$comment Show the parameter values. $end
$dumpall
$end
#0
$dumpvars
xQ
bx P
bx O
bx N
bx M
bx L
bx K
bx J
xI
bx H
bx G
bx F
bx E
bx D
b0 C
bx B
bx A
bx @
bx ?
bx >
bx =
x<
bx ;
x:
bx 9
x8
x7
x6
bx 5
bx 4
x3
bx 2
x1
bx 0
b0 /
b0 .
b0 -
b0 ,
0+
1*
b0 )
0(
b0 '
b0 &
b0 %
0$
x#
bx "
x!
$end
#50
b0 A
b0 ?
b0 @
b0 =
b0 ;
b0 9
b0 B
b0 5
b0 J
0!
0#
b0 "
b0 >
1$
#100
0$
#150
1$
#200
0$
0*
#250
1$
#300
b1010 5
b1010 J
0$
b1 &
b1 -
b1010 '
b1010 .
1(
#350
1$
#400
0$
0(
#450
1$
#500
b10100 9
b10100 B
0$
b10 &
b10 -
b10100 '
b10100 .
1(
#550
1$
#600
0$
0(
#650
1$
#700
b11110 ;
0$
b11 &
b11 -
b11110 '
b11110 .
1(
#750
1$
#800
0$
0(
#850
1$
#900
b101000 =
0$
b100 &
b100 -
b101000 '
b101000 .
1(
#950
1$
#1000
0$
0(
#1050
1$
#1100
b110010 @
0$
b101 &
b101 -
b110010 '
b110010 .
1(
#1150
1$
#1200
0$
0(
#1250
1$
#1300
b101 ?
0$
b110 &
b110 -
b101 '
b101 .
1(
#1350
1$
#1400
0$
b0 &
b0 -
0(
#1450
1$
#1500
01
0I
b0 D
b0 G
b0 F
b0 E
03
0Q
b0 L
b0 O
b0 N
b0 M
18
1<
0$
1+
b11001 %
b11001 ,
b11001 C
b11001 '
b11001 .
#1550
17
08
b110010 A
1$
#1600
0<
0$
0+
#1650
07
1#
b110010 "
b110010 >
1$
#1700
0$
#1750
1$
#1800
0$
#1850
1$
#1900
0$
#1950
1$
#2000
0$
#2050
1$
#2100
0$
#2150
1$
#2200
0$
#2250
1$
#2300
0$
#2350
1$
#2400
0$
#2450
1$
#2500
0$
#2550
1$
#2600
0$
#2650
1$
#2700
0$
#2750
1$
#2800
18
1<
0#
0$
1+
b100011 %
b100011 ,
b100011 C
b1 )
b1 /
#2850
1I
b100011 F
b10100 E
17
08
06
1:
b110111 A
1$
#2900
0<
0$
0+
#2950
07
b1 D
b10001 F
b10100 G
1$
#3000
0$
#3050
b10 D
b1000 F
b111100 G
1$
#3100
0$
#3150
b11 D
b100 F
1$
#3200
0$
#3250
b100 D
b10 F
1$
#3300
0$
#3350
b101 D
b1 F
1$
#3400
0$
#3450
b110 D
b0 F
b1010111100 G
1$
#3500
0$
#3550
b111 D
1$
#3600
0$
#3650
b1000 D
1$
#3700
0$
#3750
b1001 D
1$
#3800
0$
#3850
b1010 D
1$
#3900
0$
#3950
b1011 D
1$
#4000
0$
#4050
b1100 D
1$
#4100
0$
#4150
b1101 D
1$
#4200
0$
#4250
b1110 D
1$
#4300
0$
#4350
b1111 D
1$
#4400
0$
#4450
b10000 D
1$
#4500
0$
#4550
b10001 D
1$
#4600
0$
#4650
b10010 D
1$
#4700
0$
#4750
b10011 D
1$
#4800
0$
#4850
b10100 D
1$
#4900
0$
#4950
b10101 D
1$
#5000
0$
#5050
b10110 D
1$
#5100
0$
#5150
b10111 D
1$
#5200
0$
#5250
b11000 D
1$
#5300
0$
#5350
b11001 D
1$
#5400
0$
#5450
b11010 D
1$
#5500
0$
#5550
b11011 D
1$
#5600
0$
#5650
b11100 D
1$
#5700
0$
#5750
b11101 D
1$
#5800
0$
#5850
b11110 D
1$
#5900
0$
#5950
b11111 D
1$
#6000
0$
#6050
b100000 D
1$
#6100
0$
#6150
0:
b1010110111 0
b1010110111 K
0I
11
b1010111100 2
b1010111100 H
1$
#6200
0$
#6250
1Q
b1010110111 N
b1010 M
16
1$
#6300
0$
#6350
b1 L
b101011011 N
b1010 O
1$
#6400
0$
#6450
b10 L
b10101101 N
b11110 O
1$
#6500
0$
#6550
b11 L
b1010110 N
b1000110 O
1$
#6600
0$
#6650
b100 L
b101011 N
1$
#6700
0$
#6750
b101 L
b10101 N
b11100110 O
1$
#6800
0$
#6850
b110 L
b1010 N
b1000100110 O
1$
#6900
0$
#6950
b111 L
b101 N
1$
#7000
0$
#7050
b1000 L
b10 N
b11100100110 O
1$
#7100
0$
#7150
b1001 L
b1 N
1$
#7200
0$
#7250
b1010 L
b0 N
b1101100100110 O
1$
#7300
0$
#7350
b1011 L
1$
#7400
0$
#7450
b1100 L
1$
#7500
0$
#7550
b1101 L
1$
#7600
0$
#7650
b1110 L
1$
#7700
0$
#7750
b1111 L
1$
#7800
0$
#7850
b10000 L
1$
#7900
0$
#7950
b10001 L
1$
#8000
0$
#8050
b10010 L
1$
#8100
0$
#8150
b10011 L
1$
#8200
0$
#8250
b10100 L
1$
#8300
0$
#8350
b10101 L
1$
#8400
0$
#8450
b10110 L
1$
#8500
0$
#8550
b10111 L
1$
#8600
0$
#8650
b11000 L
1$
#8700
0$
#8750
b11001 L
1$
#8800
0$
#8850
b11010 L
1$
#8900
0$
#8950
b11011 L
1$
#9000
0$
#9050
b11100 L
1$
#9100
0$
#9150
b11101 L
1$
#9200
0$
#9250
b11110 L
1$
#9300
0$
#9350
b11111 L
1$
#9400
0$
#9450
b100000 L
1$
#9500
0$
#9550
0Q
13
b1101100100110 4
b1101100100110 P
1$
