utils/encording.v
// Decay modes
`define LIF0 3'b000
`define LIF2 3'b001
`define LIF4 3'b010
`define LIF8 3'b011
`define LIF24 3'b100
`define IZHI 3'b101
`define QUAD 3'b110
`define IDLE 3'b111

// Decay Status

utils/32bit_shifter.v
module shifter_32bit (
    input wire clk,
    input wire start,
    input wire [31:0] data_in,
    input wire [4:0] shift_amount,  // Supports shifting up to 31 bits
    input wire [1:0] mode,          // 00: Logical Left, 01: Logical Right, 10: Arithmetic Right
    output reg [31:0] data_out,
    output reg done
);

    reg [31:0] shift_reg;
    reg [4:0] count;
    reg running;

    always @(posedge start) begin
        shift_reg <= data_in;
        count <= shift_amount;
        running <= 1;
        done <= 0;
    end

    always @(posedge clk) begin
        if (running) begin
            if (count > 0) begin
                case (mode)
                    2'b00: shift_reg <= shift_reg << 1;  // Logical Left Shift
                    2'b01: shift_reg <= shift_reg >> 1;  // Logical Right Shift
                    2'b10: shift_reg <= shift_reg >>> 1; // Arithmetic Right Shift
                    default: shift_reg <= shift_reg; // No operation
                endcase
                count <= count - 1;
            end else begin
                data_out <= shift_reg;
                done <= 1;
                running <= 0;
            end
        end
    end

endmodule

utils/32bit_mul.v
module multiplier_32bit(
    input wire clk,
    input wire start,
    input wire [31:0] A,
    input wire [31:0] B,
    output reg [63:0] result,
    output reg done
);
    
    reg [31:0] multiplicand, multiplier;
    reg [63:0] product;
    reg [5:0] count;
    reg running;

    always @(posedge start) begin
        multiplicand <= A;
        multiplier <= B;
        product <= 0;
        count <= 0;
        running <= 1;
        done <= 0;
    end

    always @(posedge clk) begin
        if (running) begin
            if (count < 32) begin
                if (multiplier[0] == 1'b1) begin
                    product = product + ({32'b0, multiplicand} << count);
                end
                multiplier = multiplier >> 1;
                count = count + 1;
            end else begin
                result <= product;
                done <= 1;
                running <= 0;
            end
        end
    end

endmodule

decay/decay.v
`include "../utils/32bit_mul.v"
`include "../utils/32bit_shifter.v"
`include "../utils/encording.v"

module potential_decay(
    input wire clk,
    input wire rst,
    input wire load,
    input wire time_step,
    input wire [2:0] mode,
    input wire [31:0] new_potential,
    output reg [31:0] output_potential_decay
);
    
    reg [31:0] membrane_potential;
    wire [31:0] output_lif2;
    wire [31:0] output_lif4;
    wire [31:0] output_lif8;
    wire done_lif2;
    wire done_lif4;
    wire done_lif8;
    wire [63:0] v_squared;
    wire [31:0] izi_first_term;
    wire [63:0] izi_second_term;
    wire v_squared_done;
    wire izi1_done;
    wire izi2_done;

    multiplier_32bit v_squared_mul(
        .clk(clk),
        .start(time_step),
        .A(membrane_potential),
        .B(membrane_potential),
        .result(v_squared),
        .done(v_squared_done)
    );

    shifter_32bit izi1(
        .clk(clk),
        .start(v_squared_done),
        .data_in(v_squared[31:0]),
        .shift_amount(5'b00011),
        .mode(2'b01),
        .data_out(izi_first_term),
        .done(izi1_done)
    );

    multiplier_32bit izi2(
        .clk(clk),
        .start(time_step),
        .A(membrane_potential),
        .B(32'h0005),
        .result(izi_second_term),
        .done(izi2_done)
    );

    shifter_32bit lif2(
        .clk(clk),
        .start(time_step),
        .data_in(membrane_potential),
        .shift_amount(5'b00001),
        .mode(2'b01),
        .data_out(output_lif2),
        .done(done_lif2)
    );

    shifter_32bit lif4(
        .clk(clk),
        .start(time_step),
        .data_in(membrane_potential),
        .shift_amount(5'b00010),
        .mode(2'b01),
        .data_out(output_lif4),
        .done(done_lif4)
    );

    shifter_32bit lif8(
        .clk(clk),
        .start(time_step),
        .data_in(membrane_potential),
        .shift_amount(5'b00011),
        .mode(2'b01),
        .data_out(output_lif8),
        .done(done_lif8)
    );

    always @(posedge load) begin
        membrane_potential <= new_potential;
    end

    always @(posedge time_step) begin
        output_potential_decay <= membrane_potential;
    end

    always @(posedge clk) begin
        if (rst) begin
            membrane_potential <= 0;
        end else if (mode == `LIF0) begin
            membrane_potential <= membrane_potential;
        end else if (mode == `LIF2) begin
            if (done_lif2) begin
                membrane_potential <= output_lif2;
            end
        end else if (mode == `LIF4) begin
            if (done_lif4) begin
                membrane_potential <= output_lif4;
            end
        end else if (mode == `LIF8) begin
            if(done_lif8) begin
                membrane_potential <= output_lif8;
            end
        end else if (mode == `LIF24) begin
            if(done_lif2 & done_lif4) begin
                membrane_potential <= output_lif2 + output_lif4;
            end
        end else if(mode == `IZHI) begin
            if(izi1_done & izi2_done) begin
                membrane_potential <= izi_first_term - izi_second_term[31:0];
            end
        end else if(mode == `QUAD) begin
            if(v_squared_done) begin
                membrane_potential <= v_squared;
            end
        end else if(mode == `IDLE) begin
            membrane_potential <= membrane_potential;
        end
    end

endmodule

decay/decay_tb.v
`timescale 1ns/1ps
`include "decay.v"

module potential_decay_tb;
    reg clk;
    reg rst;
    reg load;
    reg time_step;
    reg [2:0] mode;
    reg [31:0] new_potential;
    wire [31:0] output_potential_decay;

    // Instantiate the DUT (Device Under Test)
    potential_decay dut (
        .clk(clk),
        .rst(rst),
        .load(load),
        .time_step(time_step),
        .mode(mode),
        .new_potential(new_potential),
        .output_potential_decay(output_potential_decay)
    );

    // Generate clock signal
    always #5 clk = ~clk;

    initial begin
        time_step = 0;
        #100;
        forever begin
            time_step = 1;
            #10 time_step = 0;
            #40;
        end
    end

    always @(posedge time_step) begin
        #5;
        if(output_potential_decay != 0)
            new_potential <= output_potential_decay;
        #10 load = 1;
        #10 load = 0;
    end

    initial begin
        $dumpfile("decay_tb.vcd");
        $dumpvars(0, potential_decay_tb);

        // Initialize signals
        clk = 0;
        rst = 1;
        load = 0;
        time_step = 0;
        mode = 3'b111;
        new_potential = 32'd0;
        
        // Apply reset
        #10 rst = 0;
        
        // Load initial potential
        #10 new_potential = 32'd1000;
        load = 1;
        #10 load = 0;
        
        #20 mode = 3'b001; 

        // End simulation
        #5000 $finish;
    end

    // Monitor outputs
    initial begin
        $monitor("Time=%0t | Mode=%b | Potential=%d | Output=%d", 
                 $time, mode, new_potential, output_potential_decay);
    end
endmodule

decay/decay_tb.vcd
$date
	Sun Feb 02 14:08:17 2025
$end
$version
	Icarus Verilog
$end
$timescale
	1ps
$end
$scope module potential_decay_tb $end
$var wire 32 ! output_potential_decay [31:0] $end
$var reg 1 " clk $end
$var reg 1 # load $end
$var reg 3 $ mode [2:0] $end
$var reg 32 % new_potential [31:0] $end
$var reg 1 & rst $end
$var reg 1 ' time_step $end
$scope module dut $end
$var wire 1 " clk $end
$var wire 1 # load $end
$var wire 3 ( mode [2:0] $end
$var wire 32 ) new_potential [31:0] $end
$var wire 1 & rst $end
$var wire 1 ' time_step $end
$var wire 1 * v_squared_done $end
$var wire 64 + v_squared [63:0] $end
$var wire 32 , output_lif8 [31:0] $end
$var wire 32 - output_lif4 [31:0] $end
$var wire 32 . output_lif2 [31:0] $end
$var wire 64 / izi_second_term [63:0] $end
$var wire 32 0 izi_first_term [31:0] $end
$var wire 1 1 izi2_done $end
$var wire 1 2 izi1_done $end
$var wire 1 3 done_lif8 $end
$var wire 1 4 done_lif4 $end
$var wire 1 5 done_lif2 $end
$var reg 32 6 membrane_potential [31:0] $end
$var reg 32 7 output_potential_decay [31:0] $end
$scope module izi1 $end
$var wire 1 " clk $end
$var wire 32 8 data_in [31:0] $end
$var wire 2 9 mode [1:0] $end
$var wire 5 : shift_amount [4:0] $end
$var wire 1 * start $end
$var reg 5 ; count [4:0] $end
$var reg 32 < data_out [31:0] $end
$var reg 1 2 done $end
$var reg 1 = running $end
$var reg 32 > shift_reg [31:0] $end
$upscope $end
$scope module izi2 $end
$var wire 32 ? A [31:0] $end
$var wire 32 @ B [31:0] $end
$var wire 1 " clk $end
$var wire 1 ' start $end
$var reg 6 A count [5:0] $end
$var reg 1 1 done $end
$var reg 32 B multiplicand [31:0] $end
$var reg 32 C multiplier [31:0] $end
$var reg 64 D product [63:0] $end
$var reg 64 E result [63:0] $end
$var reg 1 F running $end
$upscope $end
$scope module lif2 $end
$var wire 1 " clk $end
$var wire 32 G data_in [31:0] $end
$var wire 2 H mode [1:0] $end
$var wire 5 I shift_amount [4:0] $end
$var wire 1 ' start $end
$var reg 5 J count [4:0] $end
$var reg 32 K data_out [31:0] $end
$var reg 1 5 done $end
$var reg 1 L running $end
$var reg 32 M shift_reg [31:0] $end
$upscope $end
$scope module lif4 $end
$var wire 1 " clk $end
$var wire 32 N data_in [31:0] $end
$var wire 2 O mode [1:0] $end
$var wire 5 P shift_amount [4:0] $end
$var wire 1 ' start $end
$var reg 5 Q count [4:0] $end
$var reg 32 R data_out [31:0] $end
$var reg 1 4 done $end
$var reg 1 S running $end
$var reg 32 T shift_reg [31:0] $end
$upscope $end
$scope module lif8 $end
$var wire 1 " clk $end
$var wire 32 U data_in [31:0] $end
$var wire 2 V mode [1:0] $end
$var wire 5 W shift_amount [4:0] $end
$var wire 1 ' start $end
$var reg 5 X count [4:0] $end
$var reg 32 Y data_out [31:0] $end
$var reg 1 3 done $end
$var reg 1 Z running $end
$var reg 32 [ shift_reg [31:0] $end
$upscope $end
$scope module v_squared_mul $end
$var wire 32 \ A [31:0] $end
$var wire 32 ] B [31:0] $end
$var wire 1 " clk $end
$var wire 1 ' start $end
$var reg 6 ^ count [5:0] $end
$var reg 1 * done $end
$var reg 32 _ multiplicand [31:0] $end
$var reg 32 ` multiplier [31:0] $end
$var reg 64 a product [63:0] $end
$var reg 64 b result [63:0] $end
$var reg 1 c running $end
$upscope $end
$upscope $end
$upscope $end
$enddefinitions $end
$comment Show the parameter values. $end
$dumpall
$end
#0
$dumpvars
xc
bx b
bx a
bx `
bx _
bx ^
bx ]
bx \
bx [
xZ
bx Y
bx X
b11 W
b1 V
bx U
bx T
xS
bx R
bx Q
b10 P
b1 O
bx N
bx M
xL
bx K
bx J
b1 I
b1 H
bx G
xF
bx E
bx D
bx C
bx B
bx A
b101 @
bx ?
bx >
x=
bx <
bx ;
b11 :
b1 9
bx 8
bx 7
bx 6
x5
x4
x3
x2
x1
bx 0
bx /
bx .
bx -
bx ,
bx +
x*
b0 )
b111 (
0'
1&
b0 %
b111 $
0#
0"
bx !
$end
#5000
b0 6
b0 ?
b0 G
b0 N
b0 U
b0 \
b0 ]
1"
#10000
0"
0&
#15000
1"
#20000
b1111101000 6
b1111101000 ?
b1111101000 G
b1111101000 N
b1111101000 U
b1111101000 \
b1111101000 ]
0"
1#
b1111101000 %
b1111101000 )
#25000
1"
#30000
0"
0#
#35000
1"
#40000
0"
#45000
1"
#50000
0"
b1 $
b1 (
#55000
1"
#60000
0"
#65000
1"
#70000
0"
#75000
1"
#80000
0"
#85000
1"
#90000
0"
#95000
1"
#100000
0*
1c
b0 ^
b0 a
b1111101000 `
b1111101000 _
01
1F
b0 A
b0 D
b101 C
b1111101000 B
05
1L
b1 J
b1111101000 M
04
1S
b10 Q
b1111101000 T
03
1Z
b11 X
b1111101000 [
b1111101000 !
b1111101000 7
0"
1'
#105000
b0 J
b111110100 M
b1 Q
b111110100 T
b10 X
b111110100 [
b1 ^
b111110100 `
b1 A
b10 C
b1111101000 D
1"
#110000
0"
0'
#115000
b1 X
b11111010 [
b0 Q
b11111010 T
0L
15
b111110100 .
b111110100 K
b10 A
b1 C
b10 ^
b11111010 `
1"
1#
#120000
0"
#125000
0S
14
b11111010 -
b11111010 R
b0 X
b1111101 [
b111110100 6
b111110100 ?
b111110100 G
b111110100 N
b111110100 U
b111110100 \
b111110100 ]
b11 ^
b1111101 `
b11 A
b0 C
b1001110001000 D
1"
0#
#130000
0"
#135000
0Z
13
b1111101 ,
b1111101 Y
b100 A
b100 ^
b111110 `
b1111101000000 a
1"
#140000
0"
#145000
b101 ^
b11111 `
b101 A
1"
#150000
b111110100 !
b111110100 7
03
1Z
b11 X
b111110100 [
04
1S
b10 Q
b111110100 T
05
1L
b1 J
b0 A
b0 D
b101 C
b111110100 B
b0 ^
b0 a
b111110100 `
b111110100 _
0"
1'
#155000
b10 X
b11111010 [
b1 Q
b11111010 T
b0 J
b11111010 M
b111110100 %
b111110100 )
b1 A
b10 C
b111110100 D
b1 ^
b11111010 `
1"
#160000
0"
0'
#165000
0L
15
b11111010 .
b11111010 K
b0 Q
b1111101 T
b1 X
b1111101 [
b10 ^
b1111101 `
b10 A
b1 C
1"
1#
#170000
0"
#175000
b11111010 6
b11111010 ?
b11111010 G
b11111010 N
b11111010 U
b11111010 \
b11111010 ]
b0 X
b111110 [
0S
14
b1111101 -
b1111101 R
b11 A
b0 C
b100111000100 D
b11 ^
b111110 `
b11111010000 a
1"
0#
#180000
0"
#185000
0Z
13
b111110 ,
b111110 Y
b100 ^
b11111 `
b100 A
1"
#190000
0"
#195000
b101 A
b101 ^
b1111 `
b10011100010000 a
1"
#200000
b0 ^
b0 a
b11111010 `
b11111010 _
b0 A
b0 D
b101 C
b11111010 B
05
1L
b1 J
04
1S
b10 Q
b11111010 T
03
1Z
b11 X
b11111010 [
b11111010 !
b11111010 7
0"
1'
#205000
b0 J
b1111101 M
b1 Q
b1111101 T
b10 X
b1111101 [
b11111010 %
b11111010 )
b1 ^
b1111101 `
b1 A
b10 C
b11111010 D
1"
#210000
0"
0'
#215000
b1 X
b111110 [
b0 Q
b111110 T
0L
15
b1111101 .
b1111101 K
b10 A
b1 C
b10 ^
b111110 `
b111110100 a
1"
1#
#220000
0"
#225000
0S
14
b111110 -
b111110 R
b0 X
b11111 [
b1111101 6
b1111101 ?
b1111101 G
b1111101 N
b1111101 U
b1111101 \
b1111101 ]
b11 ^
b11111 `
b11 A
b0 C
b10011100010 D
1"
0#
#230000
0"
#235000
0Z
13
b11111 ,
b11111 Y
b100 A
b100 ^
b1111 `
b100111000100 a
1"
#240000
0"
#245000
b101 ^
b111 `
b1100101100100 a
b101 A
1"
#250000
b1111101 !
b1111101 7
03
1Z
b11 X
b1111101 [
04
1S
b10 Q
b1111101 T
05
1L
b1 J
b0 A
b0 D
b101 C
b1111101 B
b0 ^
b0 a
b1111101 `
b1111101 _
0"
1'
#255000
b10 X
b111110 [
b1 Q
b111110 T
b0 J
b111110 M
b1111101 %
b1111101 )
b1 A
b10 C
b1111101 D
b1 ^
b111110 `
b1111101 a
1"
#260000
0"
0'
#265000
0L
15
b111110 .
b111110 K
b0 Q
b11111 T
b1 X
b11111 [
b10 ^
b11111 `
b10 A
b1 C
1"
1#
#270000
0"
#275000
b111110 6
b111110 ?
b111110 G
b111110 N
b111110 U
b111110 \
b111110 ]
b0 X
b1111 [
0S
14
b11111 -
b11111 R
b11 A
b0 C
b1001110001 D
b11 ^
b1111 `
b1001110001 a
1"
0#
#280000
0"
#285000
0Z
13
b1111 ,
b1111 Y
b100 ^
b111 `
b11001011001 a
b100 A
1"
#290000
0"
#295000
b101 A
b101 ^
b11 `
b111000101001 a
1"
#300000
b0 ^
b0 a
b111110 `
b111110 _
b0 A
b0 D
b101 C
b111110 B
05
1L
b1 J
04
1S
b10 Q
b111110 T
03
1Z
b11 X
b111110 [
b111110 !
b111110 7
0"
1'
#305000
b0 J
b11111 M
b1 Q
b11111 T
b10 X
b11111 [
b111110 %
b111110 )
b1 ^
b11111 `
b1 A
b10 C
b111110 D
1"
#310000
0"
0'
#315000
b1 X
b1111 [
b0 Q
b1111 T
0L
15
b11111 .
b11111 K
b10 A
b1 C
b10 ^
b1111 `
b1111100 a
1"
1#
#320000
0"
#325000
0S
14
b1111 -
b1111 R
b0 X
b111 [
b11111 6
b11111 ?
b11111 G
b11111 N
b11111 U
b11111 \
b11111 ]
b11 ^
b111 `
b101110100 a
b11 A
b0 C
b100110110 D
1"
0#
#330000
0"
#335000
0Z
13
b111 ,
b111 Y
b100 A
b100 ^
b11 `
b1101100100 a
1"
#340000
0"
#345000
b101 ^
b1 `
b11101000100 a
b101 A
1"
#350000
b11111 !
b11111 7
03
1Z
b11 X
b11111 [
04
1S
b10 Q
b11111 T
05
1L
b1 J
b0 A
b0 D
b101 C
b11111 B
b0 ^
b0 a
b11111 `
b11111 _
0"
1'
#355000
b10 X
b1111 [
b1 Q
b1111 T
b0 J
b1111 M
b11111 %
b11111 )
b1 A
b10 C
b11111 D
b1 ^
b1111 `
b11111 a
1"
#360000
0"
0'
#365000
0L
15
b1111 .
b1111 K
b0 Q
b111 T
b1 X
b111 [
b10 ^
b111 `
b1011101 a
b10 A
b1 C
1"
1#
#370000
0"
#375000
b1111 6
b1111 ?
b1111 G
b1111 N
b1111 U
b1111 \
b1111 ]
b0 X
b11 [
0S
14
b111 -
b111 R
b11 A
b0 C
b10011011 D
b11 ^
b11 `
b11011001 a
1"
0#
#380000
0"
#385000
0Z
13
b11 ,
b11 Y
b100 ^
b1 `
b111010001 a
b100 A
1"
#390000
0"
#395000
b101 A
b101 ^
b0 `
b1111000001 a
1"
#400000
b0 ^
b0 a
b1111 `
b1111 _
b0 A
b0 D
b101 C
b1111 B
05
1L
b1 J
04
1S
b10 Q
b1111 T
03
1Z
b11 X
b1111 [
b1111 !
b1111 7
0"
1'
#405000
b0 J
b111 M
b1 Q
b111 T
b10 X
b111 [
b1111 %
b1111 )
b1 ^
b111 `
b1111 a
b1 A
b10 C
b1111 D
1"
#410000
0"
0'
#415000
b1 X
b11 [
b0 Q
b11 T
0L
15
b111 .
b111 K
b10 A
b1 C
b10 ^
b11 `
b101101 a
1"
1#
#420000
0"
#425000
0S
14
b11 -
b11 R
b0 X
b1 [
b111 6
b111 ?
b111 G
b111 N
b111 U
b111 \
b111 ]
b11 ^
b1 `
b1101001 a
b11 A
b0 C
b1001011 D
1"
0#
#430000
0"
#435000
0Z
13
b1 ,
b1 Y
b100 A
b100 ^
b0 `
b11100001 a
1"
#440000
0"
#445000
b101 ^
b101 A
1"
#450000
b111 !
b111 7
03
1Z
b11 X
b111 [
04
1S
b10 Q
b111 T
05
1L
b1 J
b0 A
b0 D
b101 C
b111 B
b0 ^
b0 a
b111 `
b111 _
0"
1'
#455000
b10 X
b11 [
b1 Q
b11 T
b0 J
b11 M
b111 %
b111 )
b1 A
b10 C
b111 D
b1 ^
b11 `
b111 a
1"
#460000
0"
0'
#465000
0L
15
b11 .
b11 K
b0 Q
b1 T
b1 X
b1 [
b10 ^
b1 `
b10101 a
b10 A
b1 C
1"
1#
#470000
0"
#475000
b11 6
b11 ?
b11 G
b11 N
b11 U
b11 \
b11 ]
b0 X
b0 [
0S
14
b1 -
b1 R
b11 A
b0 C
b100011 D
b11 ^
b0 `
b110001 a
1"
0#
#480000
0"
#485000
0Z
13
b0 ,
b0 Y
b100 ^
b100 A
1"
#490000
0"
#495000
b101 A
b101 ^
1"
#500000
b0 ^
b0 a
b11 `
b11 _
b0 A
b0 D
b101 C
b11 B
05
1L
b1 J
04
1S
b10 Q
b11 T
03
1Z
b11 X
b11 [
b11 !
b11 7
0"
1'
#505000
b0 J
b1 M
b1 Q
b1 T
b10 X
b1 [
b11 %
b11 )
b1 ^
b1 `
b11 a
b1 A
b10 C
b11 D
1"
#510000
0"
0'
#515000
b1 X
b0 [
b0 Q
b0 T
0L
15
b1 .
b1 K
b10 A
b1 C
b10 ^
b0 `
b1001 a
1"
1#
#520000
0"
#525000
0S
14
b0 -
b0 R
b0 X
b1 6
b1 ?
b1 G
b1 N
b1 U
b1 \
b1 ]
b11 ^
b11 A
b0 C
b1111 D
1"
0#
#530000
0"
#535000
0Z
13
b100 A
b100 ^
1"
#540000
0"
#545000
b101 ^
b101 A
1"
#550000
b1 !
b1 7
03
1Z
b11 X
b1 [
04
1S
b10 Q
b1 T
05
1L
b1 J
b0 A
b0 D
b101 C
b1 B
b0 ^
b0 a
b1 `
b1 _
0"
1'
#555000
b10 X
b0 [
b1 Q
b0 T
b0 J
b0 M
b1 %
b1 )
b1 A
b10 C
b1 D
b1 ^
b0 `
b1 a
1"
#560000
0"
0'
#565000
0L
15
b0 .
b0 K
b0 Q
b1 X
b10 ^
b10 A
b1 C
1"
1#
#570000
0"
#575000
b0 6
b0 ?
b0 G
b0 N
b0 U
b0 \
b0 ]
b0 X
0S
14
b11 A
b0 C
b101 D
b11 ^
1"
0#
#580000
0"
#585000
0Z
13
b100 ^
b100 A
1"
#590000
0"
#595000
b101 A
b101 ^
1"
#600000
b0 ^
b0 a
b0 _
b0 A
b0 D
b101 C
b0 B
05
1L
b1 J
04
1S
b10 Q
03
1Z
b11 X
b0 !
b0 7
0"
1'
#605000
b0 J
b1 Q
b10 X
b1 ^
b1 A
b10 C
1"
#610000
0"
0'
#615000
b1 X
b0 Q
0L
15
b1 6
b1 ?
b1 G
b1 N
b1 U
b1 \
b1 ]
b10 A
b1 C
b10 ^
1"
1#
#620000
0"
#625000
0S
14
b0 X
b0 6
b0 ?
b0 G
b0 N
b0 U
b0 \
b0 ]
b11 ^
b11 A
b0 C
1"
0#
#630000
0"
#635000
0Z
13
b100 A
b100 ^
1"
#640000
0"
#645000
b101 ^
b101 A
1"
#650000
03
1Z
b11 X
04
1S
b10 Q
05
1L
b1 J
b0 A
b101 C
b0 ^
0"
1'
#655000
b10 X
b1 Q
b0 J
b1 A
b10 C
b1 ^
1"
#660000
0"
0'
#665000
0L
15
b0 Q
b1 X
b1 6
b1 ?
b1 G
b1 N
b1 U
b1 \
b1 ]
b10 ^
b10 A
b1 C
1"
1#
#670000
0"
#675000
b0 6
b0 ?
b0 G
b0 N
b0 U
b0 \
b0 ]
b0 X
0S
14
b11 A
b0 C
b11 ^
1"
0#
#680000
0"
#685000
0Z
13
b100 ^
b100 A
1"
#690000
0"
#695000
b101 A
b101 ^
1"
#700000
b0 ^
b0 A
b101 C
05
1L
b1 J
04
1S
b10 Q
03
1Z
b11 X
0"
1'
#705000
b0 J
b1 Q
b10 X
b1 ^
b1 A
b10 C
1"
#710000
0"
0'
#715000
b1 X
b0 Q
0L
15
b1 6
b1 ?
b1 G
b1 N
b1 U
b1 \
b1 ]
b10 A
b1 C
b10 ^
1"
1#
#720000
0"
#725000
0S
14
b0 X
b0 6
b0 ?
b0 G
b0 N
b0 U
b0 \
b0 ]
b11 ^
b11 A
b0 C
1"
0#
#730000
0"
#735000
0Z
13
b100 A
b100 ^
1"
#740000
0"
#745000
b101 ^
b101 A
1"
#750000
03
1Z
b11 X
04
1S
b10 Q
05
1L
b1 J
b0 A
b101 C
b0 ^
0"
1'
#755000
b10 X
b1 Q
b0 J
b1 A
b10 C
b1 ^
1"
#760000
0"
0'
#765000
0L
15
b0 Q
b1 X
b1 6
b1 ?
b1 G
b1 N
b1 U
b1 \
b1 ]
b10 ^
b10 A
b1 C
1"
1#
#770000
0"
#775000
b0 6
b0 ?
b0 G
b0 N
b0 U
b0 \
b0 ]
b0 X
0S
14
b11 A
b0 C
b11 ^
1"
0#
#780000
0"
#785000
0Z
13
b100 ^
b100 A
1"
#790000
0"
#795000
b101 A
b101 ^
1"
#800000
b0 ^
b0 A
b101 C
05
1L
b1 J
04
1S
b10 Q
03
1Z
b11 X
0"
1'
#805000
b0 J
b1 Q
b10 X
b1 ^
b1 A
b10 C
1"
#810000
0"
0'
#815000
b1 X
b0 Q
0L
15
b1 6
b1 ?
b1 G
b1 N
b1 U
b1 \
b1 ]
b10 A
b1 C
b10 ^
1"
1#
#820000
0"
#825000
0S
14
b0 X
b0 6
b0 ?
b0 G
b0 N
b0 U
b0 \
b0 ]
b11 ^
b11 A
b0 C
1"
0#
#830000
0"
#835000
0Z
13
b100 A
b100 ^
1"
#840000
0"
#845000
b101 ^
b101 A
1"
#850000
03
1Z
b11 X
04
1S
b10 Q
05
1L
b1 J
b0 A
b101 C
b0 ^
0"
1'
#855000
b10 X
b1 Q
b0 J
b1 A
b10 C
b1 ^
1"
#860000
0"
0'
#865000
0L
15
b0 Q
b1 X
b1 6
b1 ?
b1 G
b1 N
b1 U
b1 \
b1 ]
b10 ^
b10 A
b1 C
1"
1#
#870000
0"
#875000
b0 6
b0 ?
b0 G
b0 N
b0 U
b0 \
b0 ]
b0 X
0S
14
b11 A
b0 C
b11 ^
1"
0#
#880000
0"
#885000
0Z
13
b100 ^
b100 A
1"
#890000
0"
#895000
b101 A
b101 ^
1"
#900000
b0 ^
b0 A
b101 C
05
1L
b1 J
04
1S
b10 Q
03
1Z
b11 X
0"
1'
#905000
b0 J
b1 Q
b10 X
b1 ^
b1 A
b10 C
1"
#910000
0"
0'
#915000
b1 X
b0 Q
0L
15
b1 6
b1 ?
b1 G
b1 N
b1 U
b1 \
b1 ]
b10 A
b1 C
b10 ^
1"
1#
#920000
0"
#925000
0S
14
b0 X
b0 6
b0 ?
b0 G
b0 N
b0 U
b0 \
b0 ]
b11 ^
b11 A
b0 C
1"
0#
#930000
0"
#935000
0Z
13
b100 A
b100 ^
1"
#940000
0"
#945000
b101 ^
b101 A
1"
#950000
03
1Z
b11 X
04
1S
b10 Q
05
1L
b1 J
b0 A
b101 C
b0 ^
0"
1'
#955000
b10 X
b1 Q
b0 J
b1 A
b10 C
b1 ^
1"
#960000
0"
0'
#965000
0L
15
b0 Q
b1 X
b1 6
b1 ?
b1 G
b1 N
b1 U
b1 \
b1 ]
b10 ^
b10 A
b1 C
1"
1#
#970000
0"
#975000
b0 6
b0 ?
b0 G
b0 N
b0 U
b0 \
b0 ]
b0 X
0S
14
b11 A
b0 C
b11 ^
1"
0#
#980000
0"
#985000
0Z
13
b100 ^
b100 A
1"
#990000
0"
#995000
b101 A
b101 ^
1"
#1000000
b0 ^
b0 A
b101 C
05
1L
b1 J
04
1S
b10 Q
03
1Z
b11 X
0"
1'
#1005000
b0 J
b1 Q
b10 X
b1 ^
b1 A
b10 C
1"
#1010000
0"
0'
#1015000
b1 X
b0 Q
0L
15
b1 6
b1 ?
b1 G
b1 N
b1 U
b1 \
b1 ]
b10 A
b1 C
b10 ^
1"
1#
#1020000
0"
#1025000
0S
14
b0 X
b0 6
b0 ?
b0 G
b0 N
b0 U
b0 \
b0 ]
b11 ^
b11 A
b0 C
1"
0#
#1030000
0"
#1035000
0Z
13
b100 A
b100 ^
1"
#1040000
0"
#1045000
b101 ^
b101 A
1"
#1050000
03
1Z
b11 X
04
1S
b10 Q
05
1L
b1 J
b0 A
b101 C
b0 ^
0"
1'
#1055000
b10 X
b1 Q
b0 J
b1 A
b10 C
b1 ^
1"
#1060000
0"
0'
#1065000
0L
15
b0 Q
b1 X
b1 6
b1 ?
b1 G
b1 N
b1 U
b1 \
b1 ]
b10 ^
b10 A
b1 C
1"
1#
#1070000
0"
#1075000
b0 6
b0 ?
b0 G
b0 N
b0 U
b0 \
b0 ]
b0 X
0S
14
b11 A
b0 C
b11 ^
1"
0#
#1080000
0"
#1085000
0Z
13
b100 ^
b100 A
1"
#1090000
0"
#1095000
b101 A
b101 ^
1"
#1100000
b0 ^
b0 A
b101 C
05
1L
b1 J
04
1S
b10 Q
03
1Z
b11 X
0"
1'
#1105000
b0 J
b1 Q
b10 X
b1 ^
b1 A
b10 C
1"
#1110000
0"
0'
#1115000
b1 X
b0 Q
0L
15
b1 6
b1 ?
b1 G
b1 N
b1 U
b1 \
b1 ]
b10 A
b1 C
b10 ^
1"
1#
#1120000
0"
#1125000
0S
14
b0 X
b0 6
b0 ?
b0 G
b0 N
b0 U
b0 \
b0 ]
b11 ^
b11 A
b0 C
1"
0#
#1130000
0"
#1135000
0Z
13
b100 A
b100 ^
1"
#1140000
0"
#1145000
b101 ^
b101 A
1"
#1150000
03
1Z
b11 X
04
1S
b10 Q
05
1L
b1 J
b0 A
b101 C
b0 ^
0"
1'
#1155000
b10 X
b1 Q
b0 J
b1 A
b10 C
b1 ^
1"
#1160000
0"
0'
#1165000
0L
15
b0 Q
b1 X
b1 6
b1 ?
b1 G
b1 N
b1 U
b1 \
b1 ]
b10 ^
b10 A
b1 C
1"
1#
#1170000
0"
#1175000
b0 6
b0 ?
b0 G
b0 N
b0 U
b0 \
b0 ]
b0 X
0S
14
b11 A
b0 C
b11 ^
1"
0#
#1180000
0"
#1185000
0Z
13
b100 ^
b100 A
1"
#1190000
0"
#1195000
b101 A
b101 ^
1"
#1200000
b0 ^
b0 A
b101 C
05
1L
b1 J
04
1S
b10 Q
03
1Z
b11 X
0"
1'
#1205000
b0 J
b1 Q
b10 X
b1 ^
b1 A
b10 C
1"
#1210000
0"
0'
#1215000
b1 X
b0 Q
0L
15
b1 6
b1 ?
b1 G
b1 N
b1 U
b1 \
b1 ]
b10 A
b1 C
b10 ^
1"
1#
#1220000
0"
#1225000
0S
14
b0 X
b0 6
b0 ?
b0 G
b0 N
b0 U
b0 \
b0 ]
b11 ^
b11 A
b0 C
1"
0#
#1230000
0"
#1235000
0Z
13
b100 A
b100 ^
1"
#1240000
0"
#1245000
b101 ^
b101 A
1"
#1250000
03
1Z
b11 X
04
1S
b10 Q
05
1L
b1 J
b0 A
b101 C
b0 ^
0"
1'
#1255000
b10 X
b1 Q
b0 J
b1 A
b10 C
b1 ^
1"
#1260000
0"
0'
#1265000
0L
15
b0 Q
b1 X
b1 6
b1 ?
b1 G
b1 N
b1 U
b1 \
b1 ]
b10 ^
b10 A
b1 C
1"
1#
#1270000
0"
#1275000
b0 6
b0 ?
b0 G
b0 N
b0 U
b0 \
b0 ]
b0 X
0S
14
b11 A
b0 C
b11 ^
1"
0#
#1280000
0"
#1285000
0Z
13
b100 ^
b100 A
1"
#1290000
0"
#1295000
b101 A
b101 ^
1"
#1300000
b0 ^
b0 A
b101 C
05
1L
b1 J
04
1S
b10 Q
03
1Z
b11 X
0"
1'
#1305000
b0 J
b1 Q
b10 X
b1 ^
b1 A
b10 C
1"
#1310000
0"
0'
#1315000
b1 X
b0 Q
0L
15
b1 6
b1 ?
b1 G
b1 N
b1 U
b1 \
b1 ]
b10 A
b1 C
b10 ^
1"
1#
#1320000
0"
#1325000
0S
14
b0 X
b0 6
b0 ?
b0 G
b0 N
b0 U
b0 \
b0 ]
b11 ^
b11 A
b0 C
1"
0#
#1330000
0"
