utils/encording.v
// Decay modes
`define LIF0 3'b000
`define LIF2 3'b001
`define LIF4 3'b010
`define LIF8 3'b011
`define LIF24 3'b100
`define IZHI 3'b101
`define QUAD 3'b110
`define IDLE 3'b111

// Adder model
`define LIF 2'b00
`define IZHI_AD 2'b01
`define QLIF 2'b10

// Adder init mode
`define DEFAULT 3'b000
`define A 3'b001
`define B 3'b010
`define C 3'b011
`define D 3'b100
`define VT 3'b101
`define U 3'b110

utils/32bit_shifter.v
module shifter_32bit (
    input wire clk,
    input wire rst,
    input wire start,
    input wire [31:0] data_in,
    input wire [4:0] shift_amount,  // Supports shifting up to 31 bits
    input wire [1:0] mode,          // 00: Logical Left, 01: Logical Right, 10: Arithmetic Right
    output reg [31:0] data_out,
    output reg done
);

    reg [31:0] shift_reg;
    reg [4:0] count;
    reg running;

    always @(posedge rst) begin
        shift_reg <= 0;
        count <= 0;
        running <= 0;
        done <= 0;
        data_out <= 0;
    end

    always @(posedge start) begin
        shift_reg <= data_in;
        count <= shift_amount;
        running <= 1;
        done <= 0;
        data_out <= 0;
    end

    always @(posedge clk) begin
        if (running) begin
            if (count > 0) begin
                case (mode)
                    2'b00: shift_reg <= shift_reg << 1;  // Logical Left Shift
                    2'b01: shift_reg <= shift_reg >> 1;  // Logical Right Shift
                    2'b10: shift_reg <= shift_reg >>> 1; // Arithmetic Right Shift
                    default: shift_reg <= shift_reg; // No operation
                endcase
                count <= count - 1;
            end else begin
                data_out <= shift_reg;
                done <= 1;
                running <= 0;
            end
        end
    end

endmodule

utils/32bit_mul.v
module multiplier_32bit(
    input wire clk,
    input wire rst,
    input wire start,
    input wire [31:0] A,
    input wire [31:0] B,
    output reg [63:0] result,
    output reg done
);
    
    reg [31:0] multiplicand, multiplier;
    reg [63:0] product;
    reg [5:0] count;
    reg running;

    always @(posedge rst) begin
        multiplicand <= 0;
        multiplier <= 0;
        product <= 0;
        count <= 0;
        running <= 0;
        done <= 0;
    end

    always @(posedge start) begin
        multiplicand <= A;
        multiplier <= B;
        product <= 0;
        count <= 0;
        running <= 1;
        done <= 0;
    end

    always @(posedge clk) begin
        if (running) begin
            if (count < 32) begin
                if (multiplier[0] == 1'b1) begin
                    product = product + ({32'b0, multiplicand} << count);
                end
                multiplier = multiplier >> 1;
                count = count + 1;
            end else begin
                result <= product;
                done <= 1;
                running <= 0;
            end
        end
    end

endmodule

decay/decay.v
`include "../utils/32bit_mul.v"
`include "../utils/32bit_shifter.v"
`include "../utils/encording.v"

module potential_decay(
    input wire clk,
    input wire rst,
    input wire load,
    input wire time_step,
    input wire [2:0] mode,
    input wire [31:0] new_potential,
    output reg [31:0] output_potential_decay
);
    
    reg [31:0] membrane_potential;
    wire [31:0] output_lif2;
    wire [31:0] output_lif4;
    wire [31:0] output_lif8;
    wire done_lif2;
    wire done_lif4;
    wire done_lif8;
    wire [63:0] v_squared;
    wire [31:0] izi_first_term;
    wire [63:0] izi_second_term;
    wire v_squared_done;
    wire izi1_done;
    wire izi2_done;
    reg start;

    multiplier_32bit v_squared_mul(
        .clk(clk),
        .rst(time_step),
        .start(start),
        .A(membrane_potential),
        .B(membrane_potential),
        .result(v_squared),
        .done(v_squared_done)
    );

    shifter_32bit izi1(
        .clk(clk),
        .rst(time_step),
        .start(v_squared_done),
        .data_in(v_squared[31:0]),
        .shift_amount(5'b00011),
        .mode(2'b01),
        .data_out(izi_first_term),
        .done(izi1_done)
    );

    multiplier_32bit izi2(
        .clk(clk),
        .rst(time_step),
        .start(start),
        .A(membrane_potential),
        .B(32'h0005),
        .result(izi_second_term),
        .done(izi2_done)
    );

    shifter_32bit lif2(
        .clk(clk),
        .rst(time_step),
        .start(start),
        .data_in(membrane_potential),
        .shift_amount(5'b00001),
        .mode(2'b01),
        .data_out(output_lif2),
        .done(done_lif2)
    );

    shifter_32bit lif4(
        .clk(clk),
        .rst(time_step),
        .start(start),
        .data_in(membrane_potential),
        .shift_amount(5'b00010),
        .mode(2'b01),
        .data_out(output_lif4),
        .done(done_lif4)
    );

    shifter_32bit lif8(
        .clk(clk),
        .rst(time_step),
        .start(start),
        .data_in(membrane_potential),
        .shift_amount(5'b00011),
        .mode(2'b01),
        .data_out(output_lif8),
        .done(done_lif8)
    );

    always @(posedge load) begin
        membrane_potential <= new_potential;
        #10 start <= 1;
        #10 start <= 0;
    end

    always @(posedge time_step) begin
        output_potential_decay <= membrane_potential;
    end

    always @(posedge clk) begin
        if (rst) begin
            membrane_potential <= 0;
            output_potential_decay <= 0;
        end else if (mode == `LIF0) begin
            // Do nothing
        end else if (mode == `LIF2) begin
            if (done_lif2) begin
                membrane_potential <= output_lif2;
            end
        end else if (mode == `LIF4) begin
            if (done_lif4) begin
                membrane_potential <= output_lif4;
            end
        end else if (mode == `LIF8) begin
            if(done_lif8) begin
                membrane_potential <= output_lif8;
            end
        end else if (mode == `LIF24) begin
            if(done_lif2 & done_lif4) begin
                membrane_potential <= output_lif2 + output_lif4;
            end
        end else if(mode == `IZHI) begin
            if(izi1_done & izi2_done) begin
                membrane_potential <= izi_first_term - izi_second_term[31:0];
            end
        end else if(mode == `QUAD) begin
            if(v_squared_done) begin
                membrane_potential <= v_squared;
            end
        end else if(mode == `IDLE) begin
            // do nothing
        end
    end

endmodule

code/neuro_int/decay/decay_tb.v
`timescale 1ns/1ps
`include "decay.v"

module potential_decay_tb;
    reg clk;
    reg rst;
    reg load;
    reg time_step;
    reg [2:0] mode;
    reg [31:0] new_potential;
    wire [31:0] output_potential_decay;

    // Instantiate the DUT (Device Under Test)
    potential_decay dut (
        .clk(clk),
        .rst(rst),
        .load(load),
        .time_step(time_step),
        .mode(mode),
        .new_potential(new_potential),
        .output_potential_decay(output_potential_decay)
    );

    // Generate clock signal
    always #5 clk = ~clk;

    initial begin
        time_step = 0;
        #100;
        forever begin
            time_step = 1;
            #10 time_step = 0;
            #400;
        end
    end

    always @(posedge time_step) begin
        #10 new_potential <= output_potential_decay;
        #10 load = 1;
        #10 load = 0;
    end

    initial begin
        $dumpfile("decay_tb.vcd");
        $dumpvars(0, potential_decay_tb);

        // Initialize signals
        clk = 0;
        rst = 1;
        load = 0;
        time_step = 0;
        mode = 3'b111;
        new_potential = 32'd0;
        
        // Apply reset
        #10 rst = 0;
        
        // Load initial potential
        #10 new_potential = 32'd1000;
        load = 1;
        #10 load = 0;
        
        #20 mode = `IZHI; 

        // End simulation
        #5000 $finish;
    end

    // Monitor outputs
    initial begin
        $monitor("Time=%0t | Mode=%b | Potential=%d | Output=%d", 
                 $time, mode, new_potential, output_potential_decay);
    end
endmodule

decay/decay_tb.vcd
$date
	Sun Feb 02 16:04:16 2025
$end
$version
	Icarus Verilog
$end
$timescale
	1ps
$end
$scope module potential_decay_tb $end
$var wire 32 ! output_potential_decay [31:0] $end
$var reg 1 " clk $end
$var reg 1 # load $end
$var reg 3 $ mode [2:0] $end
$var reg 32 % new_potential [31:0] $end
$var reg 1 & rst $end
$var reg 1 ' time_step $end
$scope module dut $end
$var wire 1 " clk $end
$var wire 1 # load $end
$var wire 3 ( mode [2:0] $end
$var wire 32 ) new_potential [31:0] $end
$var wire 1 & rst $end
$var wire 1 ' time_step $end
$var wire 1 * v_squared_done $end
$var wire 64 + v_squared [63:0] $end
$var wire 32 , output_lif8 [31:0] $end
$var wire 32 - output_lif4 [31:0] $end
$var wire 32 . output_lif2 [31:0] $end
$var wire 64 / izi_second_term [63:0] $end
$var wire 32 0 izi_first_term [31:0] $end
$var wire 1 1 izi2_done $end
$var wire 1 2 izi1_done $end
$var wire 1 3 done_lif8 $end
$var wire 1 4 done_lif4 $end
$var wire 1 5 done_lif2 $end
$var reg 32 6 membrane_potential [31:0] $end
$var reg 32 7 output_potential_decay [31:0] $end
$var reg 1 8 start $end
$scope module izi1 $end
$var wire 1 " clk $end
$var wire 32 9 data_in [31:0] $end
$var wire 2 : mode [1:0] $end
$var wire 1 ' rst $end
$var wire 5 ; shift_amount [4:0] $end
$var wire 1 * start $end
$var reg 5 < count [4:0] $end
$var reg 32 = data_out [31:0] $end
$var reg 1 2 done $end
$var reg 1 > running $end
$var reg 32 ? shift_reg [31:0] $end
$upscope $end
$scope module izi2 $end
$var wire 32 @ A [31:0] $end
$var wire 32 A B [31:0] $end
$var wire 1 " clk $end
$var wire 1 ' rst $end
$var wire 1 8 start $end
$var reg 6 B count [5:0] $end
$var reg 1 1 done $end
$var reg 32 C multiplicand [31:0] $end
$var reg 32 D multiplier [31:0] $end
$var reg 64 E product [63:0] $end
$var reg 64 F result [63:0] $end
$var reg 1 G running $end
$upscope $end
$scope module lif2 $end
$var wire 1 " clk $end
$var wire 32 H data_in [31:0] $end
$var wire 2 I mode [1:0] $end
$var wire 1 ' rst $end
$var wire 5 J shift_amount [4:0] $end
$var wire 1 8 start $end
$var reg 5 K count [4:0] $end
$var reg 32 L data_out [31:0] $end
$var reg 1 5 done $end
$var reg 1 M running $end
$var reg 32 N shift_reg [31:0] $end
$upscope $end
$scope module lif4 $end
$var wire 1 " clk $end
$var wire 32 O data_in [31:0] $end
$var wire 2 P mode [1:0] $end
$var wire 1 ' rst $end
$var wire 5 Q shift_amount [4:0] $end
$var wire 1 8 start $end
$var reg 5 R count [4:0] $end
$var reg 32 S data_out [31:0] $end
$var reg 1 4 done $end
$var reg 1 T running $end
$var reg 32 U shift_reg [31:0] $end
$upscope $end
$scope module lif8 $end
$var wire 1 " clk $end
$var wire 32 V data_in [31:0] $end
$var wire 2 W mode [1:0] $end
$var wire 1 ' rst $end
$var wire 5 X shift_amount [4:0] $end
$var wire 1 8 start $end
$var reg 5 Y count [4:0] $end
$var reg 32 Z data_out [31:0] $end
$var reg 1 3 done $end
$var reg 1 [ running $end
$var reg 32 \ shift_reg [31:0] $end
$upscope $end
$scope module v_squared_mul $end
$var wire 32 ] A [31:0] $end
$var wire 32 ^ B [31:0] $end
$var wire 1 " clk $end
$var wire 1 ' rst $end
$var wire 1 8 start $end
$var reg 6 _ count [5:0] $end
$var reg 1 * done $end
$var reg 32 ` multiplicand [31:0] $end
$var reg 32 a multiplier [31:0] $end
$var reg 64 b product [63:0] $end
$var reg 64 c result [63:0] $end
$var reg 1 d running $end
$upscope $end
$upscope $end
$upscope $end
$enddefinitions $end
$comment Show the parameter values. $end
$dumpall
$end
#0
$dumpvars
xd
bx c
bx b
bx a
bx `
bx _
bx ^
bx ]
bx \
x[
bx Z
bx Y
b11 X
b1 W
bx V
bx U
xT
bx S
bx R
b10 Q
b1 P
bx O
bx N
xM
bx L
bx K
b1 J
b1 I
bx H
xG
bx F
bx E
bx D
bx C
bx B
b101 A
bx @
bx ?
x>
bx =
bx <
b11 ;
b1 :
bx 9
x8
bx 7
bx 6
x5
x4
x3
x2
x1
bx 0
bx /
bx .
bx -
bx ,
bx +
x*
b0 )
b111 (
0'
1&
b0 %
b111 $
0#
0"
bx !
$end
#5000
b0 !
b0 7
b0 6
b0 @
b0 H
b0 O
b0 V
b0 ]
b0 ^
1"
#10000
0"
0&
#15000
1"
#20000
b1111101000 6
b1111101000 @
b1111101000 H
b1111101000 O
b1111101000 V
b1111101000 ]
b1111101000 ^
0"
1#
b1111101000 %
b1111101000 )
#25000
1"
#30000
0*
1d
b0 _
b0 b
b1111101000 a
b1111101000 `
01
1G
b0 B
b0 E
b101 D
b1111101000 C
05
1M
b1 K
b1111101000 N
04
1T
b10 R
b1111101000 U
03
1[
b11 Y
b1111101000 \
18
0"
0#
#35000
b10 Y
b111110100 \
b1 R
b111110100 U
b0 K
b111110100 N
b1 B
b10 D
b1111101000 E
b1 _
b111110100 a
1"
#40000
08
0"
#45000
0M
15
b111110100 .
b111110100 L
b0 R
b11111010 U
b1 Y
b11111010 \
b10 _
b11111010 a
b10 B
b1 D
1"
#50000
0"
b101 $
b101 (
#55000
b0 Y
b1111101 \
0T
14
b11111010 -
b11111010 S
b11 B
b0 D
b1001110001000 E
b11 _
b1111101 a
1"
#60000
0"
#65000
0[
13
b1111101 ,
b1111101 Z
b100 _
b111110 a
b1111101000000 b
b100 B
1"
#70000
0"
#75000
b101 B
b101 _
b11111 a
1"
#80000
0"
#85000
b110 _
b1111 a
b1001110001000000 b
b110 B
1"
#90000
0"
#95000
b111 B
b111 _
b111 a
b11001011001000000 b
1"
#100000
0d
b0 _
b0 b
b0 a
b0 `
02
0>
b0 <
b0 ?
0G
b0 B
b0 E
b0 C
05
b0 N
04
b0 U
03
b0 \
b1111101000 !
b1111101000 7
0"
1'
#105000
1"
#110000
0"
0'
#115000
1"
#120000
0"
1#
#125000
1"
#130000
1[
b11 Y
b1111101000 \
1T
b10 R
b1111101000 U
1M
b1 K
b1111101000 N
1G
b101 D
b1111101000 C
1d
b1111101000 a
b1111101000 `
18
0"
0#
#135000
b10 Y
b111110100 \
b1 R
b111110100 U
b0 K
b111110100 N
b1 B
b10 D
b1111101000 E
b1 _
b111110100 a
1"
#140000
08
0"
#145000
0M
15
b0 R
b11111010 U
b1 Y
b11111010 \
b10 _
b11111010 a
b10 B
b1 D
1"
#150000
0"
#155000
b0 Y
b1111101 \
0T
14
b11 B
b0 D
b1001110001000 E
b11 _
b1111101 a
1"
#160000
0"
#165000
0[
13
b100 _
b111110 a
b1111101000000 b
b100 B
1"
#170000
0"
#175000
b101 B
b101 _
b11111 a
1"
#180000
0"
#185000
b110 _
b1111 a
b1001110001000000 b
b110 B
1"
#190000
0"
#195000
b111 B
b111 _
b111 a
b11001011001000000 b
1"
#200000
0"
#205000
b1000 _
b11 a
b111000101001000000 b
b1000 B
1"
#210000
0"
#215000
b1001 B
b1001 _
b1 a
b1110111001001000000 b
1"
#220000
0"
#225000
b1010 _
b0 a
b11110100001001000000 b
b1010 B
1"
#230000
0"
#235000
b1011 B
b1011 _
1"
#240000
0"
#245000
b1100 _
b1100 B
1"
#250000
0"
#255000
b1101 B
b1101 _
1"
#260000
0"
#265000
b1110 _
b1110 B
1"
#270000
0"
#275000
b1111 B
b1111 _
1"
#280000
0"
#285000
b10000 _
b10000 B
1"
#290000
0"
#295000
b10001 B
b10001 _
1"
#300000
0"
#305000
b10010 _
b10010 B
1"
#310000
0"
#315000
b10011 B
b10011 _
1"
#320000
0"
#325000
b10100 _
b10100 B
1"
#330000
0"
#335000
b10101 B
b10101 _
1"
#340000
0"
#345000
b10110 _
b10110 B
1"
#350000
0"
#355000
b10111 B
b10111 _
1"
#360000
0"
#365000
b11000 _
b11000 B
1"
#370000
0"
#375000
b11001 B
b11001 _
1"
#380000
0"
#385000
b11010 _
b11010 B
1"
#390000
0"
#395000
b11011 B
b11011 _
1"
#400000
0"
#405000
b11100 _
b11100 B
1"
#410000
0"
#415000
b11101 B
b11101 _
1"
#420000
0"
#425000
b11110 _
b11110 B
1"
#430000
0"
#435000
b11111 B
b11111 _
1"
#440000
0"
#445000
b100000 _
b100000 B
1"
#450000
0"
#455000
1>
b11 <
b11110100001001000000 ?
b11110100001001000000 9
0G
11
b1001110001000 /
b1001110001000 F
0d
1*
b11110100001001000000 +
b11110100001001000000 c
1"
#460000
0"
#465000
b10 <
b1111010000100100000 ?
1"
#470000
0"
#475000
b1 <
b111101000010010000 ?
1"
#480000
0"
#485000
b0 <
b11110100001001000 ?
1"
#490000
0"
#495000
0>
12
b11110100001001000 0
b11110100001001000 =
1"
#500000
0"
#505000
b11101010011000000 6
b11101010011000000 @
b11101010011000000 H
b11101010011000000 O
b11101010011000000 V
b11101010011000000 ]
b11101010011000000 ^
1"
#510000
b11101010011000000 !
b11101010011000000 7
03
b0 \
04
b0 U
05
b0 N
01
b0 B
b0 E
b0 C
02
b0 ?
0*
b0 _
b0 b
b0 `
0"
1'
#515000
1"
#520000
b11101010011000000 %
b11101010011000000 )
0"
0'
#525000
1"
#530000
0"
1#
#535000
1"
#540000
1d
b11101010011000000 a
b11101010011000000 `
1G
b101 D
b11101010011000000 C
1M
b1 K
b11101010011000000 N
1T
b10 R
b11101010011000000 U
1[
b11 Y
b11101010011000000 \
18
0"
0#
#545000
b0 K
b1110101001100000 N
b1 R
b1110101001100000 U
b10 Y
b1110101001100000 \
b1 _
b1110101001100000 a
b1 B
b10 D
b11101010011000000 E
1"
#550000
08
0"
#555000
b1 Y
b111010100110000 \
b0 R
b111010100110000 U
0M
15
b1110101001100000 .
b1110101001100000 L
b10 B
b1 D
b10 _
b111010100110000 a
1"
#560000
0"
#565000
0T
14
b111010100110000 -
b111010100110000 S
b0 Y
b11101010011000 \
b11 _
b11101010011000 a
b11 B
b0 D
b10010010011111000000 E
1"
#570000
0"
#575000
0[
13
b11101010011000 ,
b11101010011000 Z
b100 B
b100 _
b1110101001100 a
1"
#580000
0"
#585000
b101 _
b111010100110 a
b101 B
1"
#590000
0"
#595000
b110 B
b110 _
b11101010011 a
1"
#600000
0"
#605000
b111 _
b1110101001 a
b11101010011000000000000 b
b111 B
1"
#610000
0"
#615000
b1000 B
b1000 _
b111010100 a
b1010111111001000000000000 b
1"
#620000
0"
#625000
b1001 _
b11101010 a
b1001 B
1"
#630000
0"
#635000
b1010 B
b1010 _
b1110101 a
1"
#640000
0"
#645000
b1011 _
b111010 a
b1000101100101001000000000000 b
b1011 B
1"
#650000
0"
#655000
b1100 B
b1100 _
b11101 a
1"
#660000
0"
#665000
b1101 _
b1110 a
b100101111111101001000000000000 b
b1101 B
1"
#670000
0"
#675000
b1110 B
b1110 _
b111 a
1"
#680000
0"
#685000
b1111 _
b11 a
b10011011001011101001000000000000 b
b1111 B
1"
#690000
0"
#695000
b10000 B
b10000 _
b1 a
b110000101100011101001000000000000 b
1"
#700000
0"
#705000
b10001 _
b0 a
b1101011010010011101001000000000000 b
b10001 B
1"
#710000
0"
#715000
b10010 B
b10010 _
1"
#720000
0"
#725000
b10011 _
b10011 B
1"
#730000
0"
#735000
b10100 B
b10100 _
1"
#740000
0"
#745000
b10101 _
b10101 B
1"
#750000
0"
#755000
b10110 B
b10110 _
1"
#760000
0"
#765000
b10111 _
b10111 B
1"
#770000
0"
#775000
b11000 B
b11000 _
1"
#780000
0"
#785000
b11001 _
b11001 B
1"
#790000
0"
#795000
b11010 B
b11010 _
1"
#800000
0"
#805000
b11011 _
b11011 B
1"
#810000
0"
#815000
b11100 B
b11100 _
1"
#820000
0"
#825000
b11101 _
b11101 B
1"
#830000
0"
#835000
b11110 B
b11110 _
1"
#840000
0"
#845000
b11111 _
b11111 B
1"
#850000
0"
#855000
b100000 B
b100000 _
1"
#860000
0"
#865000
1>
b11 <
b1011010010011101001000000000000 ?
b1011010010011101001000000000000 9
0d
1*
b1101011010010011101001000000000000 +
b1101011010010011101001000000000000 c
0G
11
b10010010011111000000 /
b10010010011111000000 F
1"
#870000
0"
#875000
b10 <
b101101001001110100100000000000 ?
1"
#880000
0"
#885000
b1 <
b10110100100111010010000000000 ?
1"
#890000
0"
#895000
b0 <
b1011010010011101001000000000 ?
1"
#900000
0"
#905000
0>
12
b1011010010011101001000000000 0
b1011010010011101001000000000 =
1"
#910000
0"
#915000
b1011010000001010101001000000 6
b1011010000001010101001000000 @
b1011010000001010101001000000 H
b1011010000001010101001000000 O
b1011010000001010101001000000 V
b1011010000001010101001000000 ]
b1011010000001010101001000000 ^
1"
#920000
0*
b0 _
b0 b
b0 `
02
b0 ?
01
b0 B
b0 E
b0 C
05
b0 N
04
b0 U
03
b0 \
b1011010000001010101001000000 !
b1011010000001010101001000000 7
0"
1'
#925000
1"
#930000
b1011010000001010101001000000 %
b1011010000001010101001000000 )
0"
0'
#935000
1"
#940000
0"
1#
#945000
1"
#950000
1[
b11 Y
b1011010000001010101001000000 \
1T
b10 R
b1011010000001010101001000000 U
1M
b1 K
b1011010000001010101001000000 N
1G
b101 D
b1011010000001010101001000000 C
1d
b1011010000001010101001000000 a
b1011010000001010101001000000 `
18
0"
0#
#955000
b10 Y
b101101000000101010100100000 \
b1 R
b101101000000101010100100000 U
b0 K
b101101000000101010100100000 N
b1 B
b10 D
b1011010000001010101001000000 E
b1 _
b101101000000101010100100000 a
1"
#960000
08
0"
#965000
0M
15
b101101000000101010100100000 .
b101101000000101010100100000 L
b0 R
b10110100000010101010010000 U
b1 Y
b10110100000010101010010000 \
b10 _
b10110100000010101010010000 a
b10 B
b1 D
1"
#970000
0"
#975000
b0 Y
b1011010000001010101001000 \
0T
14
b10110100000010101010010000 -
b10110100000010101010010000 S
b11 B
b0 D
b111000010000110101001101000000 E
b11 _
b1011010000001010101001000 a
1"
#980000
0"
#985000
0[
13
b1011010000001010101001000 ,
b1011010000001010101001000 Z
b100 _
b101101000000101010100100 a
b100 B
1"
#990000
0"
#995000
b101 B
b101 _
b10110100000010101010010 a
1"
#1000000
0"
#1005000
b110 _
b1011010000001010101001 a
b110 B
1"
#1010000
0"
#1015000
b111 B
b111 _
b101101000000101010100 a
b1011010000001010101001000000000000 b
1"
#1020000
0"
#1025000
b1000 _
b10110100000010101010 a
b1000 B
1"
#1030000
0"
#1035000
b1001 B
b1001 _
b1011010000001010101 a
1"
#1040000
0"
#1045000
b1010 _
b101101000000101010 a
b1100101010001011111110001000000000000 b
b1010 B
1"
#1050000
0"
#1055000
b1011 B
b1011 _
b10110100000010101 a
1"
#1060000
0"
#1065000
b1100 _
b1011010000001010 a
b111001101010110110100010001000000000000 b
b1100 B
1"
#1070000
0"
#1075000
b1101 B
b1101 _
b101101000000101 a
1"
#1080000
0"
#1085000
b1110 _
b10110100000010 a
b11101101101101100000110010001000000000000 b
b1110 B
1"
#1090000
0"
#1095000
b1111 B
b1111 _
b1011010000001 a
1"
#1100000
0"
#1105000
b10000 _
b101101000000 a
b1110111101111000001001110010001000000000000 b
b10000 B
1"
#1110000
0"
#1115000
b10001 B
b10001 _
b10110100000 a
1"
#1120000
0"
#1125000
b10010 _
b1011010000 a
b10010 B
1"
#1130000
0"
#1135000
b10011 B
b10011 _
b101101000 a
1"
#1140000
0"
#1145000
b10100 _
b10110100 a
b10100 B
1"
#1150000
0"
#1155000
b10101 B
b10101 _
b1011010 a
1"
#1160000
0"
#1165000
b10110 _
b101101 a
b10110 B
1"
#1170000
0"
#1175000
b10111 B
b10111 _
b10110 a
b10110101111010011001010001001110010001000000000000 b
1"
#1180000
0"
#1185000
b11000 _
b1011 a
b11000 B
1"
#1190000
0"
#1195000
b11001 B
b11001 _
b101 a
b1110000110000101000010010001001110010001000000000000 b
1"
#1200000
0"
#1205000
b11010 _
b10 a
b100100100110011010010100010001001110010001000000000000 b
b11010 B
1"
#1210000
0"
#1215000
b11011 B
b11011 _
b1 a
1"
#1220000
0"
#1225000
b11100 _
b0 a
b1111110100111101111011100010001001110010001000000000000 b
b11100 B
1"
#1230000
0"
#1235000
b11101 B
b11101 _
1"
#1240000
0"
#1245000
b11110 _
b11110 B
1"
#1250000
0"
#1255000
b11111 B
b11111 _
1"
#1260000
0"
#1265000
b100000 _
b100000 B
1"
#1270000
0"
#1275000
1>
b11 <
b10001001110010001000000000000 ?
b10001001110010001000000000000 9
0G
11
b111000010000110101001101000000 /
b111000010000110101001101000000 F
0d
1*
b1111110100111101111011100010001001110010001000000000000 +
b1111110100111101111011100010001001110010001000000000000 c
1"
#1280000
0"
#1285000
b10 <
b1000100111001000100000000000 ?
1"
#1290000
0"
#1295000
b1 <
b100010011100100010000000000 ?
1"
#1300000
0"
#1305000
b0 <
b10001001110010001000000000 ?
1"
#1310000
0"
#1315000
0>
12
b10001001110010001000000000 0
b10001001110010001000000000 =
1"
#1320000
0"
#1325000
b11001001111000111100111011000000 6
b11001001111000111100111011000000 @
b11001001111000111100111011000000 H
b11001001111000111100111011000000 O
b11001001111000111100111011000000 V
b11001001111000111100111011000000 ]
b11001001111000111100111011000000 ^
1"
#1330000
b11001001111000111100111011000000 !
b11001001111000111100111011000000 7
03
b0 \
04
b0 U
05
b0 N
01
b0 B
b0 E
b0 C
02
b0 ?
0*
b0 _
b0 b
b0 `
0"
1'
#1335000
1"
#1340000
b11001001111000111100111011000000 %
b11001001111000111100111011000000 )
0"
0'
#1345000
1"
#1350000
0"
1#
#1355000
1"
#1360000
1d
b11001001111000111100111011000000 a
b11001001111000111100111011000000 `
1G
b101 D
b11001001111000111100111011000000 C
1M
b1 K
b11001001111000111100111011000000 N
1T
b10 R
b11001001111000111100111011000000 U
1[
b11 Y
b11001001111000111100111011000000 \
18
0"
0#
#1365000
b0 K
b1100100111100011110011101100000 N
b1 R
b1100100111100011110011101100000 U
b10 Y
b1100100111100011110011101100000 \
b1 _
b1100100111100011110011101100000 a
b1 B
b10 D
b11001001111000111100111011000000 E
1"
#1370000
08
0"
#1375000
b1 Y
b110010011110001111001110110000 \
b0 R
b110010011110001111001110110000 U
0M
15
b1100100111100011110011101100000 .
b1100100111100011110011101100000 L
b10 B
b1 D
b10 _
b110010011110001111001110110000 a
1"
#1380000
0"
#1385000
0T
14
b110010011110001111001110110000 -
b110010011110001111001110110000 S
b0 Y
b11001001111000111100111011000 \
b11 _
b11001001111000111100111011000 a
b11 B
b0 D
b1111110001011100110000100111000000 E
1"
#1390000
0"
#1395000
0[
13
b11001001111000111100111011000 ,
b11001001111000111100111011000 Z
b100 B
b100 _
b1100100111100011110011101100 a
1"
#1400000
0"
#1405000
b101 _
b110010011110001111001110110 a
b101 B
1"
#1410000
0"
#1415000
b110 B
b110 _
b11001001111000111100111011 a
1"
#1420000
0"
#1425000
b111 _
b1100100111100011110011101 a
b11001001111000111100111011000000000000 b
b111 B
1"
#1430000
0"
#1435000
b1000 B
b1000 _
b110010011110001111001110 a
b1001011101101010110110110001000000000000 b
1"
#1440000
0"
#1445000
b1001 _
b11001001111000111100111 a
b1001 B
1"
#1450000
0"
#1455000
b1010 B
b1010 _
b1100100111100011110011 a
b100010101100110010011110001001000000000000 b
1"
#1460000
0"
#1465000
b1011 _
b110010011110001111001 a
b1010101001011000001101100111001000000000000 b
b1011 B
1"
#1470000
0"
#1475000
b1100 B
b1100 _
b11001001111000111100 a
b10111010000111100000001010011001000000000000 b
1"
#1480000
0"
#1485000
b1101 _
b1100100111100011110 a
b1101 B
1"
#1490000
0"
#1495000
b1110 B
b1110 _
b110010011110001111 a
1"
#1500000
0"
#1505000
b1111 _
b11001001111000111 a
b1111100001101011010011110110011001000000000000 b
b1111 B
1"
#1510000
0"
#1515000
b10000 B
b10000 _
b1100100111100011 a
b101000110000110010111011001110011001000000000000 b
1"
#1520000
0"
#1525000
b10001 _
b110010011110001 a
b1011011001111000010001001111110011001000000000000 b
b10001 B
1"
#1530000
0"
#1535000
b10010 B
b10010 _
b11001001111000 a
b11000000001011100000100111011110011001000000000000 b
1"
#1540000
0"
#1545000
b10011 _
b1100100111100 a
b10011 B
1"
#1550000
0"
#1555000
b10100 B
b10100 _
b110010011110 a
1"
#1560000
0"
#1565000
b10101 _
b11001001111 a
b10101 B
1"
#1570000
0"
#1575000
b10110 B
b10110 _
b1100100111 a
b11100001111010011000111111111011110011001000000000000 b
1"
#1580000
0"
#1585000
b10111 _
b110010011 a
b1001110101101100010010110101111011110011001000000000000 b
b10111 B
1"
#1590000
0"
#1595000
b11000 B
b11000 _
b11001001 a
b10110011101010000000110100001111011110011001000000000000 b
1"
#1600000
0"
#1605000
b11001 _
b1100100 a
b101111101100010111101101111001111011110011001000000000000 b
b11001 B
1"
#1610000
0"
#1615000
b11010 B
b11010 _
b110010 a
1"
#1620000
0"
#1625000
b11011 _
b11001 a
b11011 B
1"
#1630000
0"
#1635000
b11100 B
b11100 _
b1100 a
b11111001100101010100101000111001111011110011001000000000000 b
1"
#1640000
0"
#1645000
b11101 _
b110 a
b11101 B
1"
#1650000
0"
#1655000
b11110 B
b11110 _
b11 a
1"
#1660000
0"
#1665000
b11111 _
b1 a
b11101001000101100111100000000111001111011110011001000000000000 b
b11111 B
1"
#1670000
0"
#1675000
b100000 B
b100000 _
b0 a
b1001111100110111100001010110000111001111011110011001000000000000 b
1"
#1680000
0"
#1685000
1>
b11 <
b11001111011110011001000000000000 ?
b11001111011110011001000000000000 9
0d
1*
b1001111100110111100001010110000111001111011110011001000000000000 +
b1001111100110111100001010110000111001111011110011001000000000000 c
0G
11
b1111110001011100110000100111000000 /
b1111110001011100110000100111000000 F
1"
#1690000
0"
#1695000
b10 <
b1100111101111001100100000000000 ?
1"
#1700000
0"
#1705000
b1 <
b110011110111100110010000000000 ?
1"
#1710000
0"
#1715000
b0 <
b11001111011110011001000000000 ?
1"
#1720000
0"
#1725000
0>
12
b11001111011110011001000000000 0
b11001111011110011001000000000 =
1"
#1730000
0"
#1735000
b101000011111000010100001000000 6
b101000011111000010100001000000 @
b101000011111000010100001000000 H
b101000011111000010100001000000 O
b101000011111000010100001000000 V
b101000011111000010100001000000 ]
b101000011111000010100001000000 ^
1"
#1740000
0*
b0 _
b0 b
b0 `
02
b0 ?
01
b0 B
b0 E
b0 C
05
b0 N
04
b0 U
03
b0 \
b101000011111000010100001000000 !
b101000011111000010100001000000 7
0"
1'
#1745000
1"
#1750000
b101000011111000010100001000000 %
b101000011111000010100001000000 )
0"
0'
#1755000
1"
#1760000
0"
1#
#1765000
1"
#1770000
1[
b11 Y
b101000011111000010100001000000 \
1T
b10 R
b101000011111000010100001000000 U
1M
b1 K
b101000011111000010100001000000 N
1G
b101 D
b101000011111000010100001000000 C
1d
b101000011111000010100001000000 a
b101000011111000010100001000000 `
18
0"
0#
#1775000
b10 Y
b10100001111100001010000100000 \
b1 R
b10100001111100001010000100000 U
b0 K
b10100001111100001010000100000 N
b1 B
b10 D
b101000011111000010100001000000 E
b1 _
b10100001111100001010000100000 a
1"
#1780000
08
0"
#1785000
0M
15
b10100001111100001010000100000 .
b10100001111100001010000100000 L
b0 R
b1010000111110000101000010000 U
b1 Y
b1010000111110000101000010000 \
b10 _
b1010000111110000101000010000 a
b10 B
b1 D
1"
#1790000
0"
