utils/encording.v
// Decay modes
`define LIF0 3'b000
`define LIF2 3'b001
`define LIF4 3'b010
`define LIF8 3'b011
`define LIF24 3'b100
`define IZHI 3'b101
`define QUAD 3'b110
`define IDLE 3'b111

// Adder model
`define LIF 2'b00
`define IZHI_AD 2'b01
`define QLIF 2'b10

// Adder init mode
`define DEFAULT 3'b000
`define A 3'b001
`define B 3'b010
`define C 3'b011
`define D 3'b100
`define VT 3'b101
`define U 3'b110

utils/32bit_shifter.v
module shifter_32bit (
    input wire clk,
    input wire rst,
    input wire start,
    input wire [31:0] data_in,
    input wire [4:0] shift_amount,  // Supports shifting up to 31 bits
    input wire [1:0] mode,          // 00: Logical Left, 01: Logical Right, 10: Arithmetic Right
    output reg [31:0] data_out,
    output reg done
);

    reg [31:0] shift_reg;
    reg [4:0] count;
    reg running;

    always @(posedge rst) begin
        shift_reg <= 0;
        count <= 0;
        running <= 0;
        done <= 0;
        data_out <= 0;
    end

    always @(posedge start) begin
        shift_reg <= data_in;
        count <= shift_amount;
        running <= 1;
        done <= 0;
        data_out <= 0;
    end

    always @(posedge clk) begin
        if (running) begin
            if (count > 0) begin
                case (mode)
                    2'b00: shift_reg <= shift_reg << 1;  // Logical Left Shift
                    2'b01: shift_reg <= shift_reg >> 1;  // Logical Right Shift
                    2'b10: shift_reg <= shift_reg >>> 1; // Arithmetic Right Shift
                    default: shift_reg <= shift_reg; // No operation
                endcase
                count <= count - 1;
            end else begin
                data_out <= shift_reg;
                done <= 1;
                running <= 0;
            end
        end
    end

endmodule

utils/32bit_mul.v
module multiplier_32bit(
    input wire clk,
    input wire rst,
    input wire start,
    input wire [31:0] A,
    input wire [31:0] B,
    output reg [63:0] result,
    output reg done
);
    
    reg [31:0] multiplicand, multiplier;
    reg [63:0] product;
    reg [5:0] count;
    reg running;

    always @(posedge rst) begin
        multiplicand <= 0;
        multiplier <= 0;
        product <= 0;
        count <= 0;
        running <= 0;
        done <= 0;
    end

    always @(posedge start) begin
        multiplicand <= A;
        multiplier <= B;
        product <= 0;
        count <= 0;
        running <= 1;
        done <= 0;
    end

    always @(posedge clk) begin
        if (running) begin
            if (count < 32) begin
                if (multiplier[0] == 1'b1) begin
                    product = product + ({32'b0, multiplicand} << count);
                end
                multiplier = multiplier >> 1;
                count = count + 1;
            end else begin
                result <= product;
                done <= 1;
                running <= 0;
            end
        end
    end

endmodule

decay/decay.v
`include "../utils/32bit_mul.v"
`include "../utils/32bit_shifter.v"
`include "../utils/encording.v"

module potential_decay(
    input wire clk,
    input wire rst,
    input wire load,
    input wire time_step,
    input wire [2:0] mode,
    input wire [31:0] new_potential,
    output reg [31:0] output_potential_decay
);
    
    reg [31:0] membrane_potential;
    wire [31:0] output_lif2;
    wire [31:0] output_lif4;
    wire [31:0] output_lif8;
    wire done_lif2;
    wire done_lif4;
    wire done_lif8;
    wire [63:0] v_squared;
    wire [31:0] izi_first_term;
    wire [63:0] izi_second_term;
    wire v_squared_done;
    wire izi1_done;
    wire izi2_done;
    reg start;

    multiplier_32bit v_squared_mul(
        .clk(clk),
        .rst(time_step),
        .start(start),
        .A(membrane_potential),
        .B(membrane_potential),
        .result(v_squared),
        .done(v_squared_done)
    );

    shifter_32bit izi1(
        .clk(clk),
        .rst(time_step),
        .start(v_squared_done),
        .data_in(v_squared[31:0]),
        .shift_amount(5'b00011),
        .mode(2'b01),
        .data_out(izi_first_term),
        .done(izi1_done)
    );

    multiplier_32bit izi2(
        .clk(clk),
        .rst(time_step),
        .start(start),
        .A(membrane_potential),
        .B(32'h0005),
        .result(izi_second_term),
        .done(izi2_done)
    );

    shifter_32bit lif2(
        .clk(clk),
        .rst(time_step),
        .start(start),
        .data_in(membrane_potential),
        .shift_amount(5'b00001),
        .mode(2'b01),
        .data_out(output_lif2),
        .done(done_lif2)
    );

    shifter_32bit lif4(
        .clk(clk),
        .rst(time_step),
        .start(start),
        .data_in(membrane_potential),
        .shift_amount(5'b00010),
        .mode(2'b01),
        .data_out(output_lif4),
        .done(done_lif4)
    );

    shifter_32bit lif8(
        .clk(clk),
        .rst(time_step),
        .start(start),
        .data_in(membrane_potential),
        .shift_amount(5'b00011),
        .mode(2'b01),
        .data_out(output_lif8),
        .done(done_lif8)
    );

    always @(posedge load) begin
        membrane_potential <= new_potential;
        #10 start <= 1;
        #10 start <= 0;
    end

    always @(posedge time_step) begin
        output_potential_decay <= membrane_potential;
    end

    always @(posedge clk) begin
        if (rst) begin
            membrane_potential <= 0;
            output_potential_decay <= 0;
        end else if (mode == `LIF0) begin
            // Do nothing
        end else if (mode == `LIF2) begin
            if (done_lif2) begin
                membrane_potential <= output_lif2;
            end
        end else if (mode == `LIF4) begin
            if (done_lif4) begin
                membrane_potential <= output_lif4;
            end
        end else if (mode == `LIF8) begin
            if(done_lif8) begin
                membrane_potential <= output_lif8;
            end
        end else if (mode == `LIF24) begin
            if(done_lif2 & done_lif4) begin
                membrane_potential <= output_lif2 + output_lif4;
            end
        end else if(mode == `IZHI) begin
            if(izi1_done & izi2_done) begin
                membrane_potential <= izi_first_term - izi_second_term[31:0];
            end
        end else if(mode == `QUAD) begin
            if(v_squared_done) begin
                membrane_potential <= v_squared;
            end
        end else if(mode == `IDLE) begin
            // do nothing
        end
    end

endmodule

decay/decay_tb.v
`timescale 1ns/1ps
`include "decay.v"

module potential_decay_tb;
    reg clk;
    reg rst;
    reg load;
    reg time_step;
    reg [2:0] mode;
    reg [31:0] new_potential;
    wire [31:0] output_potential_decay;

    // Instantiate the DUT (Device Under Test)
    potential_decay dut (
        .clk(clk),
        .rst(rst),
        .load(load),
        .time_step(time_step),
        .mode(mode),
        .new_potential(new_potential),
        .output_potential_decay(output_potential_decay)
    );

    // Generate clock signal
    always #5 clk = ~clk;

    initial begin
        time_step = 0;
        #100;
        forever begin
            time_step = 1;
            #10 time_step = 0;
            #80;
        end
    end

    always @(posedge time_step) begin
        #10 new_potential <= output_potential_decay;
        #10 load = 1;
        #10 load = 0;
    end

    initial begin
        $dumpfile("decay_tb.vcd");
        $dumpvars(0, potential_decay_tb);

        // Initialize signals
        clk = 0;
        rst = 1;
        load = 0;
        time_step = 0;
        mode = 3'b111;
        new_potential = 32'd0;
        
        // Apply reset
        #10 rst = 0;
        
        // Load initial potential
        #10 new_potential = 32'd1000;
        load = 1;
        #10 load = 0;
        
        #20 mode = 3'b010; 

        // End simulation
        #5000 $finish;
    end

    // Monitor outputs
    initial begin
        $monitor("Time=%0t | Mode=%b | Potential=%d | Output=%d", 
                 $time, mode, new_potential, output_potential_decay);
    end
endmodule

decay/decay_tb.vcd
$date
	Sun Feb 02 15:42:08 2025
$end
$version
	Icarus Verilog
$end
$timescale
	1ps
$end
$scope module potential_decay_tb $end
$var wire 32 ! output_potential_decay [31:0] $end
$var reg 1 " clk $end
$var reg 1 # load $end
$var reg 3 $ mode [2:0] $end
$var reg 32 % new_potential [31:0] $end
$var reg 1 & rst $end
$var reg 1 ' time_step $end
$scope module dut $end
$var wire 1 " clk $end
$var wire 1 # load $end
$var wire 3 ( mode [2:0] $end
$var wire 32 ) new_potential [31:0] $end
$var wire 1 & rst $end
$var wire 1 ' time_step $end
$var wire 1 * v_squared_done $end
$var wire 64 + v_squared [63:0] $end
$var wire 32 , output_lif8 [31:0] $end
$var wire 32 - output_lif4 [31:0] $end
$var wire 32 . output_lif2 [31:0] $end
$var wire 64 / izi_second_term [63:0] $end
$var wire 32 0 izi_first_term [31:0] $end
$var wire 1 1 izi2_done $end
$var wire 1 2 izi1_done $end
$var wire 1 3 done_lif8 $end
$var wire 1 4 done_lif4 $end
$var wire 1 5 done_lif2 $end
$var reg 32 6 membrane_potential [31:0] $end
$var reg 32 7 output_potential_decay [31:0] $end
$var reg 1 8 start $end
$scope module izi1 $end
$var wire 1 " clk $end
$var wire 32 9 data_in [31:0] $end
$var wire 2 : mode [1:0] $end
$var wire 1 ' rst $end
$var wire 5 ; shift_amount [4:0] $end
$var wire 1 * start $end
$var reg 5 < count [4:0] $end
$var reg 32 = data_out [31:0] $end
$var reg 1 2 done $end
$var reg 1 > running $end
$var reg 32 ? shift_reg [31:0] $end
$upscope $end
$scope module izi2 $end
$var wire 32 @ A [31:0] $end
$var wire 32 A B [31:0] $end
$var wire 1 " clk $end
$var wire 1 ' rst $end
$var wire 1 8 start $end
$var reg 6 B count [5:0] $end
$var reg 1 1 done $end
$var reg 32 C multiplicand [31:0] $end
$var reg 32 D multiplier [31:0] $end
$var reg 64 E product [63:0] $end
$var reg 64 F result [63:0] $end
$var reg 1 G running $end
$upscope $end
$scope module lif2 $end
$var wire 1 " clk $end
$var wire 32 H data_in [31:0] $end
$var wire 2 I mode [1:0] $end
$var wire 1 ' rst $end
$var wire 5 J shift_amount [4:0] $end
$var wire 1 8 start $end
$var reg 5 K count [4:0] $end
$var reg 32 L data_out [31:0] $end
$var reg 1 5 done $end
$var reg 1 M running $end
$var reg 32 N shift_reg [31:0] $end
$upscope $end
$scope module lif4 $end
$var wire 1 " clk $end
$var wire 32 O data_in [31:0] $end
$var wire 2 P mode [1:0] $end
$var wire 1 ' rst $end
$var wire 5 Q shift_amount [4:0] $end
$var wire 1 8 start $end
$var reg 5 R count [4:0] $end
$var reg 32 S data_out [31:0] $end
$var reg 1 4 done $end
$var reg 1 T running $end
$var reg 32 U shift_reg [31:0] $end
$upscope $end
$scope module lif8 $end
$var wire 1 " clk $end
$var wire 32 V data_in [31:0] $end
$var wire 2 W mode [1:0] $end
$var wire 1 ' rst $end
$var wire 5 X shift_amount [4:0] $end
$var wire 1 8 start $end
$var reg 5 Y count [4:0] $end
$var reg 32 Z data_out [31:0] $end
$var reg 1 3 done $end
$var reg 1 [ running $end
$var reg 32 \ shift_reg [31:0] $end
$upscope $end
$scope module v_squared_mul $end
$var wire 32 ] A [31:0] $end
$var wire 32 ^ B [31:0] $end
$var wire 1 " clk $end
$var wire 1 ' rst $end
$var wire 1 8 start $end
$var reg 6 _ count [5:0] $end
$var reg 1 * done $end
$var reg 32 ` multiplicand [31:0] $end
$var reg 32 a multiplier [31:0] $end
$var reg 64 b product [63:0] $end
$var reg 64 c result [63:0] $end
$var reg 1 d running $end
$upscope $end
$upscope $end
$upscope $end
$enddefinitions $end
$comment Show the parameter values. $end
$dumpall
$end
#0
$dumpvars
xd
bx c
bx b
bx a
bx `
bx _
bx ^
bx ]
bx \
x[
bx Z
bx Y
b11 X
b1 W
bx V
bx U
xT
bx S
bx R
b10 Q
b1 P
bx O
bx N
xM
bx L
bx K
b1 J
b1 I
bx H
xG
bx F
bx E
bx D
bx C
bx B
b101 A
bx @
bx ?
x>
bx =
bx <
b11 ;
b1 :
bx 9
x8
bx 7
bx 6
x5
x4
x3
x2
x1
bx 0
bx /
bx .
bx -
bx ,
bx +
x*
b0 )
b111 (
0'
1&
b0 %
b111 $
0#
0"
bx !
$end
#5000
b0 !
b0 7
b0 6
b0 @
b0 H
b0 O
b0 V
b0 ]
b0 ^
1"
#10000
0"
0&
#15000
1"
#20000
b1111101000 6
b1111101000 @
b1111101000 H
b1111101000 O
b1111101000 V
b1111101000 ]
b1111101000 ^
0"
1#
b1111101000 %
b1111101000 )
#25000
1"
#30000
0*
1d
b0 _
b0 b
b1111101000 a
b1111101000 `
01
1G
b0 B
b0 E
b101 D
b1111101000 C
05
1M
b1 K
b1111101000 N
04
1T
b10 R
b1111101000 U
03
1[
b11 Y
b1111101000 \
18
0"
0#
#35000
b10 Y
b111110100 \
b1 R
b111110100 U
b0 K
b111110100 N
b1 B
b10 D
b1111101000 E
b1 _
b111110100 a
1"
#40000
08
0"
#45000
0M
15
b111110100 .
b111110100 L
b0 R
b11111010 U
b1 Y
b11111010 \
b10 _
b11111010 a
b10 B
b1 D
1"
#50000
0"
b10 $
b10 (
#55000
b0 Y
b1111101 \
0T
14
b11111010 -
b11111010 S
b11 B
b0 D
b1001110001000 E
b11 _
b1111101 a
1"
#60000
0"
#65000
0[
13
b1111101 ,
b1111101 Z
b11111010 6
b11111010 @
b11111010 H
b11111010 O
b11111010 V
b11111010 ]
b11111010 ^
b100 _
b111110 a
b1111101000000 b
b100 B
1"
#70000
0"
#75000
b101 B
b101 _
b11111 a
1"
#80000
0"
#85000
b110 _
b1111 a
b1001110001000000 b
b110 B
1"
#90000
0"
#95000
b111 B
b111 _
b111 a
b11001011001000000 b
1"
#100000
0d
b0 _
b0 b
b0 a
b0 `
02
0>
b0 <
b0 ?
0G
b0 B
b0 E
b0 C
05
b0 N
04
b0 U
03
b0 \
b11111010 !
b11111010 7
0"
1'
#105000
1"
#110000
b11111010 %
b11111010 )
0"
0'
#115000
1"
#120000
0"
1#
#125000
1"
#130000
1[
b11 Y
b11111010 \
1T
b10 R
b11111010 U
1M
b1 K
b11111010 N
1G
b101 D
b11111010 C
1d
b11111010 a
b11111010 `
18
0"
0#
#135000
b10 Y
b1111101 \
b1 R
b1111101 U
b0 K
b1111101 N
b1 B
b10 D
b11111010 E
b1 _
b1111101 a
1"
#140000
08
0"
#145000
0M
15
b1111101 .
b1111101 L
b0 R
b111110 U
b1 Y
b111110 \
b10 _
b111110 a
b111110100 b
b10 B
b1 D
1"
#150000
0"
#155000
b0 Y
b11111 \
0T
14
b111110 -
b111110 S
b11 B
b0 D
b10011100010 E
b11 _
b11111 a
1"
#160000
0"
#165000
0[
13
b11111 ,
b11111 Z
b111110 6
b111110 @
b111110 H
b111110 O
b111110 V
b111110 ]
b111110 ^
b100 _
b1111 a
b100111000100 b
b100 B
1"
#170000
0"
#175000
b101 B
b101 _
b111 a
b1100101100100 b
1"
#180000
0"
#185000
b110 _
b11 a
b11100010100100 b
b110 B
1"
#190000
b111110 !
b111110 7
03
b0 \
04
b0 U
05
b0 N
0G
b0 B
b0 E
b0 C
0d
b0 _
b0 b
b0 a
b0 `
0"
1'
#195000
1"
#200000
b111110 %
b111110 )
0"
0'
#205000
1"
#210000
0"
1#
#215000
1"
#220000
1d
b111110 a
b111110 `
1G
b101 D
b111110 C
1M
b1 K
b111110 N
1T
b10 R
b111110 U
1[
b11 Y
b111110 \
18
0"
0#
#225000
b0 K
b11111 N
b1 R
b11111 U
b10 Y
b11111 \
b1 _
b11111 a
b1 B
b10 D
b111110 E
1"
#230000
08
0"
#235000
b1 Y
b1111 \
b0 R
b1111 U
0M
15
b11111 .
b11111 L
b10 B
b1 D
b10 _
b1111 a
b1111100 b
1"
#240000
0"
#245000
0T
14
b1111 -
b1111 S
b0 Y
b111 \
b11 _
b111 a
b101110100 b
b11 B
b0 D
b100110110 E
1"
#250000
0"
#255000
b1111 6
b1111 @
b1111 H
b1111 O
b1111 V
b1111 ]
b1111 ^
0[
13
b111 ,
b111 Z
b100 B
b100 _
b11 a
b1101100100 b
1"
#260000
0"
#265000
b101 _
b1 a
b11101000100 b
b101 B
1"
#270000
0"
#275000
b110 B
b110 _
b0 a
b111100000100 b
1"
#280000
0d
b0 _
b0 b
b0 `
0G
b0 B
b0 E
b0 C
05
b0 N
04
b0 U
03
b0 \
b1111 !
b1111 7
0"
1'
#285000
1"
#290000
b1111 %
b1111 )
0"
0'
#295000
1"
#300000
0"
1#
#305000
1"
#310000
1[
b11 Y
b1111 \
1T
b10 R
b1111 U
1M
b1 K
b1111 N
1G
b101 D
b1111 C
1d
b1111 a
b1111 `
18
0"
0#
#315000
b10 Y
b111 \
b1 R
b111 U
b0 K
b111 N
b1 B
b10 D
b1111 E
b1 _
b111 a
b1111 b
1"
#320000
08
0"
#325000
0M
15
b111 .
b111 L
b0 R
b11 U
b1 Y
b11 \
b10 _
b11 a
b101101 b
b10 B
b1 D
1"
#330000
0"
#335000
b0 Y
b1 \
0T
14
b11 -
b11 S
b11 B
b0 D
b1001011 E
b11 _
b1 a
b1101001 b
1"
#340000
0"
#345000
0[
13
b1 ,
b1 Z
b11 6
b11 @
b11 H
b11 O
b11 V
b11 ]
b11 ^
b100 _
b0 a
b11100001 b
b100 B
1"
#350000
0"
#355000
b101 B
b101 _
1"
#360000
0"
#365000
b110 _
b110 B
1"
#370000
b11 !
b11 7
03
b0 \
04
b0 U
05
b0 N
0G
b0 B
b0 E
b0 C
0d
b0 _
b0 b
b0 `
0"
1'
#375000
1"
#380000
b11 %
b11 )
0"
0'
#385000
1"
#390000
0"
1#
#395000
1"
#400000
1d
b11 a
b11 `
1G
b101 D
b11 C
1M
b1 K
b11 N
1T
b10 R
b11 U
1[
b11 Y
b11 \
18
0"
0#
#405000
b0 K
b1 N
b1 R
b1 U
b10 Y
b1 \
b1 _
b1 a
b11 b
b1 B
b10 D
b11 E
1"
#410000
08
0"
#415000
b1 Y
b0 \
b0 R
b0 U
0M
15
b1 .
b1 L
b10 B
b1 D
b10 _
b0 a
b1001 b
1"
#420000
0"
#425000
0T
14
b0 -
b0 S
b0 Y
b11 _
b11 B
b0 D
b1111 E
1"
#430000
0"
#435000
b0 6
b0 @
b0 H
b0 O
b0 V
b0 ]
b0 ^
0[
13
b0 ,
b0 Z
b100 B
b100 _
1"
#440000
0"
#445000
b101 _
b101 B
1"
#450000
0"
#455000
b110 B
b110 _
1"
#460000
0d
b0 _
b0 b
b0 `
0G
b0 B
b0 E
b0 C
05
b0 N
04
03
b0 !
b0 7
0"
1'
#465000
1"
#470000
b0 %
b0 )
0"
0'
#475000
1"
#480000
0"
1#
#485000
1"
#490000
1[
b11 Y
1T
b10 R
1M
b1 K
1G
b101 D
1d
18
0"
0#
#495000
b10 Y
b1 R
b0 K
b1 B
b10 D
b1 _
1"
#500000
08
0"
#505000
0M
15
b0 .
b0 L
b0 R
b1 Y
b10 _
b10 B
b1 D
1"
#510000
0"
#515000
b0 Y
0T
14
b11 B
b0 D
b11 _
1"
#520000
0"
#525000
0[
13
b100 _
b100 B
1"
#530000
0"
#535000
b101 B
b101 _
1"
#540000
0"
#545000
b110 _
b110 B
1"
#550000
03
04
05
0G
b0 B
0d
b0 _
0"
1'
#555000
1"
#560000
0"
0'
#565000
1"
#570000
0"
1#
#575000
1"
#580000
1d
1G
b101 D
1M
b1 K
1T
b10 R
1[
b11 Y
18
0"
0#
#585000
b0 K
b1 R
b10 Y
b1 _
b1 B
b10 D
1"
#590000
08
0"
#595000
b1 Y
b0 R
0M
15
b10 B
b1 D
b10 _
1"
#600000
0"
#605000
0T
14
b0 Y
b11 _
b11 B
b0 D
1"
#610000
0"
#615000
0[
13
b100 B
b100 _
1"
#620000
0"
#625000
b101 _
b101 B
1"
#630000
0"
#635000
b110 B
b110 _
1"
#640000
0d
b0 _
0G
b0 B
05
04
03
0"
1'
#645000
1"
#650000
0"
0'
#655000
1"
#660000
0"
1#
#665000
1"
#670000
1[
b11 Y
1T
b10 R
1M
b1 K
1G
b101 D
1d
18
0"
0#
#675000
b10 Y
b1 R
b0 K
b1 B
b10 D
b1 _
1"
#680000
08
0"
#685000
0M
15
b0 R
b1 Y
b10 _
b10 B
b1 D
1"
#690000
0"
#695000
b0 Y
0T
14
b11 B
b0 D
b11 _
1"
#700000
0"
#705000
0[
13
b100 _
b100 B
1"
#710000
0"
#715000
b101 B
b101 _
1"
#720000
0"
#725000
b110 _
b110 B
1"
#730000
03
04
05
0G
b0 B
0d
b0 _
0"
1'
#735000
1"
#740000
0"
0'
#745000
1"
#750000
0"
1#
#755000
1"
#760000
1d
1G
b101 D
1M
b1 K
1T
b10 R
1[
b11 Y
18
0"
0#
#765000
b0 K
b1 R
b10 Y
b1 _
b1 B
b10 D
1"
#770000
08
0"
#775000
b1 Y
b0 R
0M
15
b10 B
b1 D
b10 _
1"
#780000
0"
#785000
0T
14
b0 Y
b11 _
b11 B
b0 D
1"
#790000
0"
#795000
0[
13
b100 B
b100 _
1"
#800000
0"
#805000
b101 _
b101 B
1"
#810000
0"
#815000
b110 B
b110 _
1"
#820000
0d
b0 _
0G
b0 B
05
04
03
0"
1'
#825000
1"
#830000
0"
0'
#835000
1"
#840000
0"
1#
#845000
1"
#850000
1[
b11 Y
1T
b10 R
1M
b1 K
1G
b101 D
1d
18
0"
0#
#855000
b10 Y
b1 R
b0 K
b1 B
b10 D
b1 _
1"
#860000
08
0"
#865000
0M
15
b0 R
b1 Y
b10 _
b10 B
b1 D
1"
#870000
0"
#875000
b0 Y
0T
14
b11 B
b0 D
b11 _
1"
#880000
0"
#885000
0[
13
b100 _
b100 B
1"
#890000
0"
#895000
b101 B
b101 _
1"
#900000
0"
#905000
b110 _
b110 B
1"
#910000
03
04
05
0G
b0 B
0d
b0 _
0"
1'
#915000
1"
#920000
0"
0'
#925000
1"
#930000
0"
1#
#935000
1"
#940000
1d
1G
b101 D
1M
b1 K
1T
b10 R
1[
b11 Y
18
0"
0#
#945000
b0 K
b1 R
b10 Y
b1 _
b1 B
b10 D
1"
#950000
08
0"
#955000
b1 Y
b0 R
0M
15
b10 B
b1 D
b10 _
1"
#960000
0"
#965000
0T
14
b0 Y
b11 _
b11 B
b0 D
1"
#970000
0"
#975000
0[
13
b100 B
b100 _
1"
#980000
0"
#985000
b101 _
b101 B
1"
#990000
0"
#995000
b110 B
b110 _
1"
#1000000
0d
b0 _
0G
b0 B
05
04
03
0"
1'
#1005000
1"
#1010000
0"
0'
#1015000
1"
#1020000
0"
1#
#1025000
1"
#1030000
1[
b11 Y
1T
b10 R
1M
b1 K
1G
b101 D
1d
18
0"
0#
#1035000
b10 Y
b1 R
b0 K
b1 B
b10 D
b1 _
1"
#1040000
08
0"
#1045000
0M
15
b0 R
b1 Y
b10 _
b10 B
b1 D
1"
#1050000
0"
#1055000
b0 Y
0T
14
b11 B
b0 D
b11 _
1"
#1060000
0"
#1065000
0[
13
b100 _
b100 B
1"
#1070000
0"
#1075000
b101 B
b101 _
1"
#1080000
0"
#1085000
b110 _
b110 B
1"
#1090000
03
04
05
0G
b0 B
0d
b0 _
0"
1'
#1095000
1"
#1100000
0"
0'
#1105000
1"
#1110000
0"
1#
#1115000
1"
#1120000
1d
1G
b101 D
1M
b1 K
1T
b10 R
1[
b11 Y
18
0"
0#
#1125000
b0 K
b1 R
b10 Y
b1 _
b1 B
b10 D
1"
#1130000
08
0"
#1135000
b1 Y
b0 R
0M
15
b10 B
b1 D
b10 _
1"
#1140000
0"
#1145000
0T
14
b0 Y
b11 _
b11 B
b0 D
1"
#1150000
0"
#1155000
0[
13
b100 B
b100 _
1"
#1160000
0"
#1165000
b101 _
b101 B
1"
#1170000
0"
#1175000
b110 B
b110 _
1"
#1180000
0d
b0 _
0G
b0 B
05
04
03
0"
1'
#1185000
1"
#1190000
0"
0'
#1195000
1"
#1200000
0"
1#
#1205000
1"
#1210000
1[
b11 Y
1T
b10 R
1M
b1 K
1G
b101 D
1d
18
0"
0#
#1215000
b10 Y
b1 R
b0 K
b1 B
b10 D
b1 _
1"
#1220000
08
0"
#1225000
0M
15
b0 R
b1 Y
b10 _
b10 B
b1 D
1"
#1230000
0"
#1235000
b0 Y
0T
14
b11 B
b0 D
b11 _
1"
#1240000
0"
#1245000
0[
13
b100 _
b100 B
1"
#1250000
0"
#1255000
b101 B
b101 _
1"
#1260000
0"
#1265000
b110 _
b110 B
1"
#1270000
03
04
05
0G
b0 B
0d
b0 _
0"
1'
#1275000
1"
#1280000
0"
0'
#1285000
1"
#1290000
0"
1#
#1295000
1"
#1300000
1d
1G
b101 D
1M
b1 K
1T
b10 R
1[
b11 Y
18
0"
0#
#1305000
b0 K
b1 R
b10 Y
b1 _
b1 B
b10 D
1"
#1310000
08
0"
#1315000
b1 Y
b0 R
0M
15
b10 B
b1 D
b10 _
1"
#1320000
0"
#1325000
0T
14
b0 Y
b11 _
b11 B
b0 D
1"
#1330000
0"
#1335000
0[
13
b100 B
b100 _
1"
#1340000
0"
#1345000
b101 _
b101 B
1"
#1350000
0"
#1355000
b110 B
b110 _
1"
#1360000
0d
b0 _
0G
b0 B
05
04
03
0"
1'
#1365000
1"
#1370000
0"
0'
#1375000
1"
#1380000
0"
1#
#1385000
1"
#1390000
1[
b11 Y
1T
b10 R
1M
b1 K
1G
b101 D
1d
18
0"
0#
#1395000
b10 Y
b1 R
b0 K
b1 B
b10 D
b1 _
1"
#1400000
08
0"
#1405000
0M
15
b0 R
b1 Y
b10 _
b10 B
b1 D
1"
#1410000
0"
#1415000
b0 Y
0T
14
b11 B
b0 D
b11 _
1"
#1420000
0"
#1425000
0[
13
b100 _
b100 B
1"
#1430000
0"
#1435000
b101 B
b101 _
1"
#1440000
0"
#1445000
b110 _
b110 B
1"
#1450000
03
04
05
0G
b0 B
0d
b0 _
0"
1'
#1455000
1"
#1460000
0"
0'
#1465000
1"
#1470000
0"
1#
#1475000
1"
#1480000
1d
1G
b101 D
1M
b1 K
1T
b10 R
1[
b11 Y
18
0"
0#
#1485000
b0 K
b1 R
b10 Y
b1 _
b1 B
b10 D
1"
#1490000
08
0"
#1495000
b1 Y
b0 R
0M
15
b10 B
b1 D
b10 _
1"
#1500000
0"
#1505000
0T
14
b0 Y
b11 _
b11 B
b0 D
1"
#1510000
0"
#1515000
0[
13
b100 B
b100 _
1"
#1520000
0"
#1525000
b101 _
b101 B
1"
#1530000
0"
#1535000
b110 B
b110 _
1"
#1540000
0d
b0 _
0G
b0 B
05
04
03
0"
1'
#1545000
1"
#1550000
0"
0'
#1555000
1"
#1560000
0"
1#
#1565000
1"
#1570000
1[
b11 Y
1T
b10 R
1M
b1 K
1G
b101 D
1d
18
0"
0#
#1575000
b10 Y
b1 R
b0 K
b1 B
b10 D
b1 _
1"
#1580000
08
0"
#1585000
0M
15
b0 R
b1 Y
b10 _
b10 B
b1 D
1"
#1590000
0"
#1595000
b0 Y
0T
14
b11 B
b0 D
b11 _
1"
#1600000
0"
#1605000
0[
13
b100 _
b100 B
1"
#1610000
0"
#1615000
b101 B
b101 _
1"
#1620000
0"
#1625000
b110 _
b110 B
1"
#1630000
03
04
05
0G
b0 B
0d
b0 _
0"
1'
#1635000
1"
#1640000
0"
0'
#1645000
1"
#1650000
0"
1#
#1655000
1"
#1660000
1d
1G
b101 D
1M
b1 K
1T
b10 R
1[
b11 Y
18
0"
0#
#1665000
b0 K
b1 R
b10 Y
b1 _
b1 B
b10 D
1"
#1670000
08
0"
#1675000
b1 Y
b0 R
0M
15
b10 B
b1 D
b10 _
1"
#1680000
0"
#1685000
0T
14
b0 Y
b11 _
b11 B
b0 D
1"
#1690000
0"
#1695000
0[
13
b100 B
b100 _
1"
#1700000
0"
#1705000
b101 _
b101 B
1"
#1710000
0"
#1715000
b110 B
b110 _
1"
#1720000
0d
b0 _
0G
b0 B
05
04
03
0"
1'
#1725000
1"
#1730000
0"
0'
#1735000
1"
#1740000
0"
1#
#1745000
1"
#1750000
1[
b11 Y
1T
b10 R
1M
b1 K
1G
b101 D
1d
18
0"
0#
#1755000
b10 Y
b1 R
b0 K
b1 B
b10 D
b1 _
1"
#1760000
08
0"
#1765000
0M
15
b0 R
b1 Y
b10 _
b10 B
b1 D
1"
#1770000
0"
#1775000
b0 Y
0T
14
b11 B
b0 D
b11 _
1"
#1780000
0"
#1785000
0[
13
b100 _
b100 B
1"
#1790000
0"
#1795000
b101 B
b101 _
1"
#1800000
0"
#1805000
b110 _
b110 B
1"
#1810000
03
04
05
0G
b0 B
0d
b0 _
0"
1'
#1815000
1"
#1820000
0"
0'
#1825000
1"
#1830000
0"
1#
#1835000
1"
#1840000
1d
1G
b101 D
1M
b1 K
1T
b10 R
1[
b11 Y
18
0"
0#
#1845000
b0 K
b1 R
b10 Y
b1 _
b1 B
b10 D
1"
#1850000
08
0"
#1855000
b1 Y
b0 R
0M
15
b10 B
b1 D
b10 _
1"
#1860000
0"
#1865000
0T
14
b0 Y
b11 _
b11 B
b0 D
1"
#1870000
0"
#1875000
0[
13
b100 B
b100 _
1"
#1880000
0"
#1885000
b101 _
b101 B
1"
#1890000
0"
#1895000
b110 B
b110 _
1"
#1900000
0d
b0 _
0G
b0 B
05
04
03
0"
1'
#1905000
1"
#1910000
0"
0'
#1915000
1"
#1920000
0"
1#
#1925000
1"
#1930000
1[
b11 Y
1T
b10 R
1M
b1 K
1G
b101 D
1d
18
0"
0#
#1935000
b10 Y
b1 R
b0 K
b1 B
b10 D
b1 _
1"
#1940000
08
0"
#1945000
0M
15
b0 R
b1 Y
b10 _
b10 B
b1 D
1"
#1950000
0"
#1955000
b0 Y
0T
14
b11 B
b0 D
b11 _
1"
#1960000
0"
#1965000
0[
13
b100 _
b100 B
1"
#1970000
0"
#1975000
b101 B
b101 _
1"
#1980000
0"
#1985000
b110 _
b110 B
1"
#1990000
03
04
05
0G
b0 B
0d
b0 _
0"
1'
#1995000
1"
#2000000
0"
0'
#2005000
1"
#2010000
0"
1#
#2015000
1"
#2020000
1d
1G
b101 D
1M
b1 K
1T
b10 R
1[
b11 Y
18
0"
0#
#2025000
b0 K
b1 R
b10 Y
b1 _
b1 B
b10 D
1"
#2030000
08
0"
#2035000
b1 Y
b0 R
0M
15
b10 B
b1 D
b10 _
1"
#2040000
0"
#2045000
0T
14
b0 Y
b11 _
b11 B
b0 D
1"
#2050000
0"
#2055000
0[
13
b100 B
b100 _
1"
#2060000
0"
#2065000
b101 _
b101 B
1"
#2070000
0"
#2075000
b110 B
b110 _
1"
#2080000
0d
b0 _
0G
b0 B
05
04
03
0"
1'
#2085000
1"
#2090000
0"
0'
#2095000
1"
#2100000
0"
1#
#2105000
1"
#2110000
1[
b11 Y
1T
b10 R
1M
b1 K
1G
b101 D
1d
18
0"
0#
#2115000
b10 Y
b1 R
b0 K
b1 B
b10 D
b1 _
1"
#2120000
08
0"
#2125000
0M
15
b0 R
b1 Y
b10 _
b10 B
b1 D
1"
#2130000
0"
#2135000
b0 Y
0T
14
b11 B
b0 D
b11 _
1"
#2140000
0"
#2145000
0[
13
b100 _
b100 B
1"
#2150000
0"
