accumulator/accumulator.v
module Accumulator (
    input  clk,        // System clock
    input  rst,        // Reset signal
    input  time_step,  // Time step pulse (sync signal)
    input  load,       // Load signal for setting weights
    input  [9:0]  src_addr,  // 10-bit Source address
    input  [31:0] weight_in, // Input weight for loading
    output reg [31:0] accumulated_out // Output accumulated weight (32-bit)
);

    // Fixed-size registers for weight addresses and values
    reg [9:0]  weight_addr [0:15];  // 16 entries of 10-bit addresses
    reg [31:0] weight_value [0:15]; // 16 entries of 32-bit weights
    reg [31:0] accumulated_reg;     // 32-bit accumulation register
    reg [4:0]  write_ptr;           // 5-bit pointer for writing weights

    integer i; // Declare loop variable

    // Reset and Weight Initialization
    always @(posedge clk) begin
        for (i = 0; i < 16; i = i + 1) begin
            if (weight_addr[i] == src_addr) begin
                accumulated_reg <= accumulated_reg + weight_value[i];
            end
        end
    end

    always @(negedge rst) begin
        for (i = 0; i < 16; i = i + 1) begin
            weight_addr[i]  <= 10'b0;
            weight_value[i] <= 32'b0;
        end
        accumulated_reg <= 32'b0;
        write_ptr       <= 5'b0;
    end

    always @(posedge load) begin
        if (load) begin
            if (write_ptr < 16) begin
                weight_addr[write_ptr]  <= src_addr;
                weight_value[write_ptr] <= weight_in;
                write_ptr <= write_ptr + 1;
            end
        end
    end

    always @(posedge time_step) begin
        if(time_step) begin
            accumulated_out <= accumulated_reg; // Store accumulated weight
            accumulated_reg <= 32'b0;           // Reset accumulator for next time step
        end
    end

endmodule

code/rtl/neuro_int/accumulator/acc_tb.v
`include "accumulator.v"

module Accumulator_tb;

    // Testbench signals
    reg        clk;
    reg        rst;
    reg        time_step;
    reg        load;
    reg [9:0] src_addr;
    reg [31:0] weight_in;
    wire [31:0] accumulated_out;

    // Instantiate the Accumulator module
    Accumulator uut (
        .clk(clk),
        .rst(rst),
        .time_step(time_step),
        .load(load),
        .src_addr(src_addr),
        .weight_in(weight_in),
        .accumulated_out(accumulated_out)
    );

    // Clock generation
    always begin
        #5 clk = ~clk;
    end

    // Time step generation
    initial begin
        time_step = 0;
        #100;
        forever begin
            time_step = 1;
            #10 time_step = 0;
            #40;
        end
    end

    // Testbench stimulus
    initial begin
        $dumpfile("accumulator.vcd");
        $dumpvars(0, Accumulator_tb);

        // Initialize signals
        clk = 0;
        rst = 1;
        time_step = 0;
        load = 0;
        src_addr = 10'b0;
        weight_in = 32'b0;

        // Apply reset
        #10;
        rst = 0;

        // Load dummy weights and source addresses
        #10;
        load = 1;
        src_addr = 10'h001; weight_in = 32'h0000_0001; #10; // Load weight 1 for address 0x001
        load = 0;
        #5;
        load = 1;
        src_addr = 10'h002; weight_in = 32'h0000_0002; #10; // Load weight 2 for address 0x002
        load = 0;
        #5;
        load = 1;
        src_addr = 10'h003; weight_in = 32'h0000_0003; #10; // Load weight 3 for address 0x003
        load = 0;
        #5;
        load = 1;
        src_addr = 10'h004; weight_in = 32'h0000_0004; #10; // Load weight 4 for address 0x004
        load = 0;
        src_addr = 10'b0; weight_in = 32'b0; // Reset load signals
        #15;

        #10 src_addr = 10'h001; // Set source address to 0x001
        #10 src_addr = 10'h002; // Set source address to 0x002
        #10 src_addr = 10'h003; // Set source address to 0x003
        #10 src_addr = 10'h002; // Set source address to 0x004
        #10 src_addr = 10'h000; // reset source address
        
        #10 src_addr = 10'h001; // Set source address to 0x001
        #10 src_addr = 10'h002; // Set source address to 0x002
        #10 src_addr = 10'h003; // Set source address to 0x003
        #10 src_addr = 10'h000; // reset source address
        #100;

        // Display results
        $display("Accumulated Output: %h", accumulated_out);

        // End simulation
        #10;
        $finish;
    end

endmodule

accumulator/accumulator.vcd
$date
	Sun Feb 02 10:35:06 2025
$end
$version
	Icarus Verilog
$end
$timescale
	1s
$end
$scope module Accumulator_tb $end
$var wire 32 ! accumulated_out [31:0] $end
$var reg 1 " clk $end
$var reg 1 # load $end
$var reg 1 $ rst $end
$var reg 10 % src_addr [9:0] $end
$var reg 1 & time_step $end
$var reg 32 ' weight_in [31:0] $end
$scope module uut $end
$var wire 1 " clk $end
$var wire 1 # load $end
$var wire 1 $ rst $end
$var wire 10 ( src_addr [9:0] $end
$var wire 1 & time_step $end
$var wire 32 ) weight_in [31:0] $end
$var reg 32 * accumulated_out [31:0] $end
$var reg 32 + accumulated_reg [31:0] $end
$var reg 5 , write_ptr [4:0] $end
$var integer 32 - i [31:0] $end
$upscope $end
$upscope $end
$enddefinitions $end
$comment Show the parameter values. $end
$dumpall
$end
#0
$dumpvars
bx -
bx ,
bx +
bx *
b0 )
b0 (
b0 '
0&
b0 %
1$
0#
0"
bx !
$end
#5
b10000 -
1"
#10
b0 ,
b0 +
b10000 -
0"
0$
#15
b10000 -
1"
#20
b1 ,
0"
b1 '
b1 )
b1 %
b1 (
1#
#25
b1 +
b10000 -
1"
#30
0"
0#
#35
b10 ,
b10000 -
1"
b10 '
b10 )
b10 %
b10 (
1#
#40
0"
#45
b11 +
b10000 -
1"
0#
#50
b11 ,
0"
b11 '
b11 )
b11 %
b11 (
1#
#55
b110 +
b10000 -
1"
#60
0"
0#
#65
b100 ,
b10000 -
1"
b100 '
b100 )
b100 %
b100 (
1#
#70
0"
#75
b10000 -
1"
b0 '
b0 )
b0 %
b0 (
0#
#80
0"
#85
b10000 -
1"
#90
0"
#95
b10000 -
1"
#100
b0 +
b110 !
b110 *
0"
b1 %
b1 (
1&
#105
b1 +
b10000 -
1"
#110
0"
b10 %
b10 (
0&
#115
b11 +
b10000 -
1"
#120
0"
b11 %
b11 (
#125
b110 +
b10000 -
1"
#130
0"
b10 %
b10 (
#135
b1000 +
b10000 -
1"
#140
0"
b0 %
b0 (
#145
b10000 -
1"
#150
b0 +
b1000 !
b1000 *
0"
b1 %
b1 (
1&
#155
b1 +
b10000 -
1"
#160
0"
b10 %
b10 (
0&
#165
b11 +
b10000 -
1"
#170
0"
b11 %
b11 (
#175
b110 +
b10000 -
1"
#180
0"
b0 %
b0 (
#185
b10000 -
1"
#190
0"
#195
b10000 -
1"
#200
b0 +
b110 !
b110 *
0"
1&
#205
b10000 -
1"
#210
0"
0&
#215
b10000 -
1"
#220
0"
#225
b10000 -
1"
#230
0"
#235
b10000 -
1"
#240
0"
#245
b10000 -
1"
#250
b0 !
b0 *
0"
1&
#255
b10000 -
1"
#260
0"
0&
#265
b10000 -
1"
#270
0"
#275
b10000 -
1"
#280
0"
#285
b10000 -
1"
