code/rtl/neuro_int/accumulator/accumulator.v
`timescale 1ns/100ps

module accumulator (
    input  clk,        // System clock
    input  rst,        // Reset signal
    input  time_step,  // Time step pulse (sync signal)
    input  load,       // Load signal for setting weights
    input  mode,       // Mode
    input  [9:0]  src_addr,  // 10-bit Source address
    input  [31:0] weight_in, // Input weight for loading
    output reg [31:0] accumulated_out // Output accumulated weight (32-bit)
);

    reg [9:0]  weight_addr [0:15];  // 16 entries of 10-bit addresses
    reg [31:0] weight_value [0:15]; // 16 entries of 32-bit weights
    reg [31:0] accumulated_reg;     // 32-bit accumulation register
    reg [4:0]  write_ptr;           // 5-bit pointer for writing weights
    reg prev_time_step_val;                   
    reg prev_load;                           


    integer i; // Declare loop variable

    // Reset and Weight Initialization
    always @(posedge clk) begin
        prev_time_step_val <= time_step;
        if(rst) begin
            accumulated_reg <= 32'b0;
            accumulated_out <= 32'b0;
            prev_time_step_val <= 0;
        end else if(!mode) begin
            for (i = 0; i < 16; i = i + 1) begin
                if (weight_addr[i] == src_addr) begin
                    if(time_step && !prev_time_step_val) begin
                        accumulated_out <= accumulated_reg; // Output accumulated weight
                        accumulated_reg <= weight_value[i]; // Load new weight
                    end else begin
                        accumulated_reg <= accumulated_reg + weight_value[i];
                    end
                end
            end
        end
    end

    always @(posedge clk) begin
        prev_load <= load;
        if (rst) begin
            write_ptr <= 0;
            for (i = 0; i < 16; i = i + 1) begin
                weight_addr[i]  <= 10'b0;
                weight_value[i] <= 32'b0;
            end
        end
        if (load && !prev_load) begin
            weight_addr[write_ptr]  <= src_addr;
            weight_value[write_ptr] <= weight_in;
            write_ptr <= write_ptr + 1;
        end
    end

endmodule

code/rtl/neuro_int/accumulator/acc_tb.v
`timescale 1ns/100ps
`include "accumulator.v"

module Accumulator_tb;

    // Testbench signals
    reg        clk;
    reg        rst;
    reg        time_step;
    reg        load;
    reg        mode;
    reg [9:0] src_addr;
    reg [31:0] weight_in;
    wire [31:0] accumulated_out;

    // Instantiate the Accumulator module
    accumulator uut (
        .clk(clk),
        .rst(rst),
        .time_step(time_step),
        .load(load),
        .mode(mode),
        .src_addr(src_addr),
        .weight_in(weight_in),
        .accumulated_out(accumulated_out)
    );

    // Clock generation
    always begin
        #5 clk = ~clk;
    end

    // Time step generation
    initial begin
        time_step = 0;
        #100;
        forever begin
            time_step = 1;
            #10 time_step = 0;
            #40;
        end
    end

    // Testbench stimulus
    initial begin
        $dumpfile("accumulator.vcd");
        $dumpvars(0, Accumulator_tb);

        // Initialize signals
        clk = 0;
        rst = 1;
        time_step = 0;
        load = 0;
        mode = 0;
        src_addr = 10'b0;
        weight_in = 32'b0;

        // Apply reset
        #10;
        rst = 0;
        #10;
        mode = 1; // Set mode to 1

        // Load dummy weights and source addresses
        #10;
        load = 1;
        src_addr = 10'h001; weight_in = 32'h0000_0001; #10; // Load weight 1 for address 0x001
        load = 0;
        #10;
        load = 1;
        src_addr = 10'h002; weight_in = 32'h0000_0002; #10; // Load weight 2 for address 0x002
        load = 0;
        #10;
        load = 1;
        src_addr = 10'h003; weight_in = 32'h0000_0003; #10; // Load weight 3 for address 0x003
        load = 0;
        #10;
        load = 1;
        src_addr = 10'h004; weight_in = 32'h0000_0004; #10; // Load weight 4 for address 0x004
        load = 0;
        src_addr = 10'b0; weight_in = 32'b0; // Reset load signals
        #15;

        // Set mode to 0
        mode = 0;

        #10 src_addr = 10'h001; // Set source address to 0x001
        #10 src_addr = 10'h002; // Set source address to 0x002
        #10 src_addr = 10'h003; // Set source address to 0x003
        #10 src_addr = 10'h002; // Set source address to 0x004
        #10 src_addr = 10'h000; // reset source address
        
        #10 src_addr = 10'h001; // Set source address to 0x001
        #10 src_addr = 10'h002; // Set source address to 0x002
        #10 src_addr = 10'h003; // Set source address to 0x003
        #10 src_addr = 10'h000; // reset source address
        #100;

        // Display results
        $display("Accumulated Output: %h", accumulated_out);

        // End simulation
        #10;
        $finish;
    end

endmodule

code/rtl/neuro_int/accumulator/accumulator.vcd
$date
	Sun Feb 09 17:02:23 2025
$end
$version
	Icarus Verilog
$end
$timescale
	100ps
$end
$scope module Accumulator_tb $end
$var wire 32 ! accumulated_out [31:0] $end
$var reg 1 " clk $end
$var reg 1 # load $end
$var reg 1 $ mode $end
$var reg 1 % rst $end
$var reg 10 & src_addr [9:0] $end
$var reg 1 ' time_step $end
$var reg 32 ( weight_in [31:0] $end
$scope module uut $end
$var wire 1 " clk $end
$var wire 1 # load $end
$var wire 1 $ mode $end
$var wire 1 % rst $end
$var wire 10 ) src_addr [9:0] $end
$var wire 1 ' time_step $end
$var wire 32 * weight_in [31:0] $end
$var reg 32 + accumulated_out [31:0] $end
$var reg 32 , accumulated_reg [31:0] $end
$var reg 1 - prev_load $end
$var reg 1 . prev_time_step_val $end
$var reg 5 / write_ptr [4:0] $end
$var integer 32 0 i [31:0] $end
$upscope $end
$upscope $end
$enddefinitions $end
$comment Show the parameter values. $end
$dumpall
$end
#0
$dumpvars
bx 0
bx /
x.
x-
bx ,
bx +
b0 *
b0 )
b0 (
0'
b0 &
1%
0$
0#
0"
bx !
$end
#50
b0 !
b0 +
b0 ,
0.
b0 /
0-
b10000 0
1"
#100
0"
0%
#150
b10000 0
1"
#200
0"
1$
#250
1"
#300
0"
b1 (
b1 *
b1 &
b1 )
1#
#350
b1 /
1-
1"
#400
0"
0#
#450
0-
1"
#500
0"
b10 (
b10 *
b10 &
b10 )
1#
#550
b10 /
1-
1"
#600
0"
0#
#650
0-
1"
#700
0"
b11 (
b11 *
b11 &
b11 )
1#
#750
b11 /
1-
1"
#800
0"
0#
#850
0-
1"
#900
0"
b100 (
b100 *
b100 &
b100 )
1#
#950
b100 /
1-
1"
#1000
0"
b0 (
b0 *
b0 &
b0 )
0#
1'
#1050
1.
0-
1"
#1100
0"
0'
#1150
0.
b10000 0
1"
0$
#1200
0"
#1250
b1 ,
b10000 0
1"
b1 &
b1 )
#1300
0"
#1350
b11 ,
b10000 0
1"
b10 &
b10 )
#1400
0"
#1450
b110 ,
b10000 0
1"
b11 &
b11 )
#1500
0"
1'
#1550
b10 ,
b110 !
b110 +
1.
b10000 0
1"
b10 &
b10 )
#1600
0"
0'
#1650
0.
b10000 0
1"
b0 &
b0 )
#1700
0"
#1750
b11 ,
b10000 0
1"
b1 &
b1 )
#1800
0"
#1850
b101 ,
b10000 0
1"
b10 &
b10 )
#1900
0"
#1950
b1000 ,
b10000 0
1"
b11 &
b11 )
#2000
0"
1'
#2050
b0 ,
b1000 !
b1000 +
1.
b10000 0
1"
b0 &
b0 )
#2100
0"
0'
#2150
0.
b10000 0
1"
#2200
0"
#2250
b10000 0
1"
#2300
0"
#2350
b10000 0
1"
#2400
0"
#2450
b10000 0
1"
#2500
0"
1'
#2550
b0 !
b0 +
1.
b10000 0
1"
#2600
0"
0'
#2650
0.
b10000 0
1"
#2700
0"
#2750
b10000 0
1"
#2800
0"
#2850
b10000 0
1"
#2900
0"
#2950
b10000 0
1"
#3000
0"
1'
#3050
1.
b10000 0
1"
#3100
0"
0'
#3150
0.
b10000 0
1"
